Workbook

Sheet 00_Leia-me
A1: MIP 12 x 12 do Piaui, 2018 - estoques mantidos na base
A3: Aba | B3: Conteudo
A4: 01_Recursos | B4: ENTRADA: bloco I da TRUR - producao, importacoes, margens e impostos
A5: 02_Usos | B5: ENTRADA: bloco II da TRUR - consumo intermediario e demanda final
A6: 03_VA | B6: ENTRADA: valor adicionado da TRUR e pessoal ocupado (fonte externa)
A7: 04_Conferencias | B7: Identidades contabeis da TRUR - ver a nota sobre a folga da fonte
A8: 05_ALFA | B8: Base de distribuicao (usos sem estoques) e matriz ALFA
A9: 06_M_comercio | B9: Margem de comercio embutida e a compensacao na linha do Comercio
A10: 07_M_transporte | B10: Margem de transporte embutida e a compensacao na linha do Transporte
A11: 08_M_impostos | B11: Base sem exportacao internacional e os impostos distribuidos
A12: 09_M_importacoes | B12: Base sem nenhuma exportacao e as importacoes (outras UFs e outros paises)
A13: 10_Usos_basicos | B13: Usos a precos de consumidor e, abaixo, a precos basicos
A14: 11_D | B14: Matriz D de participacao de mercado (atividade x produto)
... A24: 22_Simulacao | B24: Simulador simplificado de choque de demanda (conferencia com o site)
A26: Fonte: IBGE, Tabela de Recursos e Usos Regional (TRUR) 2018, Piaui (UF 22),
A27: nivel 12. Valores correntes em R$ 1 000 000. Metodologia de Guilhoto e
A28: Sesso Filho (2005).
A30: As abas 01 a 03 sao as unicas com numeros digitados; todas as demais sao
A31: formulas que referenciam as abas anteriores. Alterar uma celula de entrada
A32: recalcula a MIP inteira.
A34: ATENCAO - a TRUR publicada e arredondada e nao fecha exatamente: ha folga
A35: de balanceamento de ate ~0,24 (R$ milhao) em Transporte e ~-0,04 em
A36: Eletricidade e gas. Essa folga e da fonte, nao do metodo, e reaparece nos
A37: erros da aba 19_Diagnostico. Ver a aba 04_Conferencias.
A39: O pessoal ocupado da aba 03 NAO vem da TRUR: e dado externo de emprego,
A40: copiado de vale_perobelli/MIP2018PI_12s.xlsx.
... A57: Comparacao das tres: mippi18_excel/mippi18_excel_compara.R

Sheet 01_Recursos
A1: Codigo - Produto | B1: 01 - Agropecuária | C1: 02 - Indústrias extrativas | D1: 03 - Indústrias de transformação | E1: 04 - Eletricidade e gás, água, esgoto e gestão de resíduos | F1: 05 - Construção | G1: 06 - Comércio | H1: 07 - Transporte, armazenagem e correio | I1: 08 - Informação e comunicação | J1: 09 - Atividades financeiras, de seguros e serviços relacionados | K1: 10 - Atividades imobiliárias | L1: 11 - Outras atividades de serviços | M1: 12 - Administração, defesa, saúde e educação públicas e seguridade social | N1: Total das atividades | O1: Importacoes de outros paises | P1: Importacoes de outras UFs | Q1: Importacoes totais | R1: Oferta total a precos basicos | S1: Margem de comercio | T1: Margem de transporte | U1: Impostos liquidos sobre produtos | V1: Oferta total a precos de consumidor | W1: Producao do produto (soma das atividades)
A2: 01 - Agropecuária | B2: 7330.2675 | C2: 0 | D2: 0 | E2: 0 | F2: 0 | G2: 7.4694667 | H2: 1.9708127e-08 | I2: 0 | J2: 0 | K2: 0 | L2: 0 | M2: 9.760373 | N2: 7347.4974 | O2: 150.07679 | P2: 857.35858 | Q2: 1007.4354 | R2: 8354.9327 | S2: 821.81433 | T2: 115 | U2: 133.13959 | V2: 9424.8867 | W2: =SUM(B2:M2) -> 7347.4974
A3: 02 - Indústrias extrativas | B3: 1.6090295 | C3: 204.40492 | D3: 3.2644119 | E3: 0 | F3: 0 | G3: 0.026474143 | H3: 0 | I3: 0 | J3: 0 | K3: 0 | L3: 0 | M3: 0 | N3: 209.30483 | O3: 54.877082 | P3: 28.152058 | Q3: 83.02914 | R3: 292.33397 | S3: 44.972682 | T3: 53 | U3: 10.381149 | V3: 400.6878 | W3: =SUM(B3:M3) -> 209.30483
A4: 03 - Indústrias de transformação | B4: 203.43795 | C4: 5.3762232 | D4: 7957.9087 | E4: 0 | F4: 0.042203579 | G4: 329.33827 | H4: 2.717647e-08 | I4: 0 | J4: 0 | K4: 0 | L4: 4.9563603 | M4: 0 | N4: 8501.0597 | O4: 3703.1394 | P4: 20567.143 | Q4: 24270.282 | R4: 32771.342 | S4: 9823.7223 | T4: 409 | U4: 3787.1142 | V4: 46791.179 | W4: =SUM(B4:M4) -> 8501.0597
A5: 04 - Eletricidade e gás, água, esgoto e gestão de resíduos | B5: 0 | C5: 0 | D5: 0 | E5: 4035.2476 | F5: 0 | G5: 0 | H5: 0 | I5: 0 | J5: 0 | K5: 0 | L5: 0 | M5: 7.5659239 | N5: 4042.8136 | O5: 48.494222 | P5: 0 | Q5: 48.494222 | R5: 4091.3078 | S5: 12.447119 | T5: 0 | U5: 446.25606 | V5: 4550.011 | W5: =SUM(B5:M5) -> 4042.8136
A6: 05 - Construção | B6: 72.435669 | C6: 0 | D6: 0 | E6: 0 | F6: 5699.7469 | G6: 0 | H6: 0 | I6: 0 | J6: 0 | K6: 0 | L6: 0 | M6: 0 | N6: 5772.1826 | O6: 24.528287 | P6: 162.10475 | Q6: 186.63303 | R6: 5958.8156 | S6: 0 | T6: 0 | U6: 156.40671 | V6: 6115.2223 | W6: =SUM(B6:M6) -> 5772.1826
A7: 06 - Comércio | B7: 0 | C7: 0.15464855 | D7: 144.53766 | E7: 0 | F7: 0 | G7: 9502.032 | H7: 8.8637441 | I7: 0 | J7: 0 | K7: 0 | L7: 18.06034 | M7: 4.6352191 | N7: 9678.2836 | O7: 5.9770329 | P7: 1920.1044 | Q7: 1926.0814 | R7: 11604.365 | S7: -10795.132 | T7: 0 | U7: 7.9699169 | V7: 817.20285 | W7: =SUM(B7:M7) -> 9678.2836
A8: 07 - Transporte, armazenagem e correio | B8: 0 | C8: 0 | D8: 0 | E8: 0 | F8: 0 | G8: 10.119357 | H8: 2554.4041 | I8: 0 | J8: 0 | K8: 0 | L8: 0 | M8: 20.128201 | N8: 2584.6516 | O8: 101.34255 | P8: 669.19816 | Q8: 770.54071 | R8: 3355.1923 | S8: 0 | T8: -577 | U8: 155.83236 | V8: 2934.0247 | W8: =SUM(B8:M8) -> 2584.6516
A9: 08 - Informação e comunicação | B9: 0 | C9: 0 | D9: 0 | E9: 0 | F9: 0 | G9: 2.9691885 | H9: 0.723543 | I9: 1487.4989 | J9: 4.5618035 | K9: 0 | L9: 0.74261611 | M9: 2.7694278 | N9: 1499.2655 | O9: 107.67291 | P9: 301.76273 | Q9: 409.43564 | R9: 1908.7011 | S9: 92.175667 | T9: 0 | U9: 233.56792 | V9: 2234.4447 | W9: =SUM(B9:M9) -> 1499.2655
A10: 09 - Atividades financeiras, de seguros e serviços relacionados | B10: 0 | C10: 0 | D10: 0 | E10: 0 | F10: 0 | G10: 0 | H10: 0 | I10: 0 | J10: 2294.6362 | K10: 0 | L10: 0 | M10: 0 | N10: 2294.6362 | O10: 181.23458 | P10: 3363.8076 | Q10: 3545.0421 | R10: 5839.6784 | S10: 0 | T10: 0 | U10: 251.38189 | V10: 6091.0603 | W10: =SUM(B10:M10) -> 2294.6362
A11: 10 - Atividades imobiliárias | B11: 0.74844446 | C11: 0.37618642 | D11: 39.763046 | E11: 56.730129 | F11: 3.8716848 | G11: 35.862464 | H11: 8.2852157 | I11: 0.14100972 | J11: 42.153476 | K11: 4028.7338 | L11: 36.683971 | M11: 7.2273642 | N11: 4260.5768 | O11: 28.815291 | P11: 174.95249 | Q11: 203.76778 | R11: 4464.3446 | S11: 0 | T11: 0 | U11: 2.0969491 | V11: 4466.4416 | W11: =SUM(B11:M11) -> 4260.5768
A12: 11 - Outras atividades de serviços | B12: 0.28381577 | C12: 0 | D12: 0.13173536 | E12: 0.00042530854 | F12: 3.4308162 | G12: 64.207562 | H12: 81.278273 | I12: 0.11119788 | J12: 6.8485015 | K12: 0 | L12: 9488.5009 | M12: 285.73385 | N12: 9930.527 | O12: 868.58961 | P12: 4256.3662 | Q12: 5124.9558 | R12: 15055.483 | S12: 0 | T12: 0 | U12: 499.86888 | V12: 15555.352 | W12: =SUM(B12:M12) -> 9930.527
A13: 12 - Administração, defesa, saúde e educação públicas e seguridade social | B13: 0 | C13: 0 | D13: 0 | E13: 0 | F13: 0 | G13: 0 | H13: 0 | I13: 0 | J13: 0 | K13: 0 | L13: 0 | M13: 19314.545 | N13: 19314.545 | O13: 0 | P13: 422.67171 | Q13: 422.67171 | R13: 19737.217 | S13: 0 | T13: 0 | U13: 0 | V13: 19737.217 | W13: =SUM(B13:M13) -> 19314.545
A15: Total | B15: =SUM(B2:B13) -> 7608.7824 | C15: =SUM(C2:C13) -> 210.31198 | D15: =SUM(D2:D13) -> 8145.6056 | E15: =SUM(E2:E13) -> 4091.9782 | F15: =SUM(F2:F13) -> 5707.0916 | G15: =SUM(G2:G13) -> 9952.0248 | H15: =SUM(H2:H13) -> 2653.5548 | I15: =SUM(I2:I13) -> 1487.7511 | ... V15: =SUM(V2:V13) -> 119117.73

Sheet 02_Usos
A1: Codigo - Produto | B1: 01 - Agropecuária | C1: 02 - Indústrias extrativas | D1: 03 - Indústrias de transformação | E1: 04 - Eletricidade e gás, água, esgoto e gestão de resíduos | F1: 05 - Construção | G1: 06 - Comércio | H1: 07 - Transporte, armazenagem e correio | I1: 08 - Informação e comunicação | J1: 09 - Atividades financeiras, de seguros e serviços relacionados | K1: 10 - Atividades imobiliárias | L1: 11 - Outras atividades de serviços | M1: 12 - Administração, defesa, saúde e educação públicas e seguridade social | N1: Total das atividades | O1: Exportacoes outros paises | P1: Exportacoes outras UFs | Q1: Exportacoes totais | R1: Consumo do governo | S1: Consumo das familias | T1: Consumo das ISFLSF | U1: FBCF | V1: Variacao de estoques | W1: Demanda final | X1: Demanda total | Y1: CI do produto (soma das atividades)
A2: 01 - Agropecuária | B2: 336.52786 | C2: 0.011701408 | D2: 1591.7223 | E2: 0.26582577 | F2: 9.9470537 | G2: 63.939615 | H2: 0 | I2: 0 | J2: 0 | K2: 0 | L2: 67.900903 | M2: 45.176743 | N2: 2115.492 | O2: 2073.7754 | P2: 1269.6183 | Q2: 3343.3937 | R2: 1.2191883 | S2: 2973.5572 | T2: 0 | U2: 167.61783 | V2: 823.60672 | W2: 7309.3946 | X2: 9424.8867 | Y2: =SUM(B2:M2) -> 2115.492
A3: 02 - Indústrias extrativas | B3: 8.2404914 | C3: 4.6488867 | D3: 139.61354 | E3: 3.7427616 | F3: 94.724711 | G3: 0.50844481 | H3: 0.0042845705 | I3: 0 | J3: 0 | K3: 5.5097789 | L3: 0.3817976 | M3: 1.8826824 | N3: 259.25738 | O3: 3.3882649 | P3: 81.848675 | Q3: 85.23694 | R3: 0 | S3: 0 | T3: 0 | U3: 0 | V3: 56.193479 | W3: 141.43042 | X3: 400.6878 | Y3: =SUM(B3:M3) -> 259.25738
A4: 03 - Indústrias de transformação | B4: 2378.5487 | C4: 61.142098 | D4: 3685.8365 | E4: 427.4252 | F4: 2067.7679 | G4: 943.80323 | H4: 788.92036 | I4: 64.884884 | J4: 32.678772 | K4: 54.565436 | L4: 1245.9919 | M4: 994.02563 | N4: 12745.591 | O4: 546.53567 | P4: 5170.1451 | Q4: 5716.6808 | R4: 114.71822 | S4: 23647.917 | T4: 0 | U4: 2369.6669 | V4: 2196.6048 | W4: 34045.588 | X4: 46791.179 | Y4: =SUM(B4:M4) -> 12745.591
A5: 04 - Eletricidade e gás, água, esgoto e gestão de resíduos | B5: 154.80937 | C5: 7.900908 | D5: 136.96591 | E5: 1480.3103 | F5: 11.009585 | G5: 255.58089 | H5: 26.111449 | I5: 21.74082 | J5: 12.939323 | K5: 7.1191336 | L5: 216.79545 | M5: 382.08587 | N5: 2713.369 | O5: 0 | P5: 613.90952 | Q5: 613.90952 | R5: 0 | S5: 1221.0253 | T5: 0 | U5: 0 | V5: 1.671612 | W5: 1836.6065 | X5: 4549.9755 | Y5: =SUM(B5:M5) -> 2713.369
A6: 05 - Construção | B6: 3.8224895 | C6: 0.013787086 | D6: 2.264245 | E6: 79.02222 | F6: 705.14023 | G6: 11.177303 | H6: 8.3512823 | I6: 33.955801 | J6: 4.9087163 | K6: 10.536414 | L6: 24.851141 | M6: 362.99379 | N6: 1247.0374 | O6: 0 | P6: 0 | Q6: 0 | R6: 0 | S6: 0 | T6: 0 | U6: 4868.1849 | V6: 0 | W6: 4868.1849 | X6: 6115.2223 | Y6: =SUM(B6:M6) -> 1247.0374
A7: 06 - Comércio | B7: 4.0645391 | C7: 0.19920343 | D7: 78.202412 | E7: 12.218688 | F7: 5.2675482 | G7: 70.450246 | H7: 46.636504 | I7: 23.572888 | J7: 0.47196288 | K7: 0.125092 | L7: 12.265165 | M7: 53.081127 | N7: 306.55538 | O7: 26.994692 | P7: 0 | Q7: 26.994692 | R7: 0 | S7: 483.65278 | T7: 0 | U7: 0 | V7: 0 | W7: 510.64747 | X7: 817.20285 | Y7: =SUM(B7:M7) -> 306.55538
A8: 07 - Transporte, armazenagem e correio | B8: 112.1417 | C8: 6.233409 | D8: 405.32122 | E8: 22.46871 | F8: 35.013467 | G8: 475.61402 | H8: 304.93613 | I8: 11.000165 | J8: 27.967707 | K8: 1.895719 | L8: 133.12582 | M8: 205.00275 | N8: 1740.7208 | O8: 16 | P8: 0 | Q8: 16 | R8: 0 | S8: 1177.5397 | T8: 0 | U8: 0 | V8: 0 | W8: 1193.5397 | X8: 2934.2605 | Y8: =SUM(B8:M8) -> 1740.7208
A9: 08 - Informação e comunicação | B9: 0.61710297 | C9: 0.22864689 | D9: 48.77609 | E9: 41.137019 | F9: 16.744161 | G9: 154.23642 | H9: 31.785982 | I9: 261.46494 | J9: 105.33487 | K9: 5.9821949 | L9: 204.74525 | M9: 399.41456 | N9: 1270.4672 | O9: 2.6752358 | P9: 26.678261 | Q9: 29.353497 | R9: 0 | S9: 824.8463 | T9: 0 | U9: 110.23355 | V9: -0.45588277 | W9: 963.97747 | X9: 2234.4447 | Y9: =SUM(B9:M9) -> 1270.4672
A10: 09 - Atividades financeiras, de seguros e serviços relacionados | B10: 130.45603 | C10: 7.3087877 | D10: 183.00486 | E10: 130.82105 | F10: 96.771951 | G10: 246.23948 | H10: 71.125789 | I10: 66.780516 | J10: 366.11925 | K10: 153.22607 | L10: 148.85236 | M10: 670.49076 | N10: 2271.1969 | O10: 8.4055004 | P10: 0 | Q10: 8.4055004 | R10: 7.7394705 | S10: 3803.7186 | T10: 0 | U10: 0 | V10: 0 | W10: 3819.8635 | X10: 6091.0604 | Y10: =SUM(B10:M10) -> 2271.1969
A11: 10 - Atividades imobiliárias | B11: 0.23503353 | C11: 0.45746481 | D11: 21.746612 | E11: 23.239619 | F11: 13.560324 | G11: 369.93406 | H11: 45.167673 | I11: 25.297465 | J11: 22.641905 | K11: 12.590016 | L11: 189.57111 | M11: 52.578599 | N11: 777.01988 | O11: 0 | P11: 3.8794981 | Q11: 3.8794981 | R11: 0 | S11: 3685.5422 | T11: 0 | U11: 0 | V11: 0 | W11: 3689.4217 | X11: 4466.4416 | Y11: =SUM(B11:M11) -> 777.01988
A12: 11 - Outras atividades de serviços | B12: 42.118355 | C12: 12.527528 | D12: 458.77529 | E12: 286.22536 | F12: 178.98604 | G12: 998.8851 | H12: 184.47089 | I12: 338.46968 | J12: 261.46515 | K12: 34.804537 | L12: 903.45327 | M12: 1594.054 | N12: 5294.2352 | O12: 39.490348 | P12: 213.00548 | Q12: 252.49583 | R12: 564.58529 | S12: 8822.4347 | T12: 462.8832 | U12: 158.71751 | V12: 0 | W12: 10261.117 | X12: 15555.352 | Y12: =SUM(B12:M12) -> 5294.2352
A13: 12 - Administração, defesa, saúde e educação públicas e seguridade social | B13: 0 | C13: 0 | D13: 0 | E13: 0 | F13: 0 | G13: 0 | H13: 0 | I13: 0 | J13: 0 | K13: 0 | L13: 0 | M13: 0 | N13: 0 | O13: 0 | P13: 0 | Q13: 0 | R13: 19737.217 | S13: 0 | T13: 0 | U13: 0 | V13: 0 | W13: 19737.217 | X13: 19737.217 | Y13: =SUM(B13:M13) -> 0
A15: Total | B15: =SUM(B2:B13) -> 3171.5817 | C15: =SUM(C2:C13) -> 100.67242 | D15: =SUM(D2:D13) -> 6752.229 | E15: =SUM(E2:E13) -> 2506.8768 | F15: =SUM(F2:F13) -> 3234.9329 | G15: =SUM(G2:G13) -> 3590.3688 | H15: =SUM(H2:H13) -> 1507.5103 | I15: =SUM(I2:I13) -> 847.16715 | ... X15: =SUM(X2:X13) -> 119117.93

Sheet 03_VA
A1: Conta | B1: 01 - Agropecuária | C1: 02 - Indústrias extrativas | D1: 03 - Indústrias de transformação | E1: 04 - Eletricidade e gás, água, esgoto e gestão de resíduos | F1: 05 - Construção | G1: 06 - Comércio | H1: 07 - Transporte, armazenagem e correio | I1: 08 - Informação e comunicação | J1: 09 - Atividades financeiras, de seguros e serviços relacionados | K1: 10 - Atividades imobiliárias | L1: 11 - Outras atividades de serviços | M1: 12 - Administração, defesa, saúde e educação públicas e seguridade social | N1: Total | O1: PIB regional (TRUR)
A2: Valor adicionado bruto | B2: 4437.2008 | C2: 109.63955 | D2: 1393.3766 | E2: 1585.1014 | F2: 2472.1587 | G2: 6361.656 | H2: 1146.0445 | I2: 640.58395 | J2: 1513.6724 | K2: 3742.3795 | L2: 6401.0099 | M2: 14891.579 | N2: 44694.402 | O2: 50378.418
A3: Pessoal ocupado (dado externo - MIP2018PI_12s.xlsx, nao vem da TRUR) | B3: 243000 | C3: 1392 | D3: 65289 | E3: 4319 | F3: 94000 | G3: 259000 | H3: 47000 | I3: 35550 | J3: 33763 | K3: 12688 | L3: 192000 | M3: 240000
A5: Valor adicionado bruto (total) | B5: =N2 -> 44694.402
A6: Impostos liquidos sobre produtos | B6: ='01_Recursos'!$U$15 -> 5684.0156
A7: PIB = VA + impostos | B7: =B5+B6 -> 50378.418
A8: PIB regional publicado na TRUR | B8: =O2 -> 50378.418
A9: Diferenca | B9: =B7-B8 -> 0

Sheet 04_Conferencias
A1: ETAPA 6 - identidades da TRUR
A2: Identidade | B2: Erro maximo | C2: Tipo
A3: Producao do produto = soma das atividades que o produzem | B3: {=MAX(ABS('01_Recursos'!$N$2:$N$13-'01_Recursos'!$W$2:$W$13))} -> 9.094947e-12 | C3: formula de matriz
A4: Importacao total = outros paises + outras UFs | B4: {=MAX(ABS('01_Recursos'!$Q$2:$Q$13-('01_Recursos'!$O$2:$O$13+'01_Recursos'!$P$2:$P$13)))} -> 4.0017767e-11 | C4: formula de matriz
A5: Oferta a precos basicos = producao + importacao total | B5: {=MAX(ABS('01_Recursos'!$R$2:$R$13-('01_Recursos'!$N$2:$N$13+'01_Recursos'!$Q$2:$Q$13)))} -> 8.0035534e-11 | C5: formula de matriz
A6: Oferta a precos de consumidor = basico + margens + impostos | B6: {=MAX(ABS('01_Recursos'!$V$2:$V$13-('01_Recursos'!$R$2:$R$13+'01_Recursos'!$S$2:$S$13+'01_Recursos'!$T$2:$T$13+'01_Recursos'!$U$2:$U$13)))} -> 6.9235284e-11 | C6: formula de matriz
A7: Exportacao total = outros paises + outras UFs | B7: {=MAX(ABS('02_Usos'!$Q$2:$Q$13-('02_Usos'!$O$2:$O$13+'02_Usos'!$P$2:$P$13)))} -> 2.7284841e-12 | C7: formula de matriz
A8: CI do produto = soma das atividades que o consomem | B8: {=MAX(ABS('02_Usos'!$N$2:$N$13-'02_Usos'!$Y$2:$Y$13))} -> 4.1836756e-11 | C8: formula de matriz
A9: Demanda final = exportacao total + os 5 demais componentes | B9: {=MAX(ABS('02_Usos'!$W$2:$W$13-('02_Usos'!$Q$2:$Q$13+'02_Usos'!$R$2:$R$13+'02_Usos'!$S$2:$S$13+'02_Usos'!$T$2:$T$13+'02_Usos'!$U$2:$U$13+'02_Usos'!$V$2:$V$13)))} -> 9.094947e-12 | C9: formula de matriz
A10: Demanda total = CI total + demanda final | B10: {=MAX(ABS('02_Usos'!$X$2:$X$13-('02_Usos'!$N$2:$N$13+'02_Usos'!$W$2:$W$13)))} -> 2.0008883e-11 | C10: formula de matriz
A11: Soma da coluna de margem de comercio = 0 | B11: =ABS(SUM('01_Recursos'!$S$2:$S$13)) -> 3.1349146e-11 | C11: formula comum
A12: Soma da coluna de margem de transporte = 0 | B12: =ABS(SUM('01_Recursos'!$T$2:$T$13)) -> 0 | C12: formula comum
A13: Valor adicionado = producao da atividade - CI a precos de consumidor | B13: {=MAX(ABS('03_VA'!$B$2:$M$2-('01_Recursos'!$B$15:$M$15-'02_Usos'!$B$15:$M$15)))} -> 1.2732926e-11 | C13: formula de matriz
A15: Folga da TRUR: demanda total - oferta a precos de consumidor
A16: (diferenca da fonte publicada, nao do metodo)
A17: 01 - Agropecuária | B17: ='02_Usos'!$X$2-'01_Recursos'!$V$2 -> 0
A18: 02 - Indústrias extrativas | B18: ='02_Usos'!$X$3-'01_Recursos'!$V$3 -> 0
A19: 03 - Indústrias de transformação | B19: ='02_Usos'!$X$4-'01_Recursos'!$V$4 -> -1.0186341e-10
A20: 04 - Eletricidade e gás, água, esgoto e gestão de resíduos | B20: ='02_Usos'!$X$5-'01_Recursos'!$V$5 -> -0.035464606
A21: 05 - Construção | B21: ='02_Usos'!$X$6-'01_Recursos'!$V$6 -> 0
A22: 06 - Comércio | B22: ='02_Usos'!$X$7-'01_Recursos'!$V$7 -> -1.9326762e-12
A23: 07 - Transporte, armazenagem e correio | B23: ='02_Usos'!$X$8-'01_Recursos'!$V$8 -> 0.23582886
A24: 08 - Informação e comunicação | B24: ='02_Usos'!$X$9-'01_Recursos'!$V$9 -> 0
A25: 09 - Atividades financeiras, de seguros e serviços relacionados | B25: ='02_Usos'!$X$10-'01_Recursos'!$V$10 -> 0.00017510846
A26: 10 - Atividades imobiliárias | B26: ='02_Usos'!$X$11-'01_Recursos'!$V$11 -> 0
A27: 11 - Outras atividades de serviços | B27: ='02_Usos'!$X$12-'01_Recursos'!$V$12 -> 0
A28: 12 - Administração, defesa, saúde e educação públicas e seguridade social | B28: ='02_Usos'!$X$13-'01_Recursos'!$V$13 -> 8.0035534e-10

Sheet 05_ALFA
A1: ETAPA 8a - base das margens: sem excluir nenhuma coluna
A2: Produto \ Destino | B2: 01 - Agropecuária | C2: 02 - Indústrias extrativas | D2: 03 - Indústrias de transformação | E2: 04 - Eletricidade e gás, água, esgoto e gestão de resíduos | F2: 05 - Construção | G2: 06 - Comércio | H2: 07 - Transporte, armazenagem e correio | I2: 08 - Informação e comunicação | J2: 09 - Atividades financeiras, de seguros e serviços relacionados | K2: 10 - Atividades imobiliárias | L2: 11 - Outras atividades de serviços | M2: 12 - Administração, defesa, saúde e educação públicas e seguridade social | N2: Exportacoes outros paises | O2: Exportacoes outras UFs | P2: Consumo do governo | Q2: Consumo das familias | R2: Consumo das ISFLSF | S2: FBCF | T2: Variacao de estoques | U2: Total do produto
A3: 01 - Agropecuária | B3: ='02_Usos'!$B$2 -> 336.52786 | C3: ='02_Usos'!$C$2 -> 0.011701408 | D3: ='02_Usos'!$D$2 -> 1591.7223 | E3: ='02_Usos'!$E$2 -> 0.26582577 | F3: ='02_Usos'!$F$2 -> 9.9470537 | G3: ='02_Usos'!$G$2 -> 63.939615 | H3: ='02_Usos'!$H$2 -> 0 | I3: ='02_Usos'!$I$2 -> 0 | J3: ='02_Usos'!$J$2 -> 0 | K3: ='02_Usos'!$K$2 -> 0 | L3: ='02_Usos'!$L$2 -> 67.900903 | M3: ='02_Usos'!$M$2 -> 45.176743 | N3: ='02_Usos'!$O$2 -> 2073.7754 | O3: ='02_Usos'!$P$2 -> 1269.6183 | P3: ='02_Usos'!$R$2 -> 1.2191883 | Q3: ='02_Usos'!$S$2 -> 2973.5572 | R3: ='02_Usos'!$T$2 -> 0 | S3: ='02_Usos'!$U$2 -> 167.61783 | T3: ='02_Usos'!$V$2 -> 823.60672 | U3: =SUM(B3:T3) -> 9424.8867
A4: 02 - Indústrias extrativas | B4: ='02_Usos'!$B$3 -> 8.2404914 | C4: ='02_Usos'!$C$3 -> 4.6488867 | D4: ='02_Usos'!$D$3 -> 139.61354 | E4: ='02_Usos'!$E$3 -> 3.7427616 | F4: ='02_Usos'!$F$3 -> 94.724711 | G4: ='02_Usos'!$G$3 -> 0.50844481 | H4: ='02_Usos'!$H$3 -> 0.0042845705 | I4: ='02_Usos'!$I$3 -> 0 | J4: ='02_Usos'!$J$3 -> 0 | K4: ='02_Usos'!$K$3 -> 5.5097789 | L4: ='02_Usos'!$L$3 -> 0.3817976 | M4: ='02_Usos'!$M$3 -> 1.8826824 | N4: ='02_Usos'!$O$3 -> 3.3882649 | O4: ='02_Usos'!$P$3 -> 81.848675 | P4: ='02_Usos'!$R$3 -> 0 | Q4: ='02_Usos'!$S$3 -> 0 | R4: ='02_Usos'!$T$3 -> 0 | S4: ='02_Usos'!$U$3 -> 0 | T4: ='02_Usos'!$V$3 -> 56.193479 | U4: =SUM(B4:T4) -> 400.6878
A5: 03 - Indústrias de transformação | B5: ='02_Usos'!$B$4 -> 2378.5487 | C5: ='02_Usos'!$C$4 -> 61.142098 | D5: ='02_Usos'!$D$4 -> 3685.8365 | E5: ='02_Usos'!$E$4 -> 427.4252 | F5: ='02_Usos'!$F$4 -> 2067.7679 | G5: ='02_Usos'!$G$4 -> 943.80323 | H5: ='02_Usos'!$H$4 -> 788.92036 | I5: ='02_Usos'!$I$4 -> 64.884884 | J5: ='02_Usos'!$J$4 -> 32.678772 | K5: ='02_Usos'!$K$4 -> 54.565436 | L5: ='02_Usos'!$L$4 -> 1245.9919 | M5: ='02_Usos'!$M$4 -> 994.02563 | N5: ='02_Usos'!$O$4 -> 546.53567 | O5: ='02_Usos'!$P$4 -> 5170.1451 | P5: ='02_Usos'!$R$4 -> 114.71822 | Q5: ='02_Usos'!$S$4 -> 23647.917 | R5: ='02_Usos'!$T$4 -> 0 | S5: ='02_Usos'!$U$4 -> 2369.6669 | T5: ='02_Usos'!$V$4 -> 2196.6048 | U5: =SUM(B5:T5) -> 46791.179
A6: 04 - Eletricidade e gás, água, esgoto e gestão de resíduos | B6: ='02_Usos'!$B$5 -> 154.80937 | C6: ='02_Usos'!$C$5 -> 7.900908 | D6: ='02_Usos'!$D$5 -> 136.96591 | E6: ='02_Usos'!$E$5 -> 1480.3103 | F6: ='02_Usos'!$F$5 -> 11.009585 | G6: ='02_Usos'!$G$5 -> 255.58089 | H6: ='02_Usos'!$H$5 -> 26.111449 | I6: ='02_Usos'!$I$5 -> 21.74082 | J6: ='02_Usos'!$J$5 -> 12.939323 | K6: ='02_Usos'!$K$5 -> 7.1191336 | L6: ='02_Usos'!$L$5 -> 216.79545 | M6: ='02_Usos'!$M$5 -> 382.08587 | N6: ='02_Usos'!$O$5 -> 0 | O6: ='02_Usos'!$P$5 -> 613.90952 | P6: ='02_Usos'!$R$5 -> 0 | Q6: ='02_Usos'!$S$5 -> 1221.0253 | R6: ='02_Usos'!$T$5 -> 0 | S6: ='02_Usos'!$U$5 -> 0 | T6: ='02_Usos'!$V$5 -> 1.671612 | U6: =SUM(B6:T6) -> 4549.9755
A7: 05 - Construção | B7: ='02_Usos'!$B$6 -> 3.8224895 | C7: ='02_Usos'!$C$6 -> 0.013787086 | D7: ='02_Usos'!$D$6 -> 2.264245 | E7: ='02_Usos'!$E$6 -> 79.02222 | F7: ='02_Usos'!$F$6 -> 705.14023 | G7: ='02_Usos'!$G$6 -> 11.177303 | H7: ='02_Usos'!$H$6 -> 8.3512823 | I7: ='02_Usos'!$I$6 -> 33.955801 | J7: ='02_Usos'!$J$6 -> 4.9087163 | K7: ='02_Usos'!$K$6 -> 10.536414 | L7: ='02_Usos'!$L$6 -> 24.851141 | M7: ='02_Usos'!$M$6 -> 362.99379 | N7: ='02_Usos'!$O$6 -> 0 | O7: ='02_Usos'!$P$6 -> 0 | P7: ='02_Usos'!$R$6 -> 0 | Q7: ='02_Usos'!$S$6 -> 0 | R7: ='02_Usos'!$T$6 -> 0 | S7: ='02_Usos'!$U$6 -> 4868.1849 | T7: ='02_Usos'!$V$6 -> 0 | U7: =SUM(B7:T7) -> 6115.2223
A8: 06 - Comércio | B8: ='02_Usos'!$B$7 -> 4.0645391 | C8: ='02_Usos'!$C$7 -> 0.19920343 | D8: ='02_Usos'!$D$7 -> 78.202412 | E8: ='02_Usos'!$E$7 -> 12.218688 | F8: ='02_Usos'!$F$7 -> 5.2675482 | G8: ='02_Usos'!$G$7 -> 70.450246 | H8: ='02_Usos'!$H$7 -> 46.636504 | I8: ='02_Usos'!$I$7 -> 23.572888 | J8: ='02_Usos'!$J$7 -> 0.47196288 | K8: ='02_Usos'!$K$7 -> 0.125092 | L8: ='02_Usos'!$L$7 -> 12.265165 | M8: ='02_Usos'!$M$7 -> 53.081127 | N8: ='02_Usos'!$O$7 -> 26.994692 | O8: ='02_Usos'!$P$7 -> 0 | P8: ='02_Usos'!$R$7 -> 0 | Q8: ='02_Usos'!$S$7 -> 483.65278 | R8: ='02_Usos'!$T$7 -> 0 | S8: ='02_Usos'!$U$7 -> 0 | T8: ='02_Usos'!$V$7 -> 0 | U8: =SUM(B8:T8) -> 817.20285
A9: 07 - Transporte, armazenagem e correio | B9: ='02_Usos'!$B$8 -> 112.1417 | C9: ='02_Usos'!$C$8 -> 6.233409 | D9: ='02_Usos'!$D$8 -> 405.32122 | E9: ='02_Usos'!$E$8 -> 22.46871 | F9: ='02_Usos'!$F$8 -> 35.013467 | G9: ='02_Usos'!$G$8 -> 475.61402 | H9: ='02_Usos'!$H$8 -> 304.93613 | I9: ='02_Usos'!$I$8 -> 11.000165 | J9: ='02_Usos'!$J$8 -> 27.967707 | K9: ='02_Usos'!$K$8 -> 1.895719 | L9: ='02_Usos'!$L$8 -> 133.12582 | M9: ='02_Usos'!$M$8 -> 205.00275 | N9: ='02_Usos'!$O$8 -> 16 | O9: ='02_Usos'!$P$8 -> 0 | P9: ='02_Usos'!$R$8 -> 0 | Q9: ='02_Usos'!$S$8 -> 1177.5397 | R9: ='02_Usos'!$T$8 -> 0 | S9: ='02_Usos'!$U$8 -> 0 | T9: ='02_Usos'!$V$8 -> 0 | U9: =SUM(B9:T9) -> 2934.2605
A10: 08 - Informação e comunicação | B10: ='02_Usos'!$B$9 -> 0.61710297 | C10: ='02_Usos'!$C$9 -> 0.22864689 | D10: ='02_Usos'!$D$9 -> 48.77609 | E10: ='02_Usos'!$E$9 -> 41.137019 | F10: ='02_Usos'!$F$9 -> 16.744161 | G10: ='02_Usos'!$G$9 -> 154.23642 | H10: ='02_Usos'!$H$9 -> 31.785982 | I10: ='02_Usos'!$I$9 -> 261.46494 | J10: ='02_Usos'!$J$9 -> 105.33487 | K10: ='02_Usos'!$K$9 -> 5.9821949 | L10: ='02_Usos'!$L$9 -> 204.74525 | M10: ='02_Usos'!$M$9 -> 399.41456 | N10: ='02_Usos'!$O$9 -> 2.6752358 | O10: ='02_Usos'!$P$9 -> 26.678261 | P10: ='02_Usos'!$R$9 -> 0 | Q10: ='02_Usos'!$S$9 -> 824.8463 | R10: ='02_Usos'!$T$9 -> 0 | S10: ='02_Usos'!$U$9 -> 110.23355 | T10: ='02_Usos'!$V$9 -> -0.45588277 | U10: =SUM(B10:T10) -> 2234.4447
A11: 09 - Atividades financeiras, de seguros e serviços relacionados | B11: ='02_Usos'!$B$10 -> 130.45603 | C11: ='02_Usos'!$C$10 -> 7.3087877 | D11: ='02_Usos'!$D$10 -> 183.00486 | E11: ='02_Usos'!$E$10 -> 130.82105 | F11: ='02_Usos'!$F$10 -> 96.771951 | G11: ='02_Usos'!$G$10 -> 246.23948 | H11: ='02_Usos'!$H$10 -> 71.125789 | I11: ='02_Usos'!$I$10 -> 66.780516 | J11: ='02_Usos'!$J$10 -> 366.11925 | K11: ='02_Usos'!$K$10 -> 153.22607 | L11: ='02_Usos'!$L$10 -> 148.85236 | M11: ='02_Usos'!$M$10 -> 670.49076 | N11: ='02_Usos'!$O$10 -> 8.4055004 | O11: ='02_Usos'!$P$10 -> 0 | P11: ='02_Usos'!$R$10 -> 7.7394705 | Q11: ='02_Usos'!$S$10 -> 3803.7186 | R11: ='02_Usos'!$T$10 -> 0 | S11: ='02_Usos'!$U$10 -> 0 | T11: ='02_Usos'!$V$10 -> 0 | U11: =SUM(B11:T11) -> 6091.0604
A12: 10 - Atividades imobiliárias | B12: ='02_Usos'!$B$11 -> 0.23503353 | C12: ='02_Usos'!$C$11 -> 0.45746481 | D12: ='02_Usos'!$D$11 -> 21.746612 | E12: ='02_Usos'!$E$11 -> 23.239619 | F12: ='02_Usos'!$F$11 -> 13.560324 | G12: ='02_Usos'!$G$11 -> 369.93406 | H12: ='02_Usos'!$H$11 -> 45.167673 | I12: ='02_Usos'!$I$11 -> 25.297465 | J12: ='02_Usos'!$J$11 -> 22.641905 | K12: ='02_Usos'!$K$11 -> 12.590016 | L12: ='02_Usos'!$L$11 -> 189.57111 | M12: ='02_Usos'!$M$11 -> 52.578599 | N12: ='02_Usos'!$O$11 -> 0 | O12: ='02_Usos'!$P$11 -> 3.8794981 | P12: ='02_Usos'!$R$11 -> 0 | Q12: ='02_Usos'!$S$11 -> 3685.5422 | R12: ='02_Usos'!$T$11 -> 0 | S12: ='02_Usos'!$U$11 -> 0 | T12: ='02_Usos'!$V$11 -> 0 | U12: =SUM(B12:T12) -> 4466.4416
A13: 11 - Outras atividades de serviços | B13: ='02_Usos'!$B$12 -> 42.118355 | C13: ='02_Usos'!$C$12 -> 12.527528 | D13: ='02_Usos'!$D$12 -> 458.77529 | E13: ='02_Usos'!$E$12 -> 286.22536 | F13: ='02_Usos'!$F$12 -> 178.98604 | G13: ='02_Usos'!$G$12 -> 998.8851 | H13: ='02_Usos'!$H$12 -> 184.47089 | I13: ='02_Usos'!$I$12 -> 338.46968 | J13: ='02_Usos'!$J$12 -> 261.46515 | K13: ='02_Usos'!$K$12 -> 34.804537 | L13: ='02_Usos'!$L$12 -> 903.45327 | M13: ='02_Usos'!$M$12 -> 1594.054 | N13: ='02_Usos'!$O$12 -> 39.490348 | O13: ='02_Usos'!$P$12 -> 213.00548 | P13: ='02_Usos'!$R$12 -> 564.58529 | Q13: ='02_Usos'!$S$12 -> 8822.4347 | R13: ='02_Usos'!$T$12 -> 462.8832 | S13: ='02_Usos'!$U$12 -> 158.71751 | T13: ='02_Usos'!$V$12 -> 0 | U13: =SUM(B13:T13) -> 15555.352
A14: 12 - Administração, defesa, saúde e educação públicas e seguridade social | B14: ='02_Usos'!$B$13 -> 0 | C14: ='02_Usos'!$C$13 -> 0 | D14: ='02_Usos'!$D$13 -> 0 | E14: ='02_Usos'!$E$13 -> 0 | F14: ='02_Usos'!$F$13 -> 0 | G14: ='02_Usos'!$G$13 -> 0 | H14: ='02_Usos'!$H$13 -> 0 | I14: ='02_Usos'!$I$13 -> 0 | J14: ='02_Usos'!$J$13 -> 0 | K14: ='02_Usos'!$K$13 -> 0 | L14: ='02_Usos'!$L$13 -> 0 | M14: ='02_Usos'!$M$13 -> 0 | N14: ='02_Usos'!$O$13 -> 0 | O14: ='02_Usos'!$P$13 -> 0 | P14: ='02_Usos'!$R$13 -> 19737.217 | Q14: ='02_Usos'!$S$13 -> 0 | R14: ='02_Usos'!$T$13 -> 0 | S14: ='02_Usos'!$U$13 -> 0 | T14: ='02_Usos'!$V$13 -> 0 | U14: =SUM(B14:T14) -> 19737.217
A16: ETAPA 8b - ALFA: cada celula dividida pelo total do produto
A17: Produto \ Destino | B17: 01 - Agropecuária | C17: 02 - Indústrias extrativas | D17: 03 - Indústrias de transformação | E17: 04 - Eletricidade e gás, água, esgoto e gestão de resíduos | F17: 05 - Construção | G17: 06 - Comércio | H17: 07 - Transporte, armazenagem e correio | I17: 08 - Informação e comunicação | J17: 09 - Atividades financeiras, de seguros e serviços relacionados | K17: 10 - Atividades imobiliárias | L17: 11 - Outras atividades de serviços | M17: 12 - Administração, defesa, saúde e educação públicas e seguridade social | N17: Exportacoes outros paises | O17: Exportacoes outras UFs | P17: Consumo do governo | Q17: Consumo das familias | R17: Consumo das ISFLSF | S17: FBCF | T17: Variacao de estoques | U17: Soma da linha (deve ser 1)
A18: 01 - Agropecuária | B18: =IF($U$3=0,0,B$3/$U$3) -> 0.035706303 | C18: =IF($U$3=0,0,C$3/$U$3) -> 1.2415437e-06 | D18: =IF($U$3=0,0,D$3/$U$3) -> 0.16888504 | E18: =IF($U$3=0,0,E$3/$U$3) -> 2.8204665e-05 | F18: =IF($U$3=0,0,F$3/$U$3) -> 0.001055403 | G18: =IF($U$3=0,0,G$3/$U$3) -> 0.0067841256 | H18: =IF($U$3=0,0,H$3/$U$3) -> 0 | I18: =IF($U$3=0,0,I$3/$U$3) -> 0 | ... T18: =IF($U$3=0,0,T$3/$U$3) -> 0.087386379 | U18: =SUM(B18:T18) -> 1
A19: 02 - Indústrias extrativas | B19: =IF($U$4=0,0,B$4/$U$4) -> 0.020565865 | C19: =IF($U$4=0,0,C$4/$U$4) -> 0.011602267 | D19: =IF($U$4=0,0,D$4/$U$4) -> 0.34843473 | E19: =IF($U$4=0,0,E$4/$U$4) -> 0.0093408424 | F19: =IF($U$4=0,0,F$4/$U$4) -> 0.23640528 | G19: =IF($U$4=0,0,G$4/$U$4) -> 0.0012689301 | H19: =IF($U$4=0,0,H$4/$U$4) -> 1.069304e-05 | I19: =IF($U$4=0,0,I$4/$U$4) -> 0 | ... T19: =IF($U$4=0,0,T$4/$U$4) -> 0.14024255 | U19: =SUM(B19:T19) -> 1
A20: 03 - Indústrias de transformação | B20: =IF($U$5=0,0,B$5/$U$5) -> 0.050833272 | C20: =IF($U$5=0,0,C$5/$U$5) -> 0.0013067014 | D20: =IF($U$5=0,0,D$5/$U$5) -> 0.078772037 | E20: =IF($U$5=0,0,E$5/$U$5) -> 0.0091347389 | F20: =IF($U$5=0,0,F$5/$U$5) -> 0.044191404 | G20: =IF($U$5=0,0,G$5/$U$5) -> 0.020170538 | H20: =IF($U$5=0,0,H$5/$U$5) -> 0.016860451 | I20: =IF($U$5=0,0,I$5/$U$5) -> 0.0013866905 | ... T20: =IF($U$5=0,0,T$5/$U$5) -> 0.046944849 | U20: =SUM(B20:T20) -> 1
A21: 04 - Eletricidade e gás, água, esgoto e gestão de resíduos | B21: =IF($U$6=0,0,B$6/$U$6) -> 0.03402422 | C21: =IF($U$6=0,0,C$6/$U$6) -> 0.0017364727 | D21: =IF($U$6=0,0,D$6/$U$6) -> 0.030102561 | E21: =IF($U$6=0,0,E$6/$U$6) -> 0.32534468 | F21: =IF($U$6=0,0,F$6/$U$6) -> 0.0024197021 | G21: =IF($U$6=0,0,G$6/$U$6) -> 0.056171928 | H21: =IF($U$6=0,0,H$6/$U$6) -> 0.0057388108 | I21: =IF($U$6=0,0,I$6/$U$6) -> 0.0047782279 | ... T21: =IF($U$6=0,0,T$6/$U$6) -> 0.00036738923 | U21: =SUM(B21:T21) -> 1
A22: 05 - Construção | B22: =IF($U$7=0,0,B$7/$U$7) -> 0.00062507776 | C22: =IF($U$7=0,0,C$7/$U$7) -> 2.2545518e-06 | D22: =IF($U$7=0,0,D$7/$U$7) -> 0.00037026373 | E22: =IF($U$7=0,0,E$7/$U$7) -> 0.012922215 | F22: =IF($U$7=0,0,F$7/$U$7) -> 0.11530901 | G22: =IF($U$7=0,0,G$7/$U$7) -> 0.0018277835 | H22: =IF($U$7=0,0,H$7/$U$7) -> 0.0013656547 | I22: =IF($U$7=0,0,I$7/$U$7) -> 0.0055526682 | ... T22: =IF($U$7=0,0,T$7/$U$7) -> 0 | U22: =SUM(B22:T22) -> 1
A23: 06 - Comércio | B23: =IF($U$8=0,0,B$8/$U$8) -> 0.0049737211 | C23: =IF($U$8=0,0,C$8/$U$8) -> 0.00024376253 | D23: =IF($U$8=0,0,D$8/$U$8) -> 0.095695227 | E23: =IF($U$8=0,0,E$8/$U$8) -> 0.014951842 | F23: =IF($U$8=0,0,F$8/$U$8) -> 0.006445827 | G23: =IF($U$8=0,0,G$8/$U$8) -> 0.086209007 | H23: =IF($U$8=0,0,H$8/$U$8) -> 0.057068455 | I23: =IF($U$8=0,0,I$8/$U$8) -> 0.028845822 | ... T23: =IF($U$8=0,0,T$8/$U$8) -> 0 | U23: =SUM(B23:T23) -> 1
A24: 07 - Transporte, armazenagem e correio | B24: =IF($U$9=0,0,B$9/$U$9) -> 0.038218044 | C24: =IF($U$9=0,0,C$9/$U$9) -> 0.0021243543 | D24: =IF($U$9=0,0,D$9/$U$9) -> 0.13813403 | E24: =IF($U$9=0,0,E$9/$U$9) -> 0.0076573671 | F24: =IF($U$9=0,0,F$9/$U$9) -> 0.011932637 | G24: =IF($U$9=0,0,G$9/$U$9) -> 0.16208991 | H24: =IF($U$9=0,0,H$9/$U$9) -> 0.10392265 | I24: =IF($U$9=0,0,I$9/$U$9) -> 0.0037488712 | ... T24: =IF($U$9=0,0,T$9/$U$9) -> 0 | U24: =SUM(B24:T24) -> 1
A25: 08 - Informação e comunicação | B25: =IF($U$10=0,0,B$10/$U$10) -> 0.00027617733 | C25: =IF($U$10=0,0,C$10/$U$10) -> 0.00010232828 | D25: =IF($U$10=0,0,D$10/$U$10) -> 0.021829178 | E25: =IF($U$10=0,0,E$10/$U$10) -> 0.018410399 | F25: =IF($U$10=0,0,F$10/$U$10) -> 0.0074936563 | G25: =IF($U$10=0,0,G$10/$U$10) -> 0.069026736 | H25: =IF($U$10=0,0,H$10/$U$10) -> 0.01422545 | I25: =IF($U$10=0,0,I$10/$U$10) -> 0.11701562 | ... T25: =IF($U$10=0,0,T$10/$U$10) -> -0.00020402509 | U25: =SUM(B25:T25) -> 1
A26: 09 - Atividades financeiras, de seguros e serviços relacionados | B26: =IF($U$11=0,0,B$11/$U$11) -> 0.021417622 | C26: =IF($U$11=0,0,C$11/$U$11) -> 0.0011999204 | D26: =IF($U$11=0,0,D$11/$U$11) -> 0.030044828 | E26: =IF($U$11=0,0,E$11/$U$11) -> 0.021477548 | F26: =IF($U$11=0,0,F$11/$U$11) -> 0.015887537 | G26: =IF($U$11=0,0,G$11/$U$11) -> 0.040426372 | H26: =IF($U$11=0,0,H$11/$U$11) -> 0.011677078 | I26: =IF($U$11=0,0,I$11/$U$11) -> 0.010963693 | ... T26: =IF($U$11=0,0,T$11/$U$11) -> 0 | U26: =SUM(B26:T26) -> 1
A27: 10 - Atividades imobiliárias | B27: =IF($U$12=0,0,B$12/$U$12) -> 5.2622099e-05 | C27: =IF($U$12=0,0,C$12/$U$12) -> 0.00010242266 | D27: =IF($U$12=0,0,D$12/$U$12) -> 0.0048688898 | E27: =IF($U$12=0,0,E$12/$U$12) -> 0.005203162 | F27: =IF($U$12=0,0,F$12/$U$12) -> 0.0030360464 | G27: =IF($U$12=0,0,G$12/$U$12) -> 0.082825231 | H27: =IF($U$12=0,0,H$12/$U$12) -> 0.010112675 | I27: =IF($U$12=0,0,I$12/$U$12) -> 0.005663897 | ... T27: =IF($U$12=0,0,T$12/$U$12) -> 0 | U27: =SUM(B27:T27) -> 1
A28: 11 - Outras atividades de serviços | B28: =IF($U$13=0,0,B$13/$U$13) -> 0.002707644 | C28: =IF($U$13=0,0,C$13/$U$13) -> 0.00080535166 | D28: =IF($U$13=0,0,D$13/$U$13) -> 0.029493084 | E28: =IF($U$13=0,0,E$13/$U$13) -> 0.018400443 | F28: =IF($U$13=0,0,F$13/$U$13) -> 0.011506396 | G28: =IF($U$13=0,0,G$13/$U$13) -> 0.064214884 | H28: =IF($U$13=0,0,H$13/$U$13) -> 0.011858998 | I28: =IF($U$13=0,0,I$13/$U$13) -> 0.02175905 | ... T28: =IF($U$13=0,0,T$13/$U$13) -> 0 | U28: =SUM(B28:T28) -> 1
A29: 12 - Administração, defesa, saúde e educação públicas e seguridade social | B29: =IF($U$14=0,0,B$14/$U$14) -> 0 | C29: =IF($U$14=0,0,C$14/$U$14) -> 0 | D29: =IF($U$14=0,0,D$14/$U$14) -> 0 | E29: =IF($U$14=0,0,E$14/$U$14) -> 0 | F29: =IF($U$14=0,0,F$14/$U$14) -> 0 | G29: =IF($U$14=0,0,G$14/$U$14) -> 0 | H29: =IF($U$14=0,0,H$14/$U$14) -> 0 | I29: =IF($U$14=0,0,I$14/$U$14) -> 0 | ... T29: =IF($U$14=0,0,T$14/$U$14) -> 0 | U29: =SUM(B29:T29) -> 1

Sheet 06_M_comercio
A1: ETAPA 9a - margem de Comercio embutida em cada celula (ALFA x margem do produto)
A2: Produto \ Destino | B2: 01 - Agropecuária | C2: 02 - Indústrias extrativas | D2: 03 - Indústrias de transformação | E2: 04 - Eletricidade e gás, água, esgoto e gestão de resíduos | F2: 05 - Construção | G2: 06 - Comércio | H2: 07 - Transporte, armazenagem e correio | I2: 08 - Informação e comunicação | J2: 09 - Atividades financeiras, de seguros e serviços relacionados | K2: 10 - Atividades imobiliárias | L2: 11 - Outras atividades de serviços | M2: 12 - Administração, defesa, saúde e educação públicas e seguridade social | N2: Exportacoes outros paises | O2: Exportacoes outras UFs | P2: Consumo do governo | Q2: Consumo das familias | R2: Consumo das ISFLSF | S2: FBCF | T2: Variacao de estoques
A3: 01 - Agropecuária | B3: ='05_ALFA'!$B$18*'01_Recursos'!$S$2 -> 29.343952 | C3: ='05_ALFA'!$C$18*'01_Recursos'!$S$2 -> 0.0010203184 | D3: ='05_ALFA'!$D$18*'01_Recursos'!$S$2 -> 138.79214 | E3: ='05_ALFA'!$E$18*'01_Recursos'!$S$2 -> 0.023178998 | F3: ='05_ALFA'!$F$18*'01_Recursos'!$S$2 -> 0.86734532 | G3: ='05_ALFA'!$G$18*'01_Recursos'!$S$2 -> 5.5752916 | H3: ='05_ALFA'!$H$18*'01_Recursos'!$S$2 -> 0 | I3: ='05_ALFA'!$I$18*'01_Recursos'!$S$2 -> 0 | J3: ='05_ALFA'!$J$18*'01_Recursos'!$S$2 -> 0 | K3: ='05_ALFA'!$K$18*'01_Recursos'!$S$2 -> 0 | L3: ='05_ALFA'!$L$18*'01_Recursos'!$S$2 -> 5.9207009 | M3: ='05_ALFA'!$M$18*'01_Recursos'!$S$2 -> 3.9392405 | N3: ='05_ALFA'!$N$18*'01_Recursos'!$S$2 -> 180.82534 | O3: ='05_ALFA'!$O$18*'01_Recursos'!$S$2 -> 110.70589 | P3: ='05_ALFA'!$P$18*'01_Recursos'!$S$2 -> 0.10630859 | Q3: ='05_ALFA'!$Q$18*'01_Recursos'!$S$2 -> 259.2829 | R3: ='05_ALFA'!$R$18*'01_Recursos'!$S$2 -> 0 | S3: ='05_ALFA'!$S$18*'01_Recursos'!$S$2 -> 14.615638 | T3: ='05_ALFA'!$T$18*'01_Recursos'!$S$2 -> 71.815378
A4: 02 - Indústrias extrativas | B4: ='05_ALFA'!$B$19*'01_Recursos'!$S$3 -> 0.92490211 | C4: ='05_ALFA'!$C$19*'01_Recursos'!$S$3 -> 0.52178504 | D4: ='05_ALFA'!$D$19*'01_Recursos'!$S$3 -> 15.670044 | E4: ='05_ALFA'!$E$19*'01_Recursos'!$S$3 -> 0.42008273 | F4: ='05_ALFA'!$F$19*'01_Recursos'!$S$3 -> 10.631779 | G4: ='05_ALFA'!$G$19*'01_Recursos'!$S$3 -> 0.057067189 | H4: ='05_ALFA'!$H$19*'01_Recursos'!$S$3 -> 0.00048089466 | I4: ='05_ALFA'!$I$19*'01_Recursos'!$S$3 -> 0 | J4: ='05_ALFA'!$J$19*'01_Recursos'!$S$3 -> 0 | K4: ='05_ALFA'!$K$19*'01_Recursos'!$S$3 -> 0.61841046 | L4: ='05_ALFA'!$L$19*'01_Recursos'!$S$3 -> 0.042852469 | M4: ='05_ALFA'!$M$19*'01_Recursos'!$S$3 -> 0.21130984 | N4: ='05_ALFA'!$N$19*'01_Recursos'!$S$3 -> 0.38029447 | O4: ='05_ALFA'!$O$19*'01_Recursos'!$S$3 -> 9.1865896 | P4: ='05_ALFA'!$P$19*'01_Recursos'!$S$3 -> 0 | Q4: ='05_ALFA'!$Q$19*'01_Recursos'!$S$3 -> 0 | R4: ='05_ALFA'!$R$19*'01_Recursos'!$S$3 -> 0 | S4: ='05_ALFA'!$S$19*'01_Recursos'!$S$3 -> 0 | T4: ='05_ALFA'!$T$19*'01_Recursos'!$S$3 -> 6.3070835
A5: 03 - Indústrias de transformação | B5: ='05_ALFA'!$B$20*'01_Recursos'!$S$4 -> 499.37195 | C5: ='05_ALFA'!$C$20*'01_Recursos'!$S$4 -> 12.836672 | D5: ='05_ALFA'!$D$20*'01_Recursos'!$S$4 -> 773.83462 | E5: ='05_ALFA'!$E$20*'01_Recursos'!$S$4 -> 89.737138 | F5: ='05_ALFA'!$F$20*'01_Recursos'!$S$4 -> 434.12408 | G5: ='05_ALFA'!$G$20*'01_Recursos'!$S$4 -> 198.14976 | H5: ='05_ALFA'!$H$20*'01_Recursos'!$S$4 -> 165.63239 | I5: ='05_ALFA'!$I$20*'01_Recursos'!$S$4 -> 13.622463 | J5: ='05_ALFA'!$J$20*'01_Recursos'!$S$4 -> 6.8608484 | K5: ='05_ALFA'!$K$20*'01_Recursos'!$S$4 -> 11.455913 | L5: ='05_ALFA'!$L$20*'01_Recursos'!$S$4 -> 261.59373 | M5: ='05_ALFA'!$M$20*'01_Recursos'!$S$4 -> 208.69386 | N5: ='05_ALFA'!$N$20*'01_Recursos'!$S$4 -> 114.74416 | O5: ='05_ALFA'!$O$20*'01_Recursos'!$S$4 -> 1085.4625 | P5: ='05_ALFA'!$P$20*'01_Recursos'!$S$4 -> 24.084879 | Q5: ='05_ALFA'!$Q$20*'01_Recursos'!$S$4 -> 4964.837 | R5: ='05_ALFA'!$R$20*'01_Recursos'!$S$4 -> 0 | S5: ='05_ALFA'!$S$20*'01_Recursos'!$S$4 -> 497.50722 | T5: ='05_ALFA'!$T$20*'01_Recursos'!$S$4 -> 461.17316
A6: 04 - Eletricidade e gás, água, esgoto e gestão de resíduos | B6: ='05_ALFA'!$B$21*'01_Recursos'!$S$5 -> 0.42350351 | C6: ='05_ALFA'!$C$21*'01_Recursos'!$S$5 -> 0.021614082 | D6: ='05_ALFA'!$D$21*'01_Recursos'!$S$5 -> 0.37469015 | E6: ='05_ALFA'!$E$21*'01_Recursos'!$S$5 -> 4.0496039 | F6: ='05_ALFA'!$F$21*'01_Recursos'!$S$5 -> 0.030118319 | G6: ='05_ALFA'!$G$21*'01_Recursos'!$S$5 -> 0.69917866 | H6: ='05_ALFA'!$H$21*'01_Recursos'!$S$5 -> 0.071431661 | I6: ='05_ALFA'!$I$21*'01_Recursos'!$S$5 -> 0.059475171 | J6: ='05_ALFA'!$J$21*'01_Recursos'!$S$5 -> 0.035397398 | K6: ='05_ALFA'!$K$21*'01_Recursos'!$S$5 -> 0.019475424 | L6: ='05_ALFA'!$L$21*'01_Recursos'!$S$5 -> 0.59307546 | M6: ='05_ALFA'!$M$21*'01_Recursos'!$S$5 -> 1.0452514 | N6: ='05_ALFA'!$N$21*'01_Recursos'!$S$5 -> 0 | O6: ='05_ALFA'!$O$21*'01_Recursos'!$S$5 -> 1.6794387 | P6: ='05_ALFA'!$P$21*'01_Recursos'!$S$5 -> 0 | Q6: ='05_ALFA'!$Q$21*'01_Recursos'!$S$5 -> 3.3402922 | R6: ='05_ALFA'!$R$21*'01_Recursos'!$S$5 -> 0 | S6: ='05_ALFA'!$S$21*'01_Recursos'!$S$5 -> 0 | T6: ='05_ALFA'!$T$21*'01_Recursos'!$S$5 -> 0.0045729375
A7: 05 - Construção | B7: ='05_ALFA'!$B$22*'01_Recursos'!$S$6 -> 0 | C7: ='05_ALFA'!$C$22*'01_Recursos'!$S$6 -> 0 | D7: ='05_ALFA'!$D$22*'01_Recursos'!$S$6 -> 0 | E7: ='05_ALFA'!$E$22*'01_Recursos'!$S$6 -> 0 | F7: ='05_ALFA'!$F$22*'01_Recursos'!$S$6 -> 0 | G7: ='05_ALFA'!$G$22*'01_Recursos'!$S$6 -> 0 | H7: ='05_ALFA'!$H$22*'01_Recursos'!$S$6 -> 0 | I7: ='05_ALFA'!$I$22*'01_Recursos'!$S$6 -> 0 | J7: ='05_ALFA'!$J$22*'01_Recursos'!$S$6 -> 0 | K7: ='05_ALFA'!$K$22*'01_Recursos'!$S$6 -> 0 | L7: ='05_ALFA'!$L$22*'01_Recursos'!$S$6 -> 0 | M7: ='05_ALFA'!$M$22*'01_Recursos'!$S$6 -> 0 | N7: ='05_ALFA'!$N$22*'01_Recursos'!$S$6 -> 0 | O7: ='05_ALFA'!$O$22*'01_Recursos'!$S$6 -> 0 | P7: ='05_ALFA'!$P$22*'01_Recursos'!$S$6 -> 0 | Q7: ='05_ALFA'!$Q$22*'01_Recursos'!$S$6 -> 0 | R7: ='05_ALFA'!$R$22*'01_Recursos'!$S$6 -> 0 | S7: ='05_ALFA'!$S$22*'01_Recursos'!$S$6 -> 0 | T7: ='05_ALFA'!$T$22*'01_Recursos'!$S$6 -> 0
A8: 06 - Comércio | B8: ='05_ALFA'!$B$23*'01_Recursos'!$S$7 -> -53.691977 | C8: ='05_ALFA'!$C$23*'01_Recursos'!$S$7 -> -2.6314487 | D8: ='05_ALFA'!$D$23*'01_Recursos'!$S$7 -> -1033.0426 | E8: ='05_ALFA'!$E$23*'01_Recursos'!$S$7 -> -161.40711 | F8: ='05_ALFA'!$F$23*'01_Recursos'!$S$7 -> -69.583554 | G8: ='05_ALFA'!$G$23*'01_Recursos'!$S$7 -> -930.63763 | H8: ='05_ALFA'!$H$23*'01_Recursos'!$S$7 -> -616.06151 | I8: ='05_ALFA'!$I$23*'01_Recursos'!$S$7 -> -311.39445 | J8: ='05_ALFA'!$J$23*'01_Recursos'!$S$7 -> -6.2345617 | K8: ='05_ALFA'!$K$23*'01_Recursos'!$S$7 -> -1.6524473 | L8: ='05_ALFA'!$L$23*'01_Recursos'!$S$7 -> -162.02107 | M8: ='05_ALFA'!$M$23*'01_Recursos'!$S$7 -> -701.19405 | N8: ='05_ALFA'!$N$23*'01_Recursos'!$S$7 -> -356.59599 | O8: ='05_ALFA'!$O$23*'01_Recursos'!$S$7 -> 0 | P8: ='05_ALFA'!$P$23*'01_Recursos'!$S$7 -> 0 | Q8: ='05_ALFA'!$Q$23*'01_Recursos'!$S$7 -> -6388.9837 | R8: ='05_ALFA'!$R$23*'01_Recursos'!$S$7 -> 0 | S8: ='05_ALFA'!$S$23*'01_Recursos'!$S$7 -> 0 | T8: ='05_ALFA'!$T$23*'01_Recursos'!$S$7 -> 0
A9: 07 - Transporte, armazenagem e correio | B9: ='05_ALFA'!$B$24*'01_Recursos'!$S$8 -> 0 | C9: ='05_ALFA'!$C$24*'01_Recursos'!$S$8 -> 0 | D9: ='05_ALFA'!$D$24*'01_Recursos'!$S$8 -> 0 | E9: ='05_ALFA'!$E$24*'01_Recursos'!$S$8 -> 0 | F9: ='05_ALFA'!$F$24*'01_Recursos'!$S$8 -> 0 | G9: ='05_ALFA'!$G$24*'01_Recursos'!$S$8 -> 0 | H9: ='05_ALFA'!$H$24*'01_Recursos'!$S$8 -> 0 | I9: ='05_ALFA'!$I$24*'01_Recursos'!$S$8 -> 0 | J9: ='05_ALFA'!$J$24*'01_Recursos'!$S$8 -> 0 | K9: ='05_ALFA'!$K$24*'01_Recursos'!$S$8 -> 0 | L9: ='05_ALFA'!$L$24*'01_Recursos'!$S$8 -> 0 | M9: ='05_ALFA'!$M$24*'01_Recursos'!$S$8 -> 0 | N9: ='05_ALFA'!$N$24*'01_Recursos'!$S$8 -> 0 | O9: ='05_ALFA'!$O$24*'01_Recursos'!$S$8 -> 0 | P9: ='05_ALFA'!$P$24*'01_Recursos'!$S$8 -> 0 | Q9: ='05_ALFA'!$Q$24*'01_Recursos'!$S$8 -> 0 | R9: ='05_ALFA'!$R$24*'01_Recursos'!$S$8 -> 0 | S9: ='05_ALFA'!$S$24*'01_Recursos'!$S$8 -> 0 | T9: ='05_ALFA'!$T$24*'01_Recursos'!$S$8 -> 0
A10: 08 - Informação e comunicação | B10: ='05_ALFA'!$B$25*'01_Recursos'!$S$9 -> 0.02545683 | C10: ='05_ALFA'!$C$25*'01_Recursos'!$S$9 -> 0.0094321776 | D10: ='05_ALFA'!$D$25*'01_Recursos'!$S$9 -> 2.012119 | E10: ='05_ALFA'!$E$25*'01_Recursos'!$S$9 -> 1.6969909 | F10: ='05_ALFA'!$F$25*'01_Recursos'!$S$9 -> 0.69073277 | G10: ='05_ALFA'!$G$25*'01_Recursos'!$S$9 -> 6.3625854 | H10: ='05_ALFA'!$H$25*'01_Recursos'!$S$9 -> 1.3112404 | I10: ='05_ALFA'!$I$25*'01_Recursos'!$S$9 -> 10.785993 | J10: ='05_ALFA'!$J$25*'01_Recursos'!$S$9 -> 4.3452908 | K10: ='05_ALFA'!$K$25*'01_Recursos'!$S$9 -> 0.24677845 | L10: ='05_ALFA'!$L$25*'01_Recursos'!$S$9 -> 8.4461835 | M10: ='05_ALFA'!$M$25*'01_Recursos'!$S$9 -> 16.476713 | N10: ='05_ALFA'!$N$25*'01_Recursos'!$S$9 -> 0.11035925 | O10: ='05_ALFA'!$O$25*'01_Recursos'!$S$9 -> 1.1005359 | P10: ='05_ALFA'!$P$25*'01_Recursos'!$S$9 -> 0 | Q10: ='05_ALFA'!$Q$25*'01_Recursos'!$S$9 -> 34.02669 | R10: ='05_ALFA'!$R$25*'01_Recursos'!$S$9 -> 0 | S10: ='05_ALFA'!$S$25*'01_Recursos'!$S$9 -> 4.547372 | T10: ='05_ALFA'!$T$25*'01_Recursos'!$S$9 -> -0.018806148
A11: 09 - Atividades financeiras, de seguros e serviços relacionados | B11: ='05_ALFA'!$B$26*'01_Recursos'!$S$10 -> 0 | C11: ='05_ALFA'!$C$26*'01_Recursos'!$S$10 -> 0 | D11: ='05_ALFA'!$D$26*'01_Recursos'!$S$10 -> 0 | E11: ='05_ALFA'!$E$26*'01_Recursos'!$S$10 -> 0 | F11: ='05_ALFA'!$F$26*'01_Recursos'!$S$10 -> 0 | G11: ='05_ALFA'!$G$26*'01_Recursos'!$S$10 -> 0 | H11: ='05_ALFA'!$H$26*'01_Recursos'!$S$10 -> 0 | I11: ='05_ALFA'!$I$26*'01_Recursos'!$S$10 -> 0 | J11: ='05_ALFA'!$J$26*'01_Recursos'!$S$10 -> 0 | K11: ='05_ALFA'!$K$26*'01_Recursos'!$S$10 -> 0 | L11: ='05_ALFA'!$L$26*'01_Recursos'!$S$10 -> 0 | M11: ='05_ALFA'!$M$26*'01_Recursos'!$S$10 -> 0 | N11: ='05_ALFA'!$N$26*'01_Recursos'!$S$10 -> 0 | O11: ='05_ALFA'!$O$26*'01_Recursos'!$S$10 -> 0 | P11: ='05_ALFA'!$P$26*'01_Recursos'!$S$10 -> 0 | Q11: ='05_ALFA'!$Q$26*'01_Recursos'!$S$10 -> 0 | R11: ='05_ALFA'!$R$26*'01_Recursos'!$S$10 -> 0 | S11: ='05_ALFA'!$S$26*'01_Recursos'!$S$10 -> 0 | T11: ='05_ALFA'!$T$26*'01_Recursos'!$S$10 -> 0
A12: 10 - Atividades imobiliárias | B12: ='05_ALFA'!$B$27*'01_Recursos'!$S$11 -> 0 | C12: ='05_ALFA'!$C$27*'01_Recursos'!$S$11 -> 0 | D12: ='05_ALFA'!$D$27*'01_Recursos'!$S$11 -> 0 | E12: ='05_ALFA'!$E$27*'01_Recursos'!$S$11 -> 0 | F12: ='05_ALFA'!$F$27*'01_Recursos'!$S$11 -> 0 | G12: ='05_ALFA'!$G$27*'01_Recursos'!$S$11 -> 0 | H12: ='05_ALFA'!$H$27*'01_Recursos'!$S$11 -> 0 | I12: ='05_ALFA'!$I$27*'01_Recursos'!$S$11 -> 0 | J12: ='05_ALFA'!$J$27*'01_Recursos'!$S$11 -> 0 | K12: ='05_ALFA'!$K$27*'01_Recursos'!$S$11 -> 0 | L12: ='05_ALFA'!$L$27*'01_Recursos'!$S$11 -> 0 | M12: ='05_ALFA'!$M$27*'01_Recursos'!$S$11 -> 0 | N12: ='05_ALFA'!$N$27*'01_Recursos'!$S$11 -> 0 | O12: ='05_ALFA'!$O$27*'01_Recursos'!$S$11 -> 0 | P12: ='05_ALFA'!$P$27*'01_Recursos'!$S$11 -> 0 | Q12: ='05_ALFA'!$Q$27*'01_Recursos'!$S$11 -> 0 | R12: ='05_ALFA'!$R$27*'01_Recursos'!$S$11 -> 0 | S12: ='05_ALFA'!$S$27*'01_Recursos'!$S$11 -> 0 | T12: ='05_ALFA'!$T$27*'01_Recursos'!$S$11 -> 0
A13: 11 - Outras atividades de serviços | B13: ='05_ALFA'!$B$28*'01_Recursos'!$S$12 -> 0 | C13: ='05_ALFA'!$C$28*'01_Recursos'!$S$12 -> 0 | D13: ='05_ALFA'!$D$28*'01_Recursos'!$S$12 -> 0 | E13: ='05_ALFA'!$E$28*'01_Recursos'!$S$12 -> 0 | F13: ='05_ALFA'!$F$28*'01_Recursos'!$S$12 -> 0 | G13: ='05_ALFA'!$G$28*'01_Recursos'!$S$12 -> 0 | H13: ='05_ALFA'!$H$28*'01_Recursos'!$S$12 -> 0 | I13: ='05_ALFA'!$I$28*'01_Recursos'!$S$12 -> 0 | J13: ='05_ALFA'!$J$28*'01_Recursos'!$S$12 -> 0 | K13: ='05_ALFA'!$K$28*'01_Recursos'!$S$12 -> 0 | L13: ='05_ALFA'!$L$28*'01_Recursos'!$S$12 -> 0 | M13: ='05_ALFA'!$M$28*'01_Recursos'!$S$12 -> 0 | N13: ='05_ALFA'!$N$28*'01_Recursos'!$S$12 -> 0 | O13: ='05_ALFA'!$O$28*'01_Recursos'!$S$12 -> 0 | P13: ='05_ALFA'!$P$28*'01_Recursos'!$S$12 -> 0 | Q13: ='05_ALFA'!$Q$28*'01_Recursos'!$S$12 -> 0 | R13: ='05_ALFA'!$R$28*'01_Recursos'!$S$12 -> 0 | S13: ='05_ALFA'!$S$28*'01_Recursos'!$S$12 -> 0 | T13: ='05_ALFA'!$T$28*'01_Recursos'!$S$12 -> 0
A14: 12 - Administração, defesa, saúde e educação públicas e seguridade social | B14: ='05_ALFA'!$B$29*'01_Recursos'!$S$13 -> 0 | C14: ='05_ALFA'!$C$29*'01_Recursos'!$S$13 -> 0 | D14: ='05_ALFA'!$D$29*'01_Recursos'!$S$13 -> 0 | E14: ='05_ALFA'!$E$29*'01_Recursos'!$S$13 -> 0 | F14: ='05_ALFA'!$F$29*'01_Recursos'!$S$13 -> 0 | G14: ='05_ALFA'!$G$29*'01_Recursos'!$S$13 -> 0 | H14: ='05_ALFA'!$H$29*'01_Recursos'!$S$13 -> 0 | I14: ='05_ALFA'!$I$29*'01_Recursos'!$S$13 -> 0 | J14: ='05_ALFA'!$J$29*'01_Recursos'!$S$13 -> 0 | K14: ='05_ALFA'!$K$29*'01_Recursos'!$S$13 -> 0 | L14: ='05_ALFA'!$L$29*'01_Recursos'!$S$13 -> 0 | M14: ='05_ALFA'!$M$29*'01_Recursos'!$S$13 -> 0 | N14: ='05_ALFA'!$N$29*'01_Recursos'!$S$13 -> 0 | O14: ='05_ALFA'!$O$29*'01_Recursos'!$S$13 -> 0 | P14: ='05_ALFA'!$P$29*'01_Recursos'!$S$13 -> 0 | Q14: ='05_ALFA'!$Q$29*'01_Recursos'!$S$13 -> 0 | R14: ='05_ALFA'!$R$29*'01_Recursos'!$S$13 -> 0 | S14: ='05_ALFA'!$S$29*'01_Recursos'!$S$13 -> 0 | T14: ='05_ALFA'!$T$29*'01_Recursos'!$S$13 -> 0
A16: Margem paga pelos produtos que NAO sao Comercio | B16: =SUM(B3:B14)-B8 -> 530.08976 | C16: =SUM(C3:C14)-C8 -> 13.390523 | D16: =SUM(D3:D14)-D8 -> 930.68362 | E16: =SUM(E3:E14)-E8 -> 95.926995 | F16: =SUM(F3:F14)-F8 -> 446.34406 | G16: =SUM(G3:G14)-G8 -> 210.84388 | H16: =SUM(H3:H14)-H8 -> 167.01554 | I16: =SUM(I3:I14)-I8 -> 24.467931 | ... T16: =SUM(T3:T14)-T8 -> 539.28139
A18: ETAPA 9b - matriz final: a linha de Comercio recebe a compensacao
A19: Produto \ Destino | B19: 01 - Agropecuária | C19: 02 - Indústrias extrativas | D19: 03 - Indústrias de transformação | E19: 04 - Eletricidade e gás, água, esgoto e gestão de resíduos | F19: 05 - Construção | G19: 06 - Comércio | H19: 07 - Transporte, armazenagem e correio | I19: 08 - Informação e comunicação | J19: 09 - Atividades financeiras, de seguros e serviços relacionados | K19: 10 - Atividades imobiliárias | L19: 11 - Outras atividades de serviços | M19: 12 - Administração, defesa, saúde e educação públicas e seguridade social | N19: Exportacoes outros paises | O19: Exportacoes outras UFs | P19: Consumo do governo | Q19: Consumo das familias | R19: Consumo das ISFLSF | S19: FBCF | T19: Variacao de estoques
A20: 01 - Agropecuária | B20: =B$3 -> 29.343952 | C20: =C$3 -> 0.0010203184 | D20: =D$3 -> 138.79214 | E20: =E$3 -> 0.023178998 | F20: =F$3 -> 0.86734532 | G20: =G$3 -> 5.5752916 | H20: =H$3 -> 0 | I20: =I$3 -> 0 | ... T20: =T$3 -> 71.815378
A21: 02 - Indústrias extrativas | B21: =B$4 -> 0.92490211 | C21: =C$4 -> 0.52178504 | D21: =D$4 -> 15.670044 | E21: =E$4 -> 0.42008273 | F21: =F$4 -> 10.631779 | G21: =G$4 -> 0.057067189 | H21: =H$4 -> 0.00048089466 | I21: =I$4 -> 0 | ... T21: =T$4 -> 6.3070835
A22: 03 - Indústrias de transformação | B22: =B$5 -> 499.37195 | C22: =C$5 -> 12.836672 | D22: =D$5 -> 773.83462 | E22: =E$5 -> 89.737138 | F22: =F$5 -> 434.12408 | G22: =G$5 -> 198.14976 | H22: =H$5 -> 165.63239 | I22: =I$5 -> 13.622463 | ... T22: =T$5 -> 461.17316
A23: 04 - Eletricidade e gás, água, esgoto e gestão de resíduos | B23: =B$6 -> 0.42350351 | C23: =C$6 -> 0.021614082 | D23: =D$6 -> 0.37469015 | E23: =E$6 -> 4.0496039 | F23: =F$6 -> 0.030118319 | G23: =G$6 -> 0.69917866 | H23: =H$6 -> 0.071431661 | I23: =I$6 -> 0.059475171 | ... T23: =T$6 -> 0.0045729375
A24: 05 - Construção | B24: =B$7 -> 0 | C24: =C$7 -> 0 | D24: =D$7 -> 0 | E24: =E$7 -> 0 | F24: =F$7 -> 0 | G24: =G$7 -> 0 | H24: =H$7 -> 0 | I24: =I$7 -> 0 | ... T24: =T$7 -> 0
A25: 06 - Comércio | B25: =-B$16 -> -530.08976 | C25: =-C$16 -> -13.390523 | D25: =-D$16 -> -930.68362 | E25: =-E$16 -> -95.926995 | F25: =-F$16 -> -446.34406 | G25: =-G$16 -> -210.84388 | H25: =-H$16 -> -167.01554 | I25: =-I$16 -> -24.467931 | ... T25: =-T$16 -> -539.28139
A26: 07 - Transporte, armazenagem e correio | B26: =B$9 -> 0 | C26: =C$9 -> 0 | D26: =D$9 -> 0 | E26: =E$9 -> 0 | F26: =F$9 -> 0 | G26: =G$9 -> 0 | H26: =H$9 -> 0 | I26: =I$9 -> 0 | ... T26: =T$9 -> 0
A27: 08 - Informação e comunicação | B27: =B$10 -> 0.02545683 | C27: =C$10 -> 0.0094321776 | D27: =D$10 -> 2.012119 | E27: =E$10 -> 1.6969909 | F27: =F$10 -> 0.69073277 | G27: =G$10 -> 6.3625854 | H27: =H$10 -> 1.3112404 | I27: =I$10 -> 10.785993 | ... T27: =T$10 -> -0.018806148
A28: 09 - Atividades financeiras, de seguros e serviços relacionados | B28: =B$11 -> 0 | C28: =C$11 -> 0 | D28: =D$11 -> 0 | E28: =E$11 -> 0 | F28: =F$11 -> 0 | G28: =G$11 -> 0 | H28: =H$11 -> 0 | I28: =I$11 -> 0 | ... T28: =T$11 -> 0
A29: 10 - Atividades imobiliárias | B29: =B$12 -> 0 | C29: =C$12 -> 0 | D29: =D$12 -> 0 | E29: =E$12 -> 0 | F29: =F$12 -> 0 | G29: =G$12 -> 0 | H29: =H$12 -> 0 | I29: =I$12 -> 0 | ... T29: =T$12 -> 0
A30: 11 - Outras atividades de serviços | B30: =B$13 -> 0 | C30: =C$13 -> 0 | D30: =D$13 -> 0 | E30: =E$13 -> 0 | F30: =F$13 -> 0 | G30: =G$13 -> 0 | H30: =H$13 -> 0 | I30: =I$13 -> 0 | ... T30: =T$13 -> 0
A31: 12 - Administração, defesa, saúde e educação públicas e seguridade social | B31: =B$14 -> 0 | C31: =C$14 -> 0 | D31: =D$14 -> 0 | E31: =E$14 -> 0 | F31: =F$14 -> 0 | G31: =G$14 -> 0 | H31: =H$14 -> 0 | I31: =I$14 -> 0 | ... T31: =T$14 -> 0
A33: Conferencia: soma da coluna (deve ser 0) | B33: =SUM(B20:B31) -> 1.7329888e-14 | C33: =SUM(C20:C31) -> -1.179612e-16 | D33: =SUM(D20:D31) -> -2.8421709e-14 | E33: =SUM(E20:E31) -> -4.6629367e-15 | F33: =SUM(F20:F31) -> -2.2315483e-14 | G33: =SUM(G20:G31) -> -6.2172489e-15 | H33: =SUM(H20:H31) -> -2.6867397e-14 | I33: =SUM(I20:I31) -> -5.3290705e-15 | ... T33: =SUM(T20:T31) -> -2.4577562e-14

Sheet 07_M_transporte
A1: ETAPA 10a - margem de Transporte embutida em cada celula (ALFA x margem do produto)
A2: Produto \ Destino | B2: 01 - Agropecuária | C2: 02 - Indústrias extrativas | D2: 03 - Indústrias de transformação | E2: 04 - Eletricidade e gás, água, esgoto e gestão de resíduos | F2: 05 - Construção | G2: 06 - Comércio | H2: 07 - Transporte, armazenagem e correio | I2: 08 - Informação e comunicação | J2: 09 - Atividades financeiras, de seguros e serviços relacionados | K2: 10 - Atividades imobiliárias | L2: 11 - Outras atividades de serviços | M2: 12 - Administração, defesa, saúde e educação públicas e seguridade social | N2: Exportacoes outros paises | O2: Exportacoes outras UFs | P2: Consumo do governo | Q2: Consumo das familias | R2: Consumo das ISFLSF | S2: FBCF | T2: Variacao de estoques
A3: 01 - Agropecuária | B3: ='05_ALFA'!$B$18*'01_Recursos'!$T$2 -> 4.1062249 | C3: ='05_ALFA'!$C$18*'01_Recursos'!$T$2 -> 0.00014277752 | D3: ='05_ALFA'!$D$18*'01_Recursos'!$T$2 -> 19.421779 | E3: ='05_ALFA'!$E$18*'01_Recursos'!$T$2 -> 0.0032435365 | F3: ='05_ALFA'!$F$18*'01_Recursos'!$T$2 -> 0.12137135 | G3: ='05_ALFA'!$G$18*'01_Recursos'!$T$2 -> 0.78017444 | H3: ='05_ALFA'!$H$18*'01_Recursos'!$T$2 -> 0 | I3: ='05_ALFA'!$I$18*'01_Recursos'!$T$2 -> 0 | J3: ='05_ALFA'!$J$18*'01_Recursos'!$T$2 -> 0 | K3: ='05_ALFA'!$K$18*'01_Recursos'!$T$2 -> 0 | L3: ='05_ALFA'!$L$18*'01_Recursos'!$T$2 -> 0.82850905 | M3: ='05_ALFA'!$M$18*'01_Recursos'!$T$2 -> 0.55123479 | N3: ='05_ALFA'!$N$18*'01_Recursos'!$T$2 -> 25.303664 | O3: ='05_ALFA'!$O$18*'01_Recursos'!$T$2 -> 15.49155 | P3: ='05_ALFA'!$P$18*'01_Recursos'!$T$2 -> 0.014876217 | Q3: ='05_ALFA'!$Q$18*'01_Recursos'!$T$2 -> 36.282567 | R3: ='05_ALFA'!$R$18*'01_Recursos'!$T$2 -> 0 | S3: ='05_ALFA'!$S$18*'01_Recursos'!$T$2 -> 2.0452289 | T3: ='05_ALFA'!$T$18*'01_Recursos'!$T$2 -> 10.049434
A4: 02 - Indústrias extrativas | B4: ='05_ALFA'!$B$19*'01_Recursos'!$T$3 -> 1.0899909 | C4: ='05_ALFA'!$C$19*'01_Recursos'!$T$3 -> 0.61492013 | D4: ='05_ALFA'!$D$19*'01_Recursos'!$T$3 -> 18.46704 | E4: ='05_ALFA'!$E$19*'01_Recursos'!$T$3 -> 0.49506464 | F4: ='05_ALFA'!$F$19*'01_Recursos'!$T$3 -> 12.52948 | G4: ='05_ALFA'!$G$19*'01_Recursos'!$T$3 -> 0.067253295 | H4: ='05_ALFA'!$H$19*'01_Recursos'!$T$3 -> 0.0005667311 | I4: ='05_ALFA'!$I$19*'01_Recursos'!$T$3 -> 0 | J4: ='05_ALFA'!$J$19*'01_Recursos'!$T$3 -> 0 | K4: ='05_ALFA'!$K$19*'01_Recursos'!$T$3 -> 0.72879253 | L4: ='05_ALFA'!$L$19*'01_Recursos'!$T$3 -> 0.050501344 | M4: ='05_ALFA'!$M$19*'01_Recursos'!$T$3 -> 0.24902722 | N4: ='05_ALFA'!$N$19*'01_Recursos'!$T$3 -> 0.44817446 | O4: ='05_ALFA'!$O$19*'01_Recursos'!$T$3 -> 10.826333 | P4: ='05_ALFA'!$P$19*'01_Recursos'!$T$3 -> 0 | Q4: ='05_ALFA'!$Q$19*'01_Recursos'!$T$3 -> 0 | R4: ='05_ALFA'!$R$19*'01_Recursos'!$T$3 -> 0 | S4: ='05_ALFA'!$S$19*'01_Recursos'!$T$3 -> 0 | T4: ='05_ALFA'!$T$19*'01_Recursos'!$T$3 -> 7.4328551
A5: 03 - Indústrias de transformação | B5: ='05_ALFA'!$B$20*'01_Recursos'!$T$4 -> 20.790808 | C5: ='05_ALFA'!$C$20*'01_Recursos'!$T$4 -> 0.53444087 | D5: ='05_ALFA'!$D$20*'01_Recursos'!$T$4 -> 32.217763 | E5: ='05_ALFA'!$E$20*'01_Recursos'!$T$4 -> 3.7361082 | F5: ='05_ALFA'!$F$20*'01_Recursos'!$T$4 -> 18.074284 | G5: ='05_ALFA'!$G$20*'01_Recursos'!$T$4 -> 8.2497499 | H5: ='05_ALFA'!$H$20*'01_Recursos'!$T$4 -> 6.8959244 | I5: ='05_ALFA'!$I$20*'01_Recursos'!$T$4 -> 0.56715642 | J5: ='05_ALFA'!$J$20*'01_Recursos'!$T$4 -> 0.28564397 | K5: ='05_ALFA'!$K$20*'01_Recursos'!$T$4 -> 0.4769545 | L5: ='05_ALFA'!$L$20*'01_Recursos'!$T$4 -> 10.891171 | M5: ='05_ALFA'!$M$20*'01_Recursos'!$T$4 -> 8.6887421 | N5: ='05_ALFA'!$N$20*'01_Recursos'!$T$4 -> 4.7772486 | O5: ='05_ALFA'!$O$20*'01_Recursos'!$T$4 -> 45.192052 | P5: ='05_ALFA'!$P$20*'01_Recursos'!$T$4 -> 1.0027478 | Q5: ='05_ALFA'!$Q$20*'01_Recursos'!$T$4 -> 206.70559 | R5: ='05_ALFA'!$R$20*'01_Recursos'!$T$4 -> 0 | S5: ='05_ALFA'!$S$20*'01_Recursos'!$T$4 -> 20.713172 | T5: ='05_ALFA'!$T$20*'01_Recursos'!$T$4 -> 19.200443
A6: 04 - Eletricidade e gás, água, esgoto e gestão de resíduos | B6: ='05_ALFA'!$B$21*'01_Recursos'!$T$5 -> 0 | C6: ='05_ALFA'!$C$21*'01_Recursos'!$T$5 -> 0 | D6: ='05_ALFA'!$D$21*'01_Recursos'!$T$5 -> 0 | E6: ='05_ALFA'!$E$21*'01_Recursos'!$T$5 -> 0 | F6: ='05_ALFA'!$F$21*'01_Recursos'!$T$5 -> 0 | G6: ='05_ALFA'!$G$21*'01_Recursos'!$T$5 -> 0 | H6: ='05_ALFA'!$H$21*'01_Recursos'!$T$5 -> 0 | I6: ='05_ALFA'!$I$21*'01_Recursos'!$T$5 -> 0 | J6: ='05_ALFA'!$J$21*'01_Recursos'!$T$5 -> 0 | K6: ='05_ALFA'!$K$21*'01_Recursos'!$T$5 -> 0 | L6: ='05_ALFA'!$L$21*'01_Recursos'!$T$5 -> 0 | M6: ='05_ALFA'!$M$21*'01_Recursos'!$T$5 -> 0 | N6: ='05_ALFA'!$N$21*'01_Recursos'!$T$5 -> 0 | O6: ='05_ALFA'!$O$21*'01_Recursos'!$T$5 -> 0 | P6: ='05_ALFA'!$P$21*'01_Recursos'!$T$5 -> 0 | Q6: ='05_ALFA'!$Q$21*'01_Recursos'!$T$5 -> 0 | R6: ='05_ALFA'!$R$21*'01_Recursos'!$T$5 -> 0 | S6: ='05_ALFA'!$S$21*'01_Recursos'!$T$5 -> 0 | T6: ='05_ALFA'!$T$21*'01_Recursos'!$T$5 -> 0
A7: 05 - Construção | B7: ='05_ALFA'!$B$22*'01_Recursos'!$T$6 -> 0 | C7: ='05_ALFA'!$C$22*'01_Recursos'!$T$6 -> 0 | D7: ='05_ALFA'!$D$22*'01_Recursos'!$T$6 -> 0 | E7: ='05_ALFA'!$E$22*'01_Recursos'!$T$6 -> 0 | F7: ='05_ALFA'!$F$22*'01_Recursos'!$T$6 -> 0 | G7: ='05_ALFA'!$G$22*'01_Recursos'!$T$6 -> 0 | H7: ='05_ALFA'!$H$22*'01_Recursos'!$T$6 -> 0 | I7: ='05_ALFA'!$I$22*'01_Recursos'!$T$6 -> 0 | J7: ='05_ALFA'!$J$22*'01_Recursos'!$T$6 -> 0 | K7: ='05_ALFA'!$K$22*'01_Recursos'!$T$6 -> 0 | L7: ='05_ALFA'!$L$22*'01_Recursos'!$T$6 -> 0 | M7: ='05_ALFA'!$M$22*'01_Recursos'!$T$6 -> 0 | N7: ='05_ALFA'!$N$22*'01_Recursos'!$T$6 -> 0 | O7: ='05_ALFA'!$O$22*'01_Recursos'!$T$6 -> 0 | P7: ='05_ALFA'!$P$22*'01_Recursos'!$T$6 -> 0 | Q7: ='05_ALFA'!$Q$22*'01_Recursos'!$T$6 -> 0 | R7: ='05_ALFA'!$R$22*'01_Recursos'!$T$6 -> 0 | S7: ='05_ALFA'!$S$22*'01_Recursos'!$T$6 -> 0 | T7: ='05_ALFA'!$T$22*'01_Recursos'!$T$6 -> 0
A8: 06 - Comércio | B8: ='05_ALFA'!$B$23*'01_Recursos'!$T$7 -> 0 | C8: ='05_ALFA'!$C$23*'01_Recursos'!$T$7 -> 0 | D8: ='05_ALFA'!$D$23*'01_Recursos'!$T$7 -> 0 | E8: ='05_ALFA'!$E$23*'01_Recursos'!$T$7 -> 0 | F8: ='05_ALFA'!$F$23*'01_Recursos'!$T$7 -> 0 | G8: ='05_ALFA'!$G$23*'01_Recursos'!$T$7 -> 0 | H8: ='05_ALFA'!$H$23*'01_Recursos'!$T$7 -> 0 | I8: ='05_ALFA'!$I$23*'01_Recursos'!$T$7 -> 0 | J8: ='05_ALFA'!$J$23*'01_Recursos'!$T$7 -> 0 | K8: ='05_ALFA'!$K$23*'01_Recursos'!$T$7 -> 0 | L8: ='05_ALFA'!$L$23*'01_Recursos'!$T$7 -> 0 | M8: ='05_ALFA'!$M$23*'01_Recursos'!$T$7 -> 0 | N8: ='05_ALFA'!$N$23*'01_Recursos'!$T$7 -> 0 | O8: ='05_ALFA'!$O$23*'01_Recursos'!$T$7 -> 0 | P8: ='05_ALFA'!$P$23*'01_Recursos'!$T$7 -> 0 | Q8: ='05_ALFA'!$Q$23*'01_Recursos'!$T$7 -> 0 | R8: ='05_ALFA'!$R$23*'01_Recursos'!$T$7 -> 0 | S8: ='05_ALFA'!$S$23*'01_Recursos'!$T$7 -> 0 | T8: ='05_ALFA'!$T$23*'01_Recursos'!$T$7 -> 0
A9: 07 - Transporte, armazenagem e correio | B9: ='05_ALFA'!$B$24*'01_Recursos'!$T$8 -> -22.051811 | C9: ='05_ALFA'!$C$24*'01_Recursos'!$T$8 -> -1.2257524 | D9: ='05_ALFA'!$D$24*'01_Recursos'!$T$8 -> -79.703333 | E9: ='05_ALFA'!$E$24*'01_Recursos'!$T$8 -> -4.4183008 | F9: ='05_ALFA'!$F$24*'01_Recursos'!$T$8 -> -6.8851318 | G9: ='05_ALFA'!$G$24*'01_Recursos'!$T$8 -> -93.525878 | H9: ='05_ALFA'!$H$24*'01_Recursos'!$T$8 -> -59.963369 | I9: ='05_ALFA'!$I$24*'01_Recursos'!$T$8 -> -2.1630987 | J9: ='05_ALFA'!$J$24*'01_Recursos'!$T$8 -> -5.4996367 | K9: ='05_ALFA'!$K$24*'01_Recursos'!$T$8 -> -0.37277871 | L9: ='05_ALFA'!$L$24*'01_Recursos'!$T$8 -> -26.178179 | M9: ='05_ALFA'!$M$24*'01_Recursos'!$T$8 -> -40.31223 | N9: ='05_ALFA'!$N$24*'01_Recursos'!$T$8 -> -3.1462782 | O9: ='05_ALFA'!$O$24*'01_Recursos'!$T$8 -> 0 | P9: ='05_ALFA'!$P$24*'01_Recursos'!$T$8 -> 0 | Q9: ='05_ALFA'!$Q$24*'01_Recursos'!$T$8 -> -231.55422 | R9: ='05_ALFA'!$R$24*'01_Recursos'!$T$8 -> 0 | S9: ='05_ALFA'!$S$24*'01_Recursos'!$T$8 -> 0 | T9: ='05_ALFA'!$T$24*'01_Recursos'!$T$8 -> 0
A10: 08 - Informação e comunicação | B10: ='05_ALFA'!$B$25*'01_Recursos'!$T$9 -> 0 | C10: ='05_ALFA'!$C$25*'01_Recursos'!$T$9 -> 0 | D10: ='05_ALFA'!$D$25*'01_Recursos'!$T$9 -> 0 | E10: ='05_ALFA'!$E$25*'01_Recursos'!$T$9 -> 0 | F10: ='05_ALFA'!$F$25*'01_Recursos'!$T$9 -> 0 | G10: ='05_ALFA'!$G$25*'01_Recursos'!$T$9 -> 0 | H10: ='05_ALFA'!$H$25*'01_Recursos'!$T$9 -> 0 | I10: ='05_ALFA'!$I$25*'01_Recursos'!$T$9 -> 0 | J10: ='05_ALFA'!$J$25*'01_Recursos'!$T$9 -> 0 | K10: ='05_ALFA'!$K$25*'01_Recursos'!$T$9 -> 0 | L10: ='05_ALFA'!$L$25*'01_Recursos'!$T$9 -> 0 | M10: ='05_ALFA'!$M$25*'01_Recursos'!$T$9 -> 0 | N10: ='05_ALFA'!$N$25*'01_Recursos'!$T$9 -> 0 | O10: ='05_ALFA'!$O$25*'01_Recursos'!$T$9 -> 0 | P10: ='05_ALFA'!$P$25*'01_Recursos'!$T$9 -> 0 | Q10: ='05_ALFA'!$Q$25*'01_Recursos'!$T$9 -> 0 | R10: ='05_ALFA'!$R$25*'01_Recursos'!$T$9 -> 0 | S10: ='05_ALFA'!$S$25*'01_Recursos'!$T$9 -> 0 | T10: ='05_ALFA'!$T$25*'01_Recursos'!$T$9 -> 0
A11: 09 - Atividades financeiras, de seguros e serviços relacionados | B11: ='05_ALFA'!$B$26*'01_Recursos'!$T$10 -> 0 | C11: ='05_ALFA'!$C$26*'01_Recursos'!$T$10 -> 0 | D11: ='05_ALFA'!$D$26*'01_Recursos'!$T$10 -> 0 | E11: ='05_ALFA'!$E$26*'01_Recursos'!$T$10 -> 0 | F11: ='05_ALFA'!$F$26*'01_Recursos'!$T$10 -> 0 | G11: ='05_ALFA'!$G$26*'01_Recursos'!$T$10 -> 0 | H11: ='05_ALFA'!$H$26*'01_Recursos'!$T$10 -> 0 | I11: ='05_ALFA'!$I$26*'01_Recursos'!$T$10 -> 0 | J11: ='05_ALFA'!$J$26*'01_Recursos'!$T$10 -> 0 | K11: ='05_ALFA'!$K$26*'01_Recursos'!$T$10 -> 0 | L11: ='05_ALFA'!$L$26*'01_Recursos'!$T$10 -> 0 | M11: ='05_ALFA'!$M$26*'01_Recursos'!$T$10 -> 0 | N11: ='05_ALFA'!$N$26*'01_Recursos'!$T$10 -> 0 | O11: ='05_ALFA'!$O$26*'01_Recursos'!$T$10 -> 0 | P11: ='05_ALFA'!$P$26*'01_Recursos'!$T$10 -> 0 | Q11: ='05_ALFA'!$Q$26*'01_Recursos'!$T$10 -> 0 | R11: ='05_ALFA'!$R$26*'01_Recursos'!$T$10 -> 0 | S11: ='05_ALFA'!$S$26*'01_Recursos'!$T$10 -> 0 | T11: ='05_ALFA'!$T$26*'01_Recursos'!$T$10 -> 0
A12: 10 - Atividades imobiliárias | B12: ='05_ALFA'!$B$27*'01_Recursos'!$T$11 -> 0 | C12: ='05_ALFA'!$C$27*'01_Recursos'!$T$11 -> 0 | D12: ='05_ALFA'!$D$27*'01_Recursos'!$T$11 -> 0 | E12: ='05_ALFA'!$E$27*'01_Recursos'!$T$11 -> 0 | F12: ='05_ALFA'!$F$27*'01_Recursos'!$T$11 -> 0 | G12: ='05_ALFA'!$G$27*'01_Recursos'!$T$11 -> 0 | H12: ='05_ALFA'!$H$27*'01_Recursos'!$T$11 -> 0 | I12: ='05_ALFA'!$I$27*'01_Recursos'!$T$11 -> 0 | J12: ='05_ALFA'!$J$27*'01_Recursos'!$T$11 -> 0 | K12: ='05_ALFA'!$K$27*'01_Recursos'!$T$11 -> 0 | L12: ='05_ALFA'!$L$27*'01_Recursos'!$T$11 -> 0 | M12: ='05_ALFA'!$M$27*'01_Recursos'!$T$11 -> 0 | N12: ='05_ALFA'!$N$27*'01_Recursos'!$T$11 -> 0 | O12: ='05_ALFA'!$O$27*'01_Recursos'!$T$11 -> 0 | P12: ='05_ALFA'!$P$27*'01_Recursos'!$T$11 -> 0 | Q12: ='05_ALFA'!$Q$27*'01_Recursos'!$T$11 -> 0 | R12: ='05_ALFA'!$R$27*'01_Recursos'!$T$11 -> 0 | S12: ='05_ALFA'!$S$27*'01_Recursos'!$T$11 -> 0 | T12: ='05_ALFA'!$T$27*'01_Recursos'!$T$11 -> 0
A13: 11 - Outras atividades de serviços | B13: ='05_ALFA'!$B$28*'01_Recursos'!$T$12 -> 0 | C13: ='05_ALFA'!$C$28*'01_Recursos'!$T$12 -> 0 | D13: ='05_ALFA'!$D$28*'01_Recursos'!$T$12 -> 0 | E13: ='05_ALFA'!$E$28*'01_Recursos'!$T$12 -> 0 | F13: ='05_ALFA'!$F$28*'01_Recursos'!$T$12 -> 0 | G13: ='05_ALFA'!$G$28*'01_Recursos'!$T$12 -> 0 | H13: ='05_ALFA'!$H$28*'01_Recursos'!$T$12 -> 0 | I13: ='05_ALFA'!$I$28*'01_Recursos'!$T$12 -> 0 | J13: ='05_ALFA'!$J$28*'01_Recursos'!$T$12 -> 0 | K13: ='05_ALFA'!$K$28*'01_Recursos'!$T$12 -> 0 | L13: ='05_ALFA'!$L$28*'01_Recursos'!$T$12 -> 0 | M13: ='05_ALFA'!$M$28*'01_Recursos'!$T$12 -> 0 | N13: ='05_ALFA'!$N$28*'01_Recursos'!$T$12 -> 0 | O13: ='05_ALFA'!$O$28*'01_Recursos'!$T$12 -> 0 | P13: ='05_ALFA'!$P$28*'01_Recursos'!$T$12 -> 0 | Q13: ='05_ALFA'!$Q$28*'01_Recursos'!$T$12 -> 0 | R13: ='05_ALFA'!$R$28*'01_Recursos'!$T$12 -> 0 | S13: ='05_ALFA'!$S$28*'01_Recursos'!$T$12 -> 0 | T13: ='05_ALFA'!$T$28*'01_Recursos'!$T$12 -> 0
A14: 12 - Administração, defesa, saúde e educação públicas e seguridade social | B14: ='05_ALFA'!$B$29*'01_Recursos'!$T$13 -> 0 | C14: ='05_ALFA'!$C$29*'01_Recursos'!$T$13 -> 0 | D14: ='05_ALFA'!$D$29*'01_Recursos'!$T$13 -> 0 | E14: ='05_ALFA'!$E$29*'01_Recursos'!$T$13 -> 0 | F14: ='05_ALFA'!$F$29*'01_Recursos'!$T$13 -> 0 | G14: ='05_ALFA'!$G$29*'01_Recursos'!$T$13 -> 0 | H14: ='05_ALFA'!$H$29*'01_Recursos'!$T$13 -> 0 | I14: ='05_ALFA'!$I$29*'01_Recursos'!$T$13 -> 0 | J14: ='05_ALFA'!$J$29*'01_Recursos'!$T$13 -> 0 | K14: ='05_ALFA'!$K$29*'01_Recursos'!$T$13 -> 0 | L14: ='05_ALFA'!$L$29*'01_Recursos'!$T$13 -> 0 | M14: ='05_ALFA'!$M$29*'01_Recursos'!$T$13 -> 0 | N14: ='05_ALFA'!$N$29*'01_Recursos'!$T$13 -> 0 | O14: ='05_ALFA'!$O$29*'01_Recursos'!$T$13 -> 0 | P14: ='05_ALFA'!$P$29*'01_Recursos'!$T$13 -> 0 | Q14: ='05_ALFA'!$Q$29*'01_Recursos'!$T$13 -> 0 | R14: ='05_ALFA'!$R$29*'01_Recursos'!$T$13 -> 0 | S14: ='05_ALFA'!$S$29*'01_Recursos'!$T$13 -> 0 | T14: ='05_ALFA'!$T$29*'01_Recursos'!$T$13 -> 0
A16: Margem paga pelos produtos que NAO sao Transporte | B16: =SUM(B3:B14)-B9 -> 25.987024 | C16: =SUM(C3:C14)-C9 -> 1.1495038 | D16: =SUM(D3:D14)-D9 -> 70.106583 | E16: =SUM(E3:E14)-E9 -> 4.2344164 | F16: =SUM(F3:F14)-F9 -> 30.725135 | G16: =SUM(G3:G14)-G9 -> 9.0971777 | H16: =SUM(H3:H14)-H9 -> 6.8964911 | I16: =SUM(I3:I14)-I9 -> 0.56715642 | ... T16: =SUM(T3:T14)-T9 -> 36.682732
A18: ETAPA 10b - matriz final: a linha de Transporte recebe a compensacao
A19: Produto \ Destino | B19: 01 - Agropecuária | C19: 02 - Indústrias extrativas | D19: 03 - Indústrias de transformação | E19: 04 - Eletricidade e gás, água, esgoto e gestão de resíduos | F19: 05 - Construção | G19: 06 - Comércio | H19: 07 - Transporte, armazenagem e correio | I19: 08 - Informação e comunicação | J19: 09 - Atividades financeiras, de seguros e serviços relacionados | K19: 10 - Atividades imobiliárias | L19: 11 - Outras atividades de serviços | M19: 12 - Administração, defesa, saúde e educação públicas e seguridade social | N19: Exportacoes outros paises | O19: Exportacoes outras UFs | P19: Consumo do governo | Q19: Consumo das familias | R19: Consumo das ISFLSF | S19: FBCF | T19: Variacao de estoques
A20: 01 - Agropecuária | B20: =B$3 -> 4.1062249 | C20: =C$3 -> 0.00014277752 | D20: =D$3 -> 19.421779 | E20: =E$3 -> 0.0032435365 | F20: =F$3 -> 0.12137135 | G20: =G$3 -> 0.78017444 | H20: =H$3 -> 0 | I20: =I$3 -> 0 | ... T20: =T$3 -> 10.049434
A21: 02 - Indústrias extrativas | B21: =B$4 -> 1.0899909 | C21: =C$4 -> 0.61492013 | D21: =D$4 -> 18.46704 | E21: =E$4 -> 0.49506464 | F21: =F$4 -> 12.52948 | G21: =G$4 -> 0.067253295 | H21: =H$4 -> 0.0005667311 | I21: =I$4 -> 0 | ... T21: =T$4 -> 7.4328551
A22: 03 - Indústrias de transformação | B22: =B$5 -> 20.790808 | C22: =C$5 -> 0.53444087 | D22: =D$5 -> 32.217763 | E22: =E$5 -> 3.7361082 | F22: =F$5 -> 18.074284 | G22: =G$5 -> 8.2497499 | H22: =H$5 -> 6.8959244 | I22: =I$5 -> 0.56715642 | ... T22: =T$5 -> 19.200443
A23: 04 - Eletricidade e gás, água, esgoto e gestão de resíduos | B23: =B$6 -> 0 | C23: =C$6 -> 0 | D23: =D$6 -> 0 | E23: =E$6 -> 0 | F23: =F$6 -> 0 | G23: =G$6 -> 0 | H23: =H$6 -> 0 | I23: =I$6 -> 0 | ... T23: =T$6 -> 0
A24: 05 - Construção | B24: =B$7 -> 0 | C24: =C$7 -> 0 | D24: =D$7 -> 0 | E24: =E$7 -> 0 | F24: =F$7 -> 0 | G24: =G$7 -> 0 | H24: =H$7 -> 0 | I24: =I$7 -> 0 | ... T24: =T$7 -> 0
A25: 06 - Comércio | B25: =B$8 -> 0 | C25: =C$8 -> 0 | D25: =D$8 -> 0 | E25: =E$8 -> 0 | F25: =F$8 -> 0 | G25: =G$8 -> 0 | H25: =H$8 -> 0 | I25: =I$8 -> 0 | ... T25: =T$8 -> 0
A26: 07 - Transporte, armazenagem e correio | B26: =-B$16 -> -25.987024 | C26: =-C$16 -> -1.1495038 | D26: =-D$16 -> -70.106583 | E26: =-E$16 -> -4.2344164 | F26: =-F$16 -> -30.725135 | G26: =-G$16 -> -9.0971777 | H26: =-H$16 -> -6.8964911 | I26: =-I$16 -> -0.56715642 | ... T26: =-T$16 -> -36.682732
A27: 08 - Informação e comunicação | B27: =B$10 -> 0 | C27: =C$10 -> 0 | D27: =D$10 -> 0 | E27: =E$10 -> 0 | F27: =F$10 -> 0 | G27: =G$10 -> 0 | H27: =H$10 -> 0 | I27: =I$10 -> 0 | ... T27: =T$10 -> 0
A28: 09 - Atividades financeiras, de seguros e serviços relacionados | B28: =B$11 -> 0 | C28: =C$11 -> 0 | D28: =D$11 -> 0 | E28: =E$11 -> 0 | F28: =F$11 -> 0 | G28: =G$11 -> 0 | H28: =H$11 -> 0 | I28: =I$11 -> 0 | ... T28: =T$11 -> 0
A29: 10 - Atividades imobiliárias | B29: =B$12 -> 0 | C29: =C$12 -> 0 | D29: =D$12 -> 0 | E29: =E$12 -> 0 | F29: =F$12 -> 0 | G29: =G$12 -> 0 | H29: =H$12 -> 0 | I29: =I$12 -> 0 | ... T29: =T$12 -> 0
A30: 11 - Outras atividades de serviços | B30: =B$13 -> 0 | C30: =C$13 -> 0 | D30: =D$13 -> 0 | E30: =E$13 -> 0 | F30: =F$13 -> 0 | G30: =G$13 -> 0 | H30: =H$13 -> 0 | I30: =I$13 -> 0 | ... T30: =T$13 -> 0
A31: 12 - Administração, defesa, saúde e educação públicas e seguridade social | B31: =B$14 -> 0 | C31: =C$14 -> 0 | D31: =D$14 -> 0 | E31: =E$14 -> 0 | F31: =F$14 -> 0 | G31: =G$14 -> 0 | H31: =H$14 -> 0 | I31: =I$14 -> 0 | ... T31: =T$14 -> 0
A33: Conferencia: soma da coluna (deve ser 0) | B33: =SUM(B20:B31) -> 0 | C33: =SUM(C20:C31) -> 0 | D33: =SUM(D20:D31) -> 0 | E33: =SUM(E20:E31) -> 0 | F33: =SUM(F20:F31) -> 0 | G33: =SUM(G20:G31) -> -1.7763568e-15 | H33: =SUM(H20:H31) -> -2.6645353e-15 | I33: =SUM(I20:I31) -> -1.110223e-16 | ... T33: =SUM(T20:T31) -> 0

Sheet 08_M_impostos
A1: ETAPA 11a - base tributavel: excluindo Exportacoes outros paises
A2: Produto \ Destino | B2: 01 - Agropecuária | C2: 02 - Indústrias extrativas | D2: 03 - Indústrias de transformação | E2: 04 - Eletricidade e gás, água, esgoto e gestão de resíduos | F2: 05 - Construção | G2: 06 - Comércio | H2: 07 - Transporte, armazenagem e correio | I2: 08 - Informação e comunicação | J2: 09 - Atividades financeiras, de seguros e serviços relacionados | K2: 10 - Atividades imobiliárias | L2: 11 - Outras atividades de serviços | M2: 12 - Administração, defesa, saúde e educação públicas e seguridade social | N2: Exportacoes outros paises | O2: Exportacoes outras UFs | P2: Consumo do governo | Q2: Consumo das familias | R2: Consumo das ISFLSF | S2: FBCF | T2: Variacao de estoques | U2: Total do produto
A3: 01 - Agropecuária | B3: ='02_Usos'!$B$2 -> 336.52786 | C3: ='02_Usos'!$C$2 -> 0.011701408 | D3: ='02_Usos'!$D$2 -> 1591.7223 | E3: ='02_Usos'!$E$2 -> 0.26582577 | F3: ='02_Usos'!$F$2 -> 9.9470537 | G3: ='02_Usos'!$G$2 -> 63.939615 | H3: ='02_Usos'!$H$2 -> 0 | I3: ='02_Usos'!$I$2 -> 0 | J3: ='02_Usos'!$J$2 -> 0 | K3: ='02_Usos'!$K$2 -> 0 | L3: ='02_Usos'!$L$2 -> 67.900903 | M3: ='02_Usos'!$M$2 -> 45.176743 | N3: =0 -> 0 | O3: ='02_Usos'!$P$2 -> 1269.6183 | P3: ='02_Usos'!$R$2 -> 1.2191883 | Q3: ='02_Usos'!$S$2 -> 2973.5572 | R3: ='02_Usos'!$T$2 -> 0 | S3: ='02_Usos'!$U$2 -> 167.61783 | T3: ='02_Usos'!$V$2 -> 823.60672 | U3: =SUM(B3:T3) -> 7351.1113
A4: 02 - Indústrias extrativas | B4: ='02_Usos'!$B$3 -> 8.2404914 | C4: ='02_Usos'!$C$3 -> 4.6488867 | D4: ='02_Usos'!$D$3 -> 139.61354 | E4: ='02_Usos'!$E$3 -> 3.7427616 | F4: ='02_Usos'!$F$3 -> 94.724711 | G4: ='02_Usos'!$G$3 -> 0.50844481 | H4: ='02_Usos'!$H$3 -> 0.0042845705 | I4: ='02_Usos'!$I$3 -> 0 | J4: ='02_Usos'!$J$3 -> 0 | K4: ='02_Usos'!$K$3 -> 5.5097789 | L4: ='02_Usos'!$L$3 -> 0.3817976 | M4: ='02_Usos'!$M$3 -> 1.8826824 | N4: =0 -> 0 | O4: ='02_Usos'!$P$3 -> 81.848675 | P4: ='02_Usos'!$R$3 -> 0 | Q4: ='02_Usos'!$S$3 -> 0 | R4: ='02_Usos'!$T$3 -> 0 | S4: ='02_Usos'!$U$3 -> 0 | T4: ='02_Usos'!$V$3 -> 56.193479 | U4: =SUM(B4:T4) -> 397.29954
A5: 03 - Indústrias de transformação | B5: ='02_Usos'!$B$4 -> 2378.5487 | C5: ='02_Usos'!$C$4 -> 61.142098 | D5: ='02_Usos'!$D$4 -> 3685.8365 | E5: ='02_Usos'!$E$4 -> 427.4252 | F5: ='02_Usos'!$F$4 -> 2067.7679 | G5: ='02_Usos'!$G$4 -> 943.80323 | H5: ='02_Usos'!$H$4 -> 788.92036 | I5: ='02_Usos'!$I$4 -> 64.884884 | J5: ='02_Usos'!$J$4 -> 32.678772 | K5: ='02_Usos'!$K$4 -> 54.565436 | L5: ='02_Usos'!$L$4 -> 1245.9919 | M5: ='02_Usos'!$M$4 -> 994.02563 | N5: =0 -> 0 | O5: ='02_Usos'!$P$4 -> 5170.1451 | P5: ='02_Usos'!$R$4 -> 114.71822 | Q5: ='02_Usos'!$S$4 -> 23647.917 | R5: ='02_Usos'!$T$4 -> 0 | S5: ='02_Usos'!$U$4 -> 2369.6669 | T5: ='02_Usos'!$V$4 -> 2196.6048 | U5: =SUM(B5:T5) -> 46244.643
A6: 04 - Eletricidade e gás, água, esgoto e gestão de resíduos | B6: ='02_Usos'!$B$5 -> 154.80937 | C6: ='02_Usos'!$C$5 -> 7.900908 | D6: ='02_Usos'!$D$5 -> 136.96591 | E6: ='02_Usos'!$E$5 -> 1480.3103 | F6: ='02_Usos'!$F$5 -> 11.009585 | G6: ='02_Usos'!$G$5 -> 255.58089 | H6: ='02_Usos'!$H$5 -> 26.111449 | I6: ='02_Usos'!$I$5 -> 21.74082 | J6: ='02_Usos'!$J$5 -> 12.939323 | K6: ='02_Usos'!$K$5 -> 7.1191336 | L6: ='02_Usos'!$L$5 -> 216.79545 | M6: ='02_Usos'!$M$5 -> 382.08587 | N6: =0 -> 0 | O6: ='02_Usos'!$P$5 -> 613.90952 | P6: ='02_Usos'!$R$5 -> 0 | Q6: ='02_Usos'!$S$5 -> 1221.0253 | R6: ='02_Usos'!$T$5 -> 0 | S6: ='02_Usos'!$U$5 -> 0 | T6: ='02_Usos'!$V$5 -> 1.671612 | U6: =SUM(B6:T6) -> 4549.9755
A7: 05 - Construção | B7: ='02_Usos'!$B$6 -> 3.8224895 | C7: ='02_Usos'!$C$6 -> 0.013787086 | D7: ='02_Usos'!$D$6 -> 2.264245 | E7: ='02_Usos'!$E$6 -> 79.02222 | F7: ='02_Usos'!$F$6 -> 705.14023 | G7: ='02_Usos'!$G$6 -> 11.177303 | H7: ='02_Usos'!$H$6 -> 8.3512823 | I7: ='02_Usos'!$I$6 -> 33.955801 | J7: ='02_Usos'!$J$6 -> 4.9087163 | K7: ='02_Usos'!$K$6 -> 10.536414 | L7: ='02_Usos'!$L$6 -> 24.851141 | M7: ='02_Usos'!$M$6 -> 362.99379 | N7: =0 -> 0 | O7: ='02_Usos'!$P$6 -> 0 | P7: ='02_Usos'!$R$6 -> 0 | Q7: ='02_Usos'!$S$6 -> 0 | R7: ='02_Usos'!$T$6 -> 0 | S7: ='02_Usos'!$U$6 -> 4868.1849 | T7: ='02_Usos'!$V$6 -> 0 | U7: =SUM(B7:T7) -> 6115.2223
A8: 06 - Comércio | B8: ='02_Usos'!$B$7 -> 4.0645391 | C8: ='02_Usos'!$C$7 -> 0.19920343 | D8: ='02_Usos'!$D$7 -> 78.202412 | E8: ='02_Usos'!$E$7 -> 12.218688 | F8: ='02_Usos'!$F$7 -> 5.2675482 | G8: ='02_Usos'!$G$7 -> 70.450246 | H8: ='02_Usos'!$H$7 -> 46.636504 | I8: ='02_Usos'!$I$7 -> 23.572888 | J8: ='02_Usos'!$J$7 -> 0.47196288 | K8: ='02_Usos'!$K$7 -> 0.125092 | L8: ='02_Usos'!$L$7 -> 12.265165 | M8: ='02_Usos'!$M$7 -> 53.081127 | N8: =0 -> 0 | O8: ='02_Usos'!$P$7 -> 0 | P8: ='02_Usos'!$R$7 -> 0 | Q8: ='02_Usos'!$S$7 -> 483.65278 | R8: ='02_Usos'!$T$7 -> 0 | S8: ='02_Usos'!$U$7 -> 0 | T8: ='02_Usos'!$V$7 -> 0 | U8: =SUM(B8:T8) -> 790.20816
A9: 07 - Transporte, armazenagem e correio | B9: ='02_Usos'!$B$8 -> 112.1417 | C9: ='02_Usos'!$C$8 -> 6.233409 | D9: ='02_Usos'!$D$8 -> 405.32122 | E9: ='02_Usos'!$E$8 -> 22.46871 | F9: ='02_Usos'!$F$8 -> 35.013467 | G9: ='02_Usos'!$G$8 -> 475.61402 | H9: ='02_Usos'!$H$8 -> 304.93613 | I9: ='02_Usos'!$I$8 -> 11.000165 | J9: ='02_Usos'!$J$8 -> 27.967707 | K9: ='02_Usos'!$K$8 -> 1.895719 | L9: ='02_Usos'!$L$8 -> 133.12582 | M9: ='02_Usos'!$M$8 -> 205.00275 | N9: =0 -> 0 | O9: ='02_Usos'!$P$8 -> 0 | P9: ='02_Usos'!$R$8 -> 0 | Q9: ='02_Usos'!$S$8 -> 1177.5397 | R9: ='02_Usos'!$T$8 -> 0 | S9: ='02_Usos'!$U$8 -> 0 | T9: ='02_Usos'!$V$8 -> 0 | U9: =SUM(B9:T9) -> 2918.2605
A10: 08 - Informação e comunicação | B10: ='02_Usos'!$B$9 -> 0.61710297 | C10: ='02_Usos'!$C$9 -> 0.22864689 | D10: ='02_Usos'!$D$9 -> 48.77609 | E10: ='02_Usos'!$E$9 -> 41.137019 | F10: ='02_Usos'!$F$9 -> 16.744161 | G10: ='02_Usos'!$G$9 -> 154.23642 | H10: ='02_Usos'!$H$9 -> 31.785982 | I10: ='02_Usos'!$I$9 -> 261.46494 | J10: ='02_Usos'!$J$9 -> 105.33487 | K10: ='02_Usos'!$K$9 -> 5.9821949 | L10: ='02_Usos'!$L$9 -> 204.74525 | M10: ='02_Usos'!$M$9 -> 399.41456 | N10: =0 -> 0 | O10: ='02_Usos'!$P$9 -> 26.678261 | P10: ='02_Usos'!$R$9 -> 0 | Q10: ='02_Usos'!$S$9 -> 824.8463 | R10: ='02_Usos'!$T$9 -> 0 | S10: ='02_Usos'!$U$9 -> 110.23355 | T10: ='02_Usos'!$V$9 -> -0.45588277 | U10: =SUM(B10:T10) -> 2231.7695
A11: 09 - Atividades financeiras, de seguros e serviços relacionados | B11: ='02_Usos'!$B$10 -> 130.45603 | C11: ='02_Usos'!$C$10 -> 7.3087877 | D11: ='02_Usos'!$D$10 -> 183.00486 | E11: ='02_Usos'!$E$10 -> 130.82105 | F11: ='02_Usos'!$F$10 -> 96.771951 | G11: ='02_Usos'!$G$10 -> 246.23948 | H11: ='02_Usos'!$H$10 -> 71.125789 | I11: ='02_Usos'!$I$10 -> 66.780516 | J11: ='02_Usos'!$J$10 -> 366.11925 | K11: ='02_Usos'!$K$10 -> 153.22607 | L11: ='02_Usos'!$L$10 -> 148.85236 | M11: ='02_Usos'!$M$10 -> 670.49076 | N11: =0 -> 0 | O11: ='02_Usos'!$P$10 -> 0 | P11: ='02_Usos'!$R$10 -> 7.7394705 | Q11: ='02_Usos'!$S$10 -> 3803.7186 | R11: ='02_Usos'!$T$10 -> 0 | S11: ='02_Usos'!$U$10 -> 0 | T11: ='02_Usos'!$V$10 -> 0 | U11: =SUM(B11:T11) -> 6082.6549
A12: 10 - Atividades imobiliárias | B12: ='02_Usos'!$B$11 -> 0.23503353 | C12: ='02_Usos'!$C$11 -> 0.45746481 | D12: ='02_Usos'!$D$11 -> 21.746612 | E12: ='02_Usos'!$E$11 -> 23.239619 | F12: ='02_Usos'!$F$11 -> 13.560324 | G12: ='02_Usos'!$G$11 -> 369.93406 | H12: ='02_Usos'!$H$11 -> 45.167673 | I12: ='02_Usos'!$I$11 -> 25.297465 | J12: ='02_Usos'!$J$11 -> 22.641905 | K12: ='02_Usos'!$K$11 -> 12.590016 | L12: ='02_Usos'!$L$11 -> 189.57111 | M12: ='02_Usos'!$M$11 -> 52.578599 | N12: =0 -> 0 | O12: ='02_Usos'!$P$11 -> 3.8794981 | P12: ='02_Usos'!$R$11 -> 0 | Q12: ='02_Usos'!$S$11 -> 3685.5422 | R12: ='02_Usos'!$T$11 -> 0 | S12: ='02_Usos'!$U$11 -> 0 | T12: ='02_Usos'!$V$11 -> 0 | U12: =SUM(B12:T12) -> 4466.4416
A13: 11 - Outras atividades de serviços | B13: ='02_Usos'!$B$12 -> 42.118355 | C13: ='02_Usos'!$C$12 -> 12.527528 | D13: ='02_Usos'!$D$12 -> 458.77529 | E13: ='02_Usos'!$E$12 -> 286.22536 | F13: ='02_Usos'!$F$12 -> 178.98604 | G13: ='02_Usos'!$G$12 -> 998.8851 | H13: ='02_Usos'!$H$12 -> 184.47089 | I13: ='02_Usos'!$I$12 -> 338.46968 | J13: ='02_Usos'!$J$12 -> 261.46515 | K13: ='02_Usos'!$K$12 -> 34.804537 | L13: ='02_Usos'!$L$12 -> 903.45327 | M13: ='02_Usos'!$M$12 -> 1594.054 | N13: =0 -> 0 | O13: ='02_Usos'!$P$12 -> 213.00548 | P13: ='02_Usos'!$R$12 -> 564.58529 | Q13: ='02_Usos'!$S$12 -> 8822.4347 | R13: ='02_Usos'!$T$12 -> 462.8832 | S13: ='02_Usos'!$U$12 -> 158.71751 | T13: ='02_Usos'!$V$12 -> 0 | U13: =SUM(B13:T13) -> 15515.861
A14: 12 - Administração, defesa, saúde e educação públicas e seguridade social | B14: ='02_Usos'!$B$13 -> 0 | C14: ='02_Usos'!$C$13 -> 0 | D14: ='02_Usos'!$D$13 -> 0 | E14: ='02_Usos'!$E$13 -> 0 | F14: ='02_Usos'!$F$13 -> 0 | G14: ='02_Usos'!$G$13 -> 0 | H14: ='02_Usos'!$H$13 -> 0 | I14: ='02_Usos'!$I$13 -> 0 | J14: ='02_Usos'!$J$13 -> 0 | K14: ='02_Usos'!$K$13 -> 0 | L14: ='02_Usos'!$L$13 -> 0 | M14: ='02_Usos'!$M$13 -> 0 | N14: =0 -> 0 | O14: ='02_Usos'!$P$13 -> 0 | P14: ='02_Usos'!$R$13 -> 19737.217 | Q14: ='02_Usos'!$S$13 -> 0 | R14: ='02_Usos'!$T$13 -> 0 | S14: ='02_Usos'!$U$13 -> 0 | T14: ='02_Usos'!$V$13 -> 0 | U14: =SUM(B14:T14) -> 19737.217
A16: ETAPA 11b - ALFA da base tributavel
A17: Produto \ Destino | B17: 01 - Agropecuária | C17: 02 - Indústrias extrativas | D17: 03 - Indústrias de transformação | E17: 04 - Eletricidade e gás, água, esgoto e gestão de resíduos | F17: 05 - Construção | G17: 06 - Comércio | H17: 07 - Transporte, armazenagem e correio | I17: 08 - Informação e comunicação | J17: 09 - Atividades financeiras, de seguros e serviços relacionados | K17: 10 - Atividades imobiliárias | L17: 11 - Outras atividades de serviços | M17: 12 - Administração, defesa, saúde e educação públicas e seguridade social | N17: Exportacoes outros paises | O17: Exportacoes outras UFs | P17: Consumo do governo | Q17: Consumo das familias | R17: Consumo das ISFLSF | S17: FBCF | T17: Variacao de estoques | U17: Soma da linha (deve ser 1)
A18: 01 - Agropecuária | B18: =IF($U$3=0,0,B$3/$U$3) -> 0.045779182 | C18: =IF($U$3=0,0,C$3/$U$3) -> 1.5917877e-06 | D18: =IF($U$3=0,0,D$3/$U$3) -> 0.21652812 | E18: =IF($U$3=0,0,E$3/$U$3) -> 3.6161304e-05 | F18: =IF($U$3=0,0,F$3/$U$3) -> 0.0013531361 | G18: =IF($U$3=0,0,G$3/$U$3) -> 0.0086979523 | H18: =IF($U$3=0,0,H$3/$U$3) -> 0 | I18: =IF($U$3=0,0,I$3/$U$3) -> 0 | ... T18: =IF($U$3=0,0,T$3/$U$3) -> 0.1120384 | U18: =SUM(B18:T18) -> 1
A19: 02 - Indústrias extrativas | B19: =IF($U$4=0,0,B$4/$U$4) -> 0.020741256 | C19: =IF($U$4=0,0,C$4/$U$4) -> 0.011701213 | D19: =IF($U$4=0,0,D$4/$U$4) -> 0.35140626 | E19: =IF($U$4=0,0,E$4/$U$4) -> 0.0094205033 | F19: =IF($U$4=0,0,F$4/$U$4) -> 0.2384214 | G19: =IF($U$4=0,0,G$4/$U$4) -> 0.0012797518 | H19: =IF($U$4=0,0,H$4/$U$4) -> 1.0784232e-05 | I19: =IF($U$4=0,0,I$4/$U$4) -> 0 | ... T19: =IF($U$4=0,0,T$4/$U$4) -> 0.14143857 | U19: =SUM(B19:T19) -> 1
A20: 03 - Indústrias de transformação | B20: =IF($U$5=0,0,B$5/$U$5) -> 0.051434037 | C20: =IF($U$5=0,0,C$5/$U$5) -> 0.0013221444 | D20: =IF($U$5=0,0,D$5/$U$5) -> 0.079702993 | E20: =IF($U$5=0,0,E$5/$U$5) -> 0.0092426965 | F20: =IF($U$5=0,0,F$5/$U$5) -> 0.044713674 | G20: =IF($U$5=0,0,G$5/$U$5) -> 0.02040892 | H20: =IF($U$5=0,0,H$5/$U$5) -> 0.017059714 | I20: =IF($U$5=0,0,I$5/$U$5) -> 0.0014030789 | ... T20: =IF($U$5=0,0,T$5/$U$5) -> 0.047499659 | U20: =SUM(B20:T20) -> 1
A21: 04 - Eletricidade e gás, água, esgoto e gestão de resíduos | B21: =IF($U$6=0,0,B$6/$U$6) -> 0.03402422 | C21: =IF($U$6=0,0,C$6/$U$6) -> 0.0017364727 | D21: =IF($U$6=0,0,D$6/$U$6) -> 0.030102561 | E21: =IF($U$6=0,0,E$6/$U$6) -> 0.32534468 | F21: =IF($U$6=0,0,F$6/$U$6) -> 0.0024197021 | G21: =IF($U$6=0,0,G$6/$U$6) -> 0.056171928 | H21: =IF($U$6=0,0,H$6/$U$6) -> 0.0057388108 | I21: =IF($U$6=0,0,I$6/$U$6) -> 0.0047782279 | ... T21: =IF($U$6=0,0,T$6/$U$6) -> 0.00036738923 | U21: =SUM(B21:T21) -> 1
A22: 05 - Construção | B22: =IF($U$7=0,0,B$7/$U$7) -> 0.00062507776 | C22: =IF($U$7=0,0,C$7/$U$7) -> 2.2545518e-06 | D22: =IF($U$7=0,0,D$7/$U$7) -> 0.00037026373 | E22: =IF($U$7=0,0,E$7/$U$7) -> 0.012922215 | F22: =IF($U$7=0,0,F$7/$U$7) -> 0.11530901 | G22: =IF($U$7=0,0,G$7/$U$7) -> 0.0018277835 | H22: =IF($U$7=0,0,H$7/$U$7) -> 0.0013656547 | I22: =IF($U$7=0,0,I$7/$U$7) -> 0.0055526682 | ... T22: =IF($U$7=0,0,T$7/$U$7) -> 0 | U22: =SUM(B22:T22) -> 1
A23: 06 - Comércio | B23: =IF($U$8=0,0,B$8/$U$8) -> 0.0051436308 | C23: =IF($U$8=0,0,C$8/$U$8) -> 0.00025208982 | D23: =IF($U$8=0,0,D$8/$U$8) -> 0.098964319 | E23: =IF($U$8=0,0,E$8/$U$8) -> 0.015462619 | F23: =IF($U$8=0,0,F$8/$U$8) -> 0.0066660261 | G23: =IF($U$8=0,0,G$8/$U$8) -> 0.089154036 | H23: =IF($U$8=0,0,H$8/$U$8) -> 0.059017999 | I23: =IF($U$8=0,0,I$8/$U$8) -> 0.029831238 | ... T23: =IF($U$8=0,0,T$8/$U$8) -> 0 | U23: =SUM(B23:T23) -> 1
A24: 07 - Transporte, armazenagem e correio | B24: =IF($U$9=0,0,B$9/$U$9) -> 0.038427583 | C24: =IF($U$9=0,0,C$9/$U$9) -> 0.0021360015 | D24: =IF($U$9=0,0,D$9/$U$9) -> 0.13889138 | E24: =IF($U$9=0,0,E$9/$U$9) -> 0.0076993503 | F24: =IF($U$9=0,0,F$9/$U$9) -> 0.011998061 | G24: =IF($U$9=0,0,G$9/$U$9) -> 0.1629786 | H24: =IF($U$9=0,0,H$9/$U$9) -> 0.10449243 | I24: =IF($U$9=0,0,I$9/$U$9) -> 0.0037694252 | ... T24: =IF($U$9=0,0,T$9/$U$9) -> 0 | U24: =SUM(B24:T24) -> 1
A25: 08 - Informação e comunicação | B25: =IF($U$10=0,0,B$10/$U$10) -> 0.00027650838 | C25: =IF($U$10=0,0,C$10/$U$10) -> 0.00010245094 | D25: =IF($U$10=0,0,D$10/$U$10) -> 0.021855344 | E25: =IF($U$10=0,0,E$10/$U$10) -> 0.018432468 | F25: =IF($U$10=0,0,F$10/$U$10) -> 0.007502639 | G25: =IF($U$10=0,0,G$10/$U$10) -> 0.069109478 | H25: =IF($U$10=0,0,H$10/$U$10) -> 0.014242503 | I25: =IF($U$10=0,0,I$10/$U$10) -> 0.11715589 | ... T25: =IF($U$10=0,0,T$10/$U$10) -> -0.00020426965 | U25: =SUM(B25:T25) -> 1
A26: 09 - Atividades financeiras, de seguros e serviços relacionados | B26: =IF($U$11=0,0,B$11/$U$11) -> 0.021447218 | C26: =IF($U$11=0,0,C$11/$U$11) -> 0.0012015785 | D26: =IF($U$11=0,0,D$11/$U$11) -> 0.030086346 | E26: =IF($U$11=0,0,E$11/$U$11) -> 0.021507228 | F26: =IF($U$11=0,0,F$11/$U$11) -> 0.015909492 | G26: =IF($U$11=0,0,G$11/$U$11) -> 0.040482237 | H26: =IF($U$11=0,0,H$11/$U$11) -> 0.011693215 | I26: =IF($U$11=0,0,I$11/$U$11) -> 0.010978843 | ... T26: =IF($U$11=0,0,T$11/$U$11) -> 0 | U26: =SUM(B26:T26) -> 1
A27: 10 - Atividades imobiliárias | B27: =IF($U$12=0,0,B$12/$U$12) -> 5.2622099e-05 | C27: =IF($U$12=0,0,C$12/$U$12) -> 0.00010242266 | D27: =IF($U$12=0,0,D$12/$U$12) -> 0.0048688898 | E27: =IF($U$12=0,0,E$12/$U$12) -> 0.005203162 | F27: =IF($U$12=0,0,F$12/$U$12) -> 0.0030360464 | G27: =IF($U$12=0,0,G$12/$U$12) -> 0.082825231 | H27: =IF($U$12=0,0,H$12/$U$12) -> 0.010112675 | I27: =IF($U$12=0,0,I$12/$U$12) -> 0.005663897 | ... T27: =IF($U$12=0,0,T$12/$U$12) -> 0 | U27: =SUM(B27:T27) -> 1
A28: 11 - Outras atividades de serviços | B28: =IF($U$13=0,0,B$13/$U$13) -> 0.0027145354 | C28: =IF($U$13=0,0,C$13/$U$13) -> 0.00080740141 | D28: =IF($U$13=0,0,D$13/$U$13) -> 0.029568149 | E28: =IF($U$13=0,0,E$13/$U$13) -> 0.018447275 | F28: =IF($U$13=0,0,F$13/$U$13) -> 0.011535682 | G28: =IF($U$13=0,0,G$13/$U$13) -> 0.064378321 | H28: =IF($U$13=0,0,H$13/$U$13) -> 0.011889181 | I28: =IF($U$13=0,0,I$13/$U$13) -> 0.02181443 | ... T28: =IF($U$13=0,0,T$13/$U$13) -> 0 | U28: =SUM(B28:T28) -> 1
A29: 12 - Administração, defesa, saúde e educação públicas e seguridade social | B29: =IF($U$14=0,0,B$14/$U$14) -> 0 | C29: =IF($U$14=0,0,C$14/$U$14) -> 0 | D29: =IF($U$14=0,0,D$14/$U$14) -> 0 | E29: =IF($U$14=0,0,E$14/$U$14) -> 0 | F29: =IF($U$14=0,0,F$14/$U$14) -> 0 | G29: =IF($U$14=0,0,G$14/$U$14) -> 0 | H29: =IF($U$14=0,0,H$14/$U$14) -> 0 | I29: =IF($U$14=0,0,I$14/$U$14) -> 0 | ... T29: =IF($U$14=0,0,T$14/$U$14) -> 0 | U29: =SUM(B29:T29) -> 1
A31: ETAPA 11c - impostos liquidos distribuidos (ALFA x imposto do produto)
A32: Produto \ Destino | B32: 01 - Agropecuária | C32: 02 - Indústrias extrativas | D32: 03 - Indústrias de transformação | E32: 04 - Eletricidade e gás, água, esgoto e gestão de resíduos | F32: 05 - Construção | G32: 06 - Comércio | H32: 07 - Transporte, armazenagem e correio | I32: 08 - Informação e comunicação | J32: 09 - Atividades financeiras, de seguros e serviços relacionados | K32: 10 - Atividades imobiliárias | L32: 11 - Outras atividades de serviços | M32: 12 - Administração, defesa, saúde e educação públicas e seguridade social | N32: Exportacoes outros paises | O32: Exportacoes outras UFs | P32: Consumo do governo | Q32: Consumo das familias | R32: Consumo das ISFLSF | S32: FBCF | T32: Variacao de estoques | U32: Soma da linha | V32: Imposto do produto (TRUR) | W32: Diferenca
A33: 01 - Agropecuária | B33: =B$18*'01_Recursos'!$U$2 -> 6.0950216 | C33: =C$18*'01_Recursos'!$U$2 -> 0.00021192996 | D33: =D$18*'01_Recursos'!$U$2 -> 28.828466 | E33: =E$18*'01_Recursos'!$U$2 -> 0.0048145013 | F33: =F$18*'01_Recursos'!$U$2 -> 0.18015598 | G33: =G$18*'01_Recursos'!$U$2 -> 1.1580418 | H33: =H$18*'01_Recursos'!$U$2 -> 0 | I33: =I$18*'01_Recursos'!$U$2 -> 0 | ... T33: =T$18*'01_Recursos'!$U$2 -> 14.916746 | U33: =SUM(B33:T33) -> 133.13959 | V33: ='01_Recursos'!$U$2 -> 133.13959 | W33: =U33-V33 -> 0
A34: 02 - Indústrias extrativas | B34: =B$19*'01_Recursos'!$U$3 -> 0.21531806 | C34: =C$19*'01_Recursos'!$U$3 -> 0.12147204 | D34: =D$19*'01_Recursos'!$U$3 -> 3.6480007 | E34: =E$19*'01_Recursos'!$U$3 -> 0.097795646 | F34: =F$19*'01_Recursos'!$U$3 -> 2.475088 | G34: =G$19*'01_Recursos'!$U$3 -> 0.013285294 | H34: =H$19*'01_Recursos'!$U$3 -> 0.00011195272 | I34: =I$19*'01_Recursos'!$U$3 -> 0 | ... T34: =T$19*'01_Recursos'!$U$3 -> 1.4682948 | U34: =SUM(B34:T34) -> 10.381149 | V34: ='01_Recursos'!$U$3 -> 10.381149 | W34: =U34-V34 -> 0
A35: 03 - Indústrias de transformação | B35: =B$20*'01_Recursos'!$U$4 -> 194.78657 | C35: =C$20*'01_Recursos'!$U$4 -> 5.007112 | D35: =D$20*'01_Recursos'!$U$4 -> 301.84433 | E35: =E$20*'01_Recursos'!$U$4 -> 35.003147 | F35: =F$20*'01_Recursos'!$U$4 -> 169.33579 | G35: =G$20*'01_Recursos'!$U$4 -> 77.290911 | H35: =H$20*'01_Recursos'!$U$4 -> 64.607083 | I35: =I$20*'01_Recursos'!$U$4 -> 5.31362 | ... T35: =T$20*'01_Recursos'!$U$4 -> 179.88663 | U35: =SUM(B35:T35) -> 3787.1142 | V35: ='01_Recursos'!$U$4 -> 3787.1142 | W35: =U35-V35 -> 0
A36: 04 - Eletricidade e gás, água, esgoto e gestão de resíduos | B36: =B$21*'01_Recursos'!$U$5 -> 15.183514 | C36: =C$21*'01_Recursos'!$U$5 -> 0.77491144 | D36: =D$21*'01_Recursos'!$U$5 -> 13.43345 | E36: =E$21*'01_Recursos'!$U$5 -> 145.18703 | F36: =F$21*'01_Recursos'!$U$5 -> 1.0798067 | G36: =G$21*'01_Recursos'!$U$5 -> 25.067063 | H36: =H$21*'01_Recursos'!$U$5 -> 2.5609791 | I36: =I$21*'01_Recursos'!$U$5 -> 2.1323131 | ... T36: =T$21*'01_Recursos'!$U$5 -> 0.16394967 | U36: =SUM(B36:T36) -> 446.25606 | V36: ='01_Recursos'!$U$5 -> 446.25606 | W36: =U36-V36 -> 0
A37: 05 - Construção | B37: =B$22*'01_Recursos'!$U$6 -> 0.097766353 | C37: =C$22*'01_Recursos'!$U$6 -> 0.00035262703 | D37: =D$22*'01_Recursos'!$U$6 -> 0.05791173 | E37: =E$22*'01_Recursos'!$U$6 -> 2.0211211 | F37: =F$22*'01_Recursos'!$U$6 -> 18.035102 | G37: =G$22*'01_Recursos'!$U$6 -> 0.2858776 | H37: =H$22*'01_Recursos'!$U$6 -> 0.21359756 | I37: =I$22*'01_Recursos'!$U$6 -> 0.86847454 | ... T37: =T$22*'01_Recursos'!$U$6 -> 0 | U37: =SUM(B37:T37) -> 156.40671 | V37: ='01_Recursos'!$U$6 -> 156.40671 | W37: =U37-V37 -> 0
A38: 06 - Comércio | B38: =B$23*'01_Recursos'!$U$7 -> 0.04099431 | C38: =C$23*'01_Recursos'!$U$7 -> 0.0020091349 | D38: =D$23*'01_Recursos'!$U$7 -> 0.78873739 | E38: =E$23*'01_Recursos'!$U$7 -> 0.12323579 | F38: =F$23*'01_Recursos'!$U$7 -> 0.053127674 | G38: =G$23*'01_Recursos'!$U$7 -> 0.71055025 | H38: =H$23*'01_Recursos'!$U$7 -> 0.47036854 | I38: =I$23*'01_Recursos'!$U$7 -> 0.23775249 | ... T38: =T$23*'01_Recursos'!$U$7 -> 0 | U38: =SUM(B38:T38) -> 7.9699169 | V38: ='01_Recursos'!$U$7 -> 7.9699169 | W38: =U38-V38 -> 0
A39: 07 - Transporte, armazenagem e correio | B39: =B$24*'01_Recursos'!$U$8 -> 5.988261 | C39: =C$24*'01_Recursos'!$U$8 -> 0.33285817 | D39: =D$24*'01_Recursos'!$U$8 -> 21.643772 | E39: =E$24*'01_Recursos'!$U$8 -> 1.199808 | F39: =F$24*'01_Recursos'!$U$8 -> 1.8696862 | G39: =G$24*'01_Recursos'!$U$8 -> 25.397341 | H39: =H$24*'01_Recursos'!$U$8 -> 16.283302 | I39: =I$24*'01_Recursos'!$U$8 -> 0.58739844 | ... T39: =T$24*'01_Recursos'!$U$8 -> 0 | U39: =SUM(B39:T39) -> 155.83236 | V39: ='01_Recursos'!$U$8 -> 155.83236 | W39: =U39-V39 -> 0
A40: 08 - Informação e comunicação | B40: =B$25*'01_Recursos'!$U$9 -> 0.064583487 | C40: =C$25*'01_Recursos'!$U$9 -> 0.023929253 | D40: =D$25*'01_Recursos'!$U$9 -> 5.1047073 | E40: =E$25*'01_Recursos'!$U$9 -> 4.3052332 | F40: =F$25*'01_Recursos'!$U$9 -> 1.7523758 | G40: =G$25*'01_Recursos'!$U$9 -> 16.141757 | H40: =H$25*'01_Recursos'!$U$9 -> 3.3265917 | I40: =I$25*'01_Recursos'!$U$9 -> 27.363857 | ... T40: =T$25*'01_Recursos'!$U$9 -> -0.047710837 | U40: =SUM(B40:T40) -> 233.56792 | V40: ='01_Recursos'!$U$9 -> 233.56792 | W40: =U40-V40 -> 0
A41: 09 - Atividades financeiras, de seguros e serviços relacionados | B41: =B$26*'01_Recursos'!$U$10 -> 5.3914423 | C41: =C$26*'01_Recursos'!$U$10 -> 0.30205509 | D41: =D$26*'01_Recursos'!$U$10 -> 7.5631626 | E41: =E$26*'01_Recursos'!$U$10 -> 5.4065276 | F41: =F$26*'01_Recursos'!$U$10 -> 3.9993582 | G41: =G$26*'01_Recursos'!$U$10 -> 10.176501 | H41: =H$26*'01_Recursos'!$U$10 -> 2.9394624 | I41: =I$26*'01_Recursos'!$U$10 -> 2.7598824 | ... T41: =T$26*'01_Recursos'!$U$10 -> 0 | U41: =SUM(B41:T41) -> 251.38189 | V41: ='01_Recursos'!$U$10 -> 251.38189 | W41: =U41-V41 -> 0
A42: 10 - Atividades imobiliárias | B42: =B$27*'01_Recursos'!$U$11 -> 0.00011034586 | C42: =C$27*'01_Recursos'!$U$11 -> 0.0002147751 | D42: =D$27*'01_Recursos'!$U$11 -> 0.010209814 | E42: =E$27*'01_Recursos'!$U$11 -> 0.010910766 | F42: =F$27*'01_Recursos'!$U$11 -> 0.0063664348 | G42: =G$27*'01_Recursos'!$U$11 -> 0.1736803 | H42: =H$27*'01_Recursos'!$U$11 -> 0.021205765 | I42: =I$27*'01_Recursos'!$U$11 -> 0.011876904 | ... T42: =T$27*'01_Recursos'!$U$11 -> 0 | U42: =SUM(B42:T42) -> 2.0969491 | V42: ='01_Recursos'!$U$11 -> 2.0969491 | W42: =U42-V42 -> 0
A43: 11 - Outras atividades de serviços | B43: =B$28*'01_Recursos'!$U$12 -> 1.3569118 | C43: =C$28*'01_Recursos'!$U$12 -> 0.40359484 | D43: =D$28*'01_Recursos'!$U$12 -> 14.780197 | E43: =E$28*'01_Recursos'!$U$12 -> 9.2212187 | F43: =F$28*'01_Recursos'!$U$12 -> 5.7663283 | G43: =G$28*'01_Recursos'!$U$12 -> 32.180719 | H43: =H$28*'01_Recursos'!$U$12 -> 5.9430316 | I43: =I$28*'01_Recursos'!$U$12 -> 10.904355 | ... T43: =T$28*'01_Recursos'!$U$12 -> 0 | U43: =SUM(B43:T43) -> 499.86888 | V43: ='01_Recursos'!$U$12 -> 499.86888 | W43: =U43-V43 -> 0
A44: 12 - Administração, defesa, saúde e educação públicas e seguridade social | B44: =B$29*'01_Recursos'!$U$13 -> 0 | C44: =C$29*'01_Recursos'!$U$13 -> 0 | D44: =D$29*'01_Recursos'!$U$13 -> 0 | E44: =E$29*'01_Recursos'!$U$13 -> 0 | F44: =F$29*'01_Recursos'!$U$13 -> 0 | G44: =G$29*'01_Recursos'!$U$13 -> 0 | H44: =H$29*'01_Recursos'!$U$13 -> 0 | I44: =I$29*'01_Recursos'!$U$13 -> 0 | ... T44: =T$29*'01_Recursos'!$U$13 -> 0 | U44: =SUM(B44:T44) -> 0 | V44: ='01_Recursos'!$U$13 -> 0 | W44: =U44-V44 -> 0

Sheet 09_M_importacoes
A1: ETAPA 12a - base das importacoes: excluindo Exportacoes outros paises e Exportacoes outras UFs
A2: Produto \ Destino | B2: 01 - Agropecuária | C2: 02 - Indústrias extrativas | D2: 03 - Indústrias de transformação | E2: 04 - Eletricidade e gás, água, esgoto e gestão de resíduos | F2: 05 - Construção | G2: 06 - Comércio | H2: 07 - Transporte, armazenagem e correio | I2: 08 - Informação e comunicação | J2: 09 - Atividades financeiras, de seguros e serviços relacionados | K2: 10 - Atividades imobiliárias | L2: 11 - Outras atividades de serviços | M2: 12 - Administração, defesa, saúde e educação públicas e seguridade social | N2: Exportacoes outros paises | O2: Exportacoes outras UFs | P2: Consumo do governo | Q2: Consumo das familias | R2: Consumo das ISFLSF | S2: FBCF | T2: Variacao de estoques | U2: Total do produto
A3: 01 - Agropecuária | B3: ='02_Usos'!$B$2 -> 336.52786 | C3: ='02_Usos'!$C$2 -> 0.011701408 | D3: ='02_Usos'!$D$2 -> 1591.7223 | E3: ='02_Usos'!$E$2 -> 0.26582577 | F3: ='02_Usos'!$F$2 -> 9.9470537 | G3: ='02_Usos'!$G$2 -> 63.939615 | H3: ='02_Usos'!$H$2 -> 0 | I3: ='02_Usos'!$I$2 -> 0 | J3: ='02_Usos'!$J$2 -> 0 | K3: ='02_Usos'!$K$2 -> 0 | L3: ='02_Usos'!$L$2 -> 67.900903 | M3: ='02_Usos'!$M$2 -> 45.176743 | N3: =0 -> 0 | O3: 1269.6183 | P3: ='02_Usos'!$R$2 -> 1.2191883 | Q3: ='02_Usos'!$S$2 -> 2973.5572 | R3: ='02_Usos'!$T$2 -> 0 | S3: ='02_Usos'!$U$2 -> 167.61783 | T3: ='02_Usos'!$V$2 -> 823.60672 | U3: =SUM(B3:T3) -> 7351.1113
A4: 02 - Indústrias extrativas | B4: ='02_Usos'!$B$3 -> 8.2404914 | C4: ='02_Usos'!$C$3 -> 4.6488867 | D4: ='02_Usos'!$D$3 -> 139.61354 | E4: ='02_Usos'!$E$3 -> 3.7427616 | F4: ='02_Usos'!$F$3 -> 94.724711 | G4: ='02_Usos'!$G$3 -> 0.50844481 | H4: ='02_Usos'!$H$3 -> 0.0042845705 | I4: ='02_Usos'!$I$3 -> 0 | J4: ='02_Usos'!$J$3 -> 0 | K4: ='02_Usos'!$K$3 -> 5.5097789 | L4: ='02_Usos'!$L$3 -> 0.3817976 | M4: ='02_Usos'!$M$3 -> 1.8826824 | N4: =0 -> 0 | O4: 81.848675 | P4: ='02_Usos'!$R$3 -> 0 | Q4: ='02_Usos'!$S$3 -> 0 | R4: ='02_Usos'!$T$3 -> 0 | S4: ='02_Usos'!$U$3 -> 0 | T4: ='02_Usos'!$V$3 -> 56.193479 | U4: =SUM(B4:T4) -> 397.29954
A5: 03 - Indústrias de transformação | B5: ='02_Usos'!$B$4 -> 2378.5487 | C5: ='02_Usos'!$C$4 -> 61.142098 | D5: ='02_Usos'!$D$4 -> 3685.8365 | E5: ='02_Usos'!$E$4 -> 427.4252 | F5: ='02_Usos'!$F$4 -> 2067.7679 | G5: ='02_Usos'!$G$4 -> 943.80323 | H5: ='02_Usos'!$H$4 -> 788.92036 | I5: ='02_Usos'!$I$4 -> 64.884884 | J5: ='02_Usos'!$J$4 -> 32.678772 | K5: ='02_Usos'!$K$4 -> 54.565436 | L5: ='02_Usos'!$L$4 -> 1245.9919 | M5: ='02_Usos'!$M$4 -> 994.02563 | N5: =0 -> 0 | O5: 5170.1451 | P5: ='02_Usos'!$R$4 -> 114.71822 | Q5: ='02_Usos'!$S$4 -> 23647.917 | R5: ='02_Usos'!$T$4 -> 0 | S5: ='02_Usos'!$U$4 -> 2369.6669 | T5: ='02_Usos'!$V$4 -> 2196.6048 | U5: =SUM(B5:T5) -> 46244.643
A6: 04 - Eletricidade e gás, água, esgoto e gestão de resíduos | B6: ='02_Usos'!$B$5 -> 154.80937 | C6: ='02_Usos'!$C$5 -> 7.900908 | D6: ='02_Usos'!$D$5 -> 136.96591 | E6: ='02_Usos'!$E$5 -> 1480.3103 | F6: ='02_Usos'!$F$5 -> 11.009585 | G6: ='02_Usos'!$G$5 -> 255.58089 | H6: ='02_Usos'!$H$5 -> 26.111449 | I6: ='02_Usos'!$I$5 -> 21.74082 | J6: ='02_Usos'!$J$5 -> 12.939323 | K6: ='02_Usos'!$K$5 -> 7.1191336 | L6: ='02_Usos'!$L$5 -> 216.79545 | M6: ='02_Usos'!$M$5 -> 382.08587 | N6: =0 -> 0 | O6: 613.90952 | P6: ='02_Usos'!$R$5 -> 0 | Q6: ='02_Usos'!$S$5 -> 1221.0253 | R6: ='02_Usos'!$T$5 -> 0 | S6: ='02_Usos'!$U$5 -> 0 | T6: ='02_Usos'!$V$5 -> 1.671612 | U6: =SUM(B6:T6) -> 4549.9755
A7: 05 - Construção | B7: ='02_Usos'!$B$6 -> 3.8224895 | C7: ='02_Usos'!$C$6 -> 0.013787086 | D7: ='02_Usos'!$D$6 -> 2.264245 | E7: ='02_Usos'!$E$6 -> 79.02222 | F7: ='02_Usos'!$F$6 -> 705.14023 | G7: ='02_Usos'!$G$6 -> 11.177303 | H7: ='02_Usos'!$H$6 -> 8.3512823 | I7: ='02_Usos'!$I$6 -> 33.955801 | J7: ='02_Usos'!$J$6 -> 4.9087163 | K7: ='02_Usos'!$K$6 -> 10.536414 | L7: ='02_Usos'!$L$6 -> 24.851141 | M7: ='02_Usos'!$M$6 -> 362.99379 | N7: =0 -> 0 | O7: 0 | P7: ='02_Usos'!$R$6 -> 0 | Q7: ='02_Usos'!$S$6 -> 0 | R7: ='02_Usos'!$T$6 -> 0 | S7: ='02_Usos'!$U$6 -> 4868.1849 | T7: ='02_Usos'!$V$6 -> 0 | U7: =SUM(B7:T7) -> 6115.2223
A8: 06 - Comércio | B8: ='02_Usos'!$B$7 -> 4.0645391 | C8: ='02_Usos'!$C$7 -> 0.19920343 | D8: ='02_Usos'!$D$7 -> 78.202412 | E8: ='02_Usos'!$E$7 -> 12.218688 | F8: ='02_Usos'!$F$7 -> 5.2675482 | G8: ='02_Usos'!$G$7 -> 70.450246 | H8: ='02_Usos'!$H$7 -> 46.636504 | I8: ='02_Usos'!$I$7 -> 23.572888 | J8: ='02_Usos'!$J$7 -> 0.47196288 | K8: ='02_Usos'!$K$7 -> 0.125092 | L8: ='02_Usos'!$L$7 -> 12.265165 | M8: ='02_Usos'!$M$7 -> 53.081127 | N8: =0 -> 0 | O8: 0 | P8: ='02_Usos'!$R$7 -> 0 | Q8: ='02_Usos'!$S$7 -> 483.65278 | R8: ='02_Usos'!$T$7 -> 0 | S8: ='02_Usos'!$U$7 -> 0 | T8: ='02_Usos'!$V$7 -> 0 | U8: =SUM(B8:T8) -> 790.20816
A9: 07 - Transporte, armazenagem e correio | B9: ='02_Usos'!$B$8 -> 112.1417 | C9: ='02_Usos'!$C$8 -> 6.233409 | D9: ='02_Usos'!$D$8 -> 405.32122 | E9: ='02_Usos'!$E$8 -> 22.46871 | F9: ='02_Usos'!$F$8 -> 35.013467 | G9: ='02_Usos'!$G$8 -> 475.61402 | H9: ='02_Usos'!$H$8 -> 304.93613 | I9: ='02_Usos'!$I$8 -> 11.000165 | J9: ='02_Usos'!$J$8 -> 27.967707 | K9: ='02_Usos'!$K$8 -> 1.895719 | L9: ='02_Usos'!$L$8 -> 133.12582 | M9: ='02_Usos'!$M$8 -> 205.00275 | N9: =0 -> 0 | O9: 0 | P9: ='02_Usos'!$R$8 -> 0 | Q9: ='02_Usos'!$S$8 -> 1177.5397 | R9: ='02_Usos'!$T$8 -> 0 | S9: ='02_Usos'!$U$8 -> 0 | T9: ='02_Usos'!$V$8 -> 0 | U9: =SUM(B9:T9) -> 2918.2605
A10: 08 - Informação e comunicação | B10: ='02_Usos'!$B$9 -> 0.61710297 | C10: ='02_Usos'!$C$9 -> 0.22864689 | D10: ='02_Usos'!$D$9 -> 48.77609 | E10: ='02_Usos'!$E$9 -> 41.137019 | F10: ='02_Usos'!$F$9 -> 16.744161 | G10: ='02_Usos'!$G$9 -> 154.23642 | H10: ='02_Usos'!$H$9 -> 31.785982 | I10: ='02_Usos'!$I$9 -> 261.46494 | J10: ='02_Usos'!$J$9 -> 105.33487 | K10: ='02_Usos'!$K$9 -> 5.9821949 | L10: ='02_Usos'!$L$9 -> 204.74525 | M10: ='02_Usos'!$M$9 -> 399.41456 | N10: =0 -> 0 | O10: 26.678261 | P10: ='02_Usos'!$R$9 -> 0 | Q10: ='02_Usos'!$S$9 -> 824.8463 | R10: ='02_Usos'!$T$9 -> 0 | S10: ='02_Usos'!$U$9 -> 110.23355 | T10: ='02_Usos'!$V$9 -> -0.45588277 | U10: =SUM(B10:T10) -> 2231.7695
A11: 09 - Atividades financeiras, de seguros e serviços relacionados | B11: ='02_Usos'!$B$10 -> 130.45603 | C11: ='02_Usos'!$C$10 -> 7.3087877 | D11: ='02_Usos'!$D$10 -> 183.00486 | E11: ='02_Usos'!$E$10 -> 130.82105 | F11: ='02_Usos'!$F$10 -> 96.771951 | G11: ='02_Usos'!$G$10 -> 246.23948 | H11: ='02_Usos'!$H$10 -> 71.125789 | I11: ='02_Usos'!$I$10 -> 66.780516 | J11: ='02_Usos'!$J$10 -> 366.11925 | K11: ='02_Usos'!$K$10 -> 153.22607 | L11: ='02_Usos'!$L$10 -> 148.85236 | M11: ='02_Usos'!$M$10 -> 670.49076 | N11: =0 -> 0 | O11: 0 | P11: ='02_Usos'!$R$10 -> 7.7394705 | Q11: ='02_Usos'!$S$10 -> 3803.7186 | R11: ='02_Usos'!$T$10 -> 0 | S11: ='02_Usos'!$U$10 -> 0 | T11: ='02_Usos'!$V$10 -> 0 | U11: =SUM(B11:T11) -> 6082.6549
A12: 10 - Atividades imobiliárias | B12: ='02_Usos'!$B$11 -> 0.23503353 | C12: ='02_Usos'!$C$11 -> 0.45746481 | D12: ='02_Usos'!$D$11 -> 21.746612 | E12: ='02_Usos'!$E$11 -> 23.239619 | F12: ='02_Usos'!$F$11 -> 13.560324 | G12: ='02_Usos'!$G$11 -> 369.93406 | H12: ='02_Usos'!$H$11 -> 45.167673 | I12: ='02_Usos'!$I$11 -> 25.297465 | J12: ='02_Usos'!$J$11 -> 22.641905 | K12: ='02_Usos'!$K$11 -> 12.590016 | L12: ='02_Usos'!$L$11 -> 189.57111 | M12: ='02_Usos'!$M$11 -> 52.578599 | N12: =0 -> 0 | O12: 3.8794981 | P12: ='02_Usos'!$R$11 -> 0 | Q12: ='02_Usos'!$S$11 -> 3685.5422 | R12: ='02_Usos'!$T$11 -> 0 | S12: ='02_Usos'!$U$11 -> 0 | T12: ='02_Usos'!$V$11 -> 0 | U12: =SUM(B12:T12) -> 4466.4416
A13: 11 - Outras atividades de serviços | B13: ='02_Usos'!$B$12 -> 42.118355 | C13: ='02_Usos'!$C$12 -> 12.527528 | D13: ='02_Usos'!$D$12 -> 458.77529 | E13: ='02_Usos'!$E$12 -> 286.22536 | F13: ='02_Usos'!$F$12 -> 178.98604 | G13: ='02_Usos'!$G$12 -> 998.8851 | H13: ='02_Usos'!$H$12 -> 184.47089 | I13: ='02_Usos'!$I$12 -> 338.46968 | J13: ='02_Usos'!$J$12 -> 261.46515 | K13: ='02_Usos'!$K$12 -> 34.804537 | L13: ='02_Usos'!$L$12 -> 903.45327 | M13: ='02_Usos'!$M$12 -> 1594.054 | N13: =0 -> 0 | O13: 213.00548 | P13: ='02_Usos'!$R$12 -> 564.58529 | Q13: ='02_Usos'!$S$12 -> 8822.4347 | R13: ='02_Usos'!$T$12 -> 462.8832 | S13: ='02_Usos'!$U$12 -> 158.71751 | T13: ='02_Usos'!$V$12 -> 0 | U13: =SUM(B13:T13) -> 15515.861
A14: 12 - Administração, defesa, saúde e educação públicas e seguridade social | B14: ='02_Usos'!$B$13 -> 0 | C14: ='02_Usos'!$C$13 -> 0 | D14: ='02_Usos'!$D$13 -> 0 | E14: ='02_Usos'!$E$13 -> 0 | F14: ='02_Usos'!$F$13 -> 0 | G14: ='02_Usos'!$G$13 -> 0 | H14: ='02_Usos'!$H$13 -> 0 | I14: ='02_Usos'!$I$13 -> 0 | J14: ='02_Usos'!$J$13 -> 0 | K14: ='02_Usos'!$K$13 -> 0 | L14: ='02_Usos'!$L$13 -> 0 | M14: ='02_Usos'!$M$13 -> 0 | N14: =0 -> 0 | O14: 0 | P14: ='02_Usos'!$R$13 -> 19737.217 | Q14: ='02_Usos'!$S$13 -> 0 | R14: ='02_Usos'!$T$13 -> 0 | S14: ='02_Usos'!$U$13 -> 0 | T14: ='02_Usos'!$V$13 -> 0 | U14: =SUM(B14:T14) -> 19737.217
A16: ETAPA 12b - ALFA da base sem exportacoes
A17: Produto \ Destino | B17: 01 - Agropecuária | C17: 02 - Indústrias extrativas | D17: 03 - Indústrias de transformação | E17: 04 - Eletricidade e gás, água, esgoto e gestão de resíduos | F17: 05 - Construção | G17: 06 - Comércio | H17: 07 - Transporte, armazenagem e correio | I17: 08 - Informação e comunicação | J17: 09 - Atividades financeiras, de seguros e serviços relacionados | K17: 10 - Atividades imobiliárias | L17: 11 - Outras atividades de serviços | M17: 12 - Administração, defesa, saúde e educação públicas e seguridade social | N17: Exportacoes outros paises | O17: Exportacoes outras UFs | P17: Consumo do governo | Q17: Consumo das familias | R17: Consumo das ISFLSF | S17: FBCF | T17: Variacao de estoques | U17: Soma da linha (deve ser 1)
A18: 01 - Agropecuária | B18: =IF($U$3=0,0,B$3/$U$3) -> 0.045779182 | C18: =IF($U$3=0,0,C$3/$U$3) -> 1.5917877e-06 | D18: =IF($U$3=0,0,D$3/$U$3) -> 0.21652812 | E18: =IF($U$3=0,0,E$3/$U$3) -> 3.6161304e-05 | F18: =IF($U$3=0,0,F$3/$U$3) -> 0.0013531361 | G18: =IF($U$3=0,0,G$3/$U$3) -> 0.0086979523 | H18: =IF($U$3=0,0,H$3/$U$3) -> 0 | I18: =IF($U$3=0,0,I$3/$U$3) -> 0 | ... T18: =IF($U$3=0,0,T$3/$U$3) -> 0.1120384 | U18: =SUM(B18:T18) -> 1
A19: 02 - Indústrias extrativas | B19: =IF($U$4=0,0,B$4/$U$4) -> 0.020741256 | C19: =IF($U$4=0,0,C$4/$U$4) -> 0.011701213 | D19: =IF($U$4=0,0,D$4/$U$4) -> 0.35140626 | E19: =IF($U$4=0,0,E$4/$U$4) -> 0.0094205033 | F19: =IF($U$4=0,0,F$4/$U$4) -> 0.2384214 | G19: =IF($U$4=0,0,G$4/$U$4) -> 0.0012797518 | H19: =IF($U$4=0,0,H$4/$U$4) -> 1.0784232e-05 | I19: =IF($U$4=0,0,I$4/$U$4) -> 0 | ... T19: =IF($U$4=0,0,T$4/$U$4) -> 0.14143857 | U19: =SUM(B19:T19) -> 1
A20: 03 - Indústrias de transformação | B20: =IF($U$5=0,0,B$5/$U$5) -> 0.051434037 | C20: =IF($U$5=0,0,C$5/$U$5) -> 0.0013221444 | D20: =IF($U$5=0,0,D$5/$U$5) -> 0.079702993 | E20: =IF($U$5=0,0,E$5/$U$5) -> 0.0092426965 | F20: =IF($U$5=0,0,F$5/$U$5) -> 0.044713674 | G20: =IF($U$5=0,0,G$5/$U$5) -> 0.02040892 | H20: =IF($U$5=0,0,H$5/$U$5) -> 0.017059714 | I20: =IF($U$5=0,0,I$5/$U$5) -> 0.0014030789 | ... T20: =IF($U$5=0,0,T$5/$U$5) -> 0.047499659 | U20: =SUM(B20:T20) -> 1
A21: 04 - Eletricidade e gás, água, esgoto e gestão de resíduos | B21: =IF($U$6=0,0,B$6/$U$6) -> 0.03402422 | C21: =IF($U$6=0,0,C$6/$U$6) -> 0.0017364727 | D21: =IF($U$6=0,0,D$6/$U$6) -> 0.030102561 | E21: =IF($U$6=0,0,E$6/$U$6) -> 0.32534468 | F21: =IF($U$6=0,0,F$6/$U$6) -> 0.0024197021 | G21: =IF($U$6=0,0,G$6/$U$6) -> 0.056171928 | H21: =IF($U$6=0,0,H$6/$U$6) -> 0.0057388108 | I21: =IF($U$6=0,0,I$6/$U$6) -> 0.0047782279 | ... T21: =IF($U$6=0,0,T$6/$U$6) -> 0.00036738923 | U21: =SUM(B21:T21) -> 1
A22: 05 - Construção | B22: =IF($U$7=0,0,B$7/$U$7) -> 0.00062507776 | C22: =IF($U$7=0,0,C$7/$U$7) -> 2.2545518e-06 | D22: =IF($U$7=0,0,D$7/$U$7) -> 0.00037026373 | E22: =IF($U$7=0,0,E$7/$U$7) -> 0.012922215 | F22: =IF($U$7=0,0,F$7/$U$7) -> 0.11530901 | G22: =IF($U$7=0,0,G$7/$U$7) -> 0.0018277835 | H22: =IF($U$7=0,0,H$7/$U$7) -> 0.0013656547 | I22: =IF($U$7=0,0,I$7/$U$7) -> 0.0055526682 | ... T22: =IF($U$7=0,0,T$7/$U$7) -> 0 | U22: =SUM(B22:T22) -> 1
A23: 06 - Comércio | B23: =IF($U$8=0,0,B$8/$U$8) -> 0.0051436308 | C23: =IF($U$8=0,0,C$8/$U$8) -> 0.00025208982 | D23: =IF($U$8=0,0,D$8/$U$8) -> 0.098964319 | E23: =IF($U$8=0,0,E$8/$U$8) -> 0.015462619 | F23: =IF($U$8=0,0,F$8/$U$8) -> 0.0066660261 | G23: =IF($U$8=0,0,G$8/$U$8) -> 0.089154036 | H23: =IF($U$8=0,0,H$8/$U$8) -> 0.059017999 | I23: =IF($U$8=0,0,I$8/$U$8) -> 0.029831238 | ... T23: =IF($U$8=0,0,T$8/$U$8) -> 0 | U23: =SUM(B23:T23) -> 1
A24: 07 - Transporte, armazenagem e correio | B24: =IF($U$9=0,0,B$9/$U$9) -> 0.038427583 | C24: =IF($U$9=0,0,C$9/$U$9) -> 0.0021360015 | D24: =IF($U$9=0,0,D$9/$U$9) -> 0.13889138 | E24: =IF($U$9=0,0,E$9/$U$9) -> 0.0076993503 | F24: =IF($U$9=0,0,F$9/$U$9) -> 0.011998061 | G24: =IF($U$9=0,0,G$9/$U$9) -> 0.1629786 | H24: =IF($U$9=0,0,H$9/$U$9) -> 0.10449243 | I24: =IF($U$9=0,0,I$9/$U$9) -> 0.0037694252 | ... T24: =IF($U$9=0,0,T$9/$U$9) -> 0 | U24: =SUM(B24:T24) -> 1
A25: 08 - Informação e comunicação | B25: =IF($U$10=0,0,B$10/$U$10) -> 0.00027650838 | C25: =IF($U$10=0,0,C$10/$U$10) -> 0.00010245094 | D25: =IF($U$10=0,0,D$10/$U$10) -> 0.021855344 | E25: =IF($U$10=0,0,E$10/$U$10) -> 0.018432468 | F25: =IF($U$10=0,0,F$10/$U$10) -> 0.007502639 | G25: =IF($U$10=0,0,G$10/$U$10) -> 0.069109478 | H25: =IF($U$10=0,0,H$10/$U$10) -> 0.014242503 | I25: =IF($U$10=0,0,I$10/$U$10) -> 0.11715589 | ... T25: =IF($U$10=0,0,T$10/$U$10) -> -0.00020426965 | U25: =SUM(B25:T25) -> 1
A26: 09 - Atividades financeiras, de seguros e serviços relacionados | B26: =IF($U$11=0,0,B$11/$U$11) -> 0.021447218 | C26: =IF($U$11=0,0,C$11/$U$11) -> 0.0012015785 | D26: =IF($U$11=0,0,D$11/$U$11) -> 0.030086346 | E26: =IF($U$11=0,0,E$11/$U$11) -> 0.021507228 | F26: =IF($U$11=0,0,F$11/$U$11) -> 0.015909492 | G26: =IF($U$11=0,0,G$11/$U$11) -> 0.040482237 | H26: =IF($U$11=0,0,H$11/$U$11) -> 0.011693215 | I26: =IF($U$11=0,0,I$11/$U$11) -> 0.010978843 | ... T26: =IF($U$11=0,0,T$11/$U$11) -> 0 | U26: =SUM(B26:T26) -> 1
A27: 10 - Atividades imobiliárias | B27: =IF($U$12=0,0,B$12/$U$12) -> 5.2622099e-05 | C27: =IF($U$12=0,0,C$12/$U$12) -> 0.00010242266 | D27: =IF($U$12=0,0,D$12/$U$12) -> 0.0048688898 | E27: =IF($U$12=0,0,E$12/$U$12) -> 0.005203162 | F27: =IF($U$12=0,0,F$12/$U$12) -> 0.0030360464 | G27: =IF($U$12=0,0,G$12/$U$12) -> 0.082825231 | H27: =IF($U$12=0,0,H$12/$U$12) -> 0.010112675 | I27: =IF($U$12=0,0,I$12/$U$12) -> 0.005663897 | ... T27: =IF($U$12=0,0,T$12/$U$12) -> 0 | U27: =SUM(B27:T27) -> 1
A28: 11 - Outras atividades de serviços | B28: =IF($U$13=0,0,B$13/$U$13) -> 0.0027145354 | C28: =IF($U$13=0,0,C$13/$U$13) -> 0.00080740141 | D28: =IF($U$13=0,0,D$13/$U$13) -> 0.029568149 | E28: =IF($U$13=0,0,E$13/$U$13) -> 0.018447275 | F28: =IF($U$13=0,0,F$13/$U$13) -> 0.011535682 | G28: =IF($U$13=0,0,G$13/$U$13) -> 0.064378321 | H28: =IF($U$13=0,0,H$13/$U$13) -> 0.011889181 | I28: =IF($U$13=0,0,I$13/$U$13) -> 0.02181443 | ... T28: =IF($U$13=0,0,T$13/$U$13) -> 0 | U28: =SUM(B28:T28) -> 1
A29: 12 - Administração, defesa, saúde e educação públicas e seguridade social | B29: =IF($U$14=0,0,B$14/$U$14) -> 0 | C29: =IF($U$14=0,0,C$14/$U$14) -> 0 | D29: =IF($U$14=0,0,D$14/$U$14) -> 0 | E29: =IF($U$14=0,0,E$14/$U$14) -> 0 | F29: =IF($U$14=0,0,F$14/$U$14) -> 0 | G29: =IF($U$14=0,0,G$14/$U$14) -> 0 | H29: =IF($U$14=0,0,H$14/$U$14) -> 0 | I29: =IF($U$14=0,0,I$14/$U$14) -> 0 | ... T29: =IF($U$14=0,0,T$14/$U$14) -> 0 | U29: =SUM(B29:T29) -> 1
A31: ETAPA 12c - importacoes de outras UFs distribuidas
A32: Produto \ Destino | B32: 01 - Agropecuária | C32: 02 - Indústrias extrativas | D32: 03 - Indústrias de transformação | E32: 04 - Eletricidade e gás, água, esgoto e gestão de resíduos | F32: 05 - Construção | G32: 06 - Comércio | H32: 07 - Transporte, armazenagem e correio | I32: 08 - Informação e comunicação | J32: 09 - Atividades financeiras, de seguros e serviços relacionados | K32: 10 - Atividades imobiliárias | L32: 11 - Outras atividades de serviços | M32: 12 - Administração, defesa, saúde e educação públicas e seguridade social | N32: Exportacoes outros paises | O32: Exportacoes outras UFs | P32: Consumo do governo | Q32: Consumo das familias | R32: Consumo das ISFLSF | S32: FBCF | T32: Variacao de estoques
A33: 01 - Agropecuária | B33: =B$18*'01_Recursos'!$P$2 -> 39.249175 | C33: =C$18*'01_Recursos'!$P$2 -> 0.0013647328 | D33: =D$18*'01_Recursos'!$P$2 -> 185.64224 | E33: =E$18*'01_Recursos'!$P$2 -> 0.031003204 | F33: =F$18*'01_Recursos'!$P$2 -> 1.1601228 | G33: =G$18*'01_Recursos'!$P$2 -> 7.457264 | H33: =H$18*'01_Recursos'!$P$2 -> 0 | I33: =I$18*'01_Recursos'!$P$2 -> 0 | ... T33: =T$18*'01_Recursos'!$P$2 -> 96.057081
A34: 02 - Indústrias extrativas | B34: =B$19*'01_Recursos'!$P$3 -> 0.58390904 | C34: =C$19*'01_Recursos'!$P$3 -> 0.32941324 | D34: =D$19*'01_Recursos'!$P$3 -> 9.8928094 | E34: =E$19*'01_Recursos'!$P$3 -> 0.26520655 | F34: =F$19*'01_Recursos'!$P$3 -> 6.712053 | G34: =G$19*'01_Recursos'!$P$3 -> 0.036027648 | H34: =H$19*'01_Recursos'!$P$3 -> 0.00030359833 | I34: =I$19*'01_Recursos'!$P$3 -> 0 | ... T34: =T$19*'01_Recursos'!$P$3 -> 3.9817868
A35: 03 - Indústrias de transformação | B35: =B$20*'01_Recursos'!$P$4 -> 1057.8512 | C35: =C$20*'01_Recursos'!$P$4 -> 27.192734 | D35: =D$20*'01_Recursos'!$P$4 -> 1639.2629 | E35: =E$20*'01_Recursos'!$P$4 -> 190.09586 | F35: =F$20*'01_Recursos'!$P$4 -> 919.63252 | G35: =G$20*'01_Recursos'!$P$4 -> 419.75318 | H35: =H$20*'01_Recursos'!$P$4 -> 350.86957 | I35: =I$20*'01_Recursos'!$P$4 -> 28.857325 | ... T35: =T$20*'01_Recursos'!$P$4 -> 976.93229
A36: 04 - Eletricidade e gás, água, esgoto e gestão de resíduos | B36: =B$21*'01_Recursos'!$P$5 -> 0 | C36: =C$21*'01_Recursos'!$P$5 -> 0 | D36: =D$21*'01_Recursos'!$P$5 -> 0 | E36: =E$21*'01_Recursos'!$P$5 -> 0 | F36: =F$21*'01_Recursos'!$P$5 -> 0 | G36: =G$21*'01_Recursos'!$P$5 -> 0 | H36: =H$21*'01_Recursos'!$P$5 -> 0 | I36: =I$21*'01_Recursos'!$P$5 -> 0 | ... T36: =T$21*'01_Recursos'!$P$5 -> 0
A37: 05 - Construção | B37: =B$22*'01_Recursos'!$P$6 -> 0.10132807 | C37: =C$22*'01_Recursos'!$P$6 -> 0.00036547356 | D37: =D$22*'01_Recursos'!$P$6 -> 0.060021508 | E37: =E$22*'01_Recursos'!$P$6 -> 2.0947525 | F37: =F$22*'01_Recursos'!$P$6 -> 18.692138 | G37: =G$22*'01_Recursos'!$P$6 -> 0.29629239 | H37: =H$22*'01_Recursos'!$P$6 -> 0.22137911 | I37: =I$22*'01_Recursos'!$P$6 -> 0.90011388 | ... T37: =T$22*'01_Recursos'!$P$6 -> 0
A38: 06 - Comércio | B38: =B$23*'01_Recursos'!$P$7 -> 9.8763083 | C38: =C$23*'01_Recursos'!$P$7 -> 0.48403877 | D38: =D$23*'01_Recursos'!$P$7 -> 190.02183 | E38: =E$23*'01_Recursos'!$P$7 -> 29.689843 | F38: =F$23*'01_Recursos'!$P$7 -> 12.799466 | G38: =G$23*'01_Recursos'!$P$7 -> 171.18506 | H38: =H$23*'01_Recursos'!$P$7 -> 113.32072 | I38: =I$23*'01_Recursos'!$P$7 -> 57.279092 | ... T38: =T$23*'01_Recursos'!$P$7 -> 0
A39: 07 - Transporte, armazenagem e correio | B39: =B$24*'01_Recursos'!$P$8 -> 25.715667 | C39: =C$24*'01_Recursos'!$P$8 -> 1.4294083 | D39: =D$24*'01_Recursos'!$P$8 -> 92.945853 | E39: =E$24*'01_Recursos'!$P$8 -> 5.152391 | F39: =F$24*'01_Recursos'!$P$8 -> 8.0290801 | G39: =G$24*'01_Recursos'!$P$8 -> 109.06498 | H39: =H$24*'01_Recursos'!$P$8 -> 69.92614 | I39: =I$24*'01_Recursos'!$P$8 -> 2.5224924 | ... T39: =T$24*'01_Recursos'!$P$8 -> 0
A40: 08 - Informação e comunicação | B40: =B$25*'01_Recursos'!$P$9 -> 0.083439926 | C40: =C$25*'01_Recursos'!$P$9 -> 0.030915877 | D40: =D$25*'01_Recursos'!$P$9 -> 6.5951285 | E40: =E$25*'01_Recursos'!$P$9 -> 5.562232 | F40: =F$25*'01_Recursos'!$P$9 -> 2.2640168 | G40: =G$25*'01_Recursos'!$P$9 -> 20.854665 | H40: =H$25*'01_Recursos'!$P$9 -> 4.2978565 | I40: =I$25*'01_Recursos'!$P$9 -> 35.353281 | ... T40: =T$25*'01_Recursos'!$P$9 -> -0.061640969
A41: 09 - Atividades financeiras, de seguros e serviços relacionados | B41: =B$26*'01_Recursos'!$P$10 -> 72.144316 | C41: =C$26*'01_Recursos'!$P$10 -> 4.041879 | D41: =D$26*'01_Recursos'!$P$10 -> 101.20468 | E41: =E$26*'01_Recursos'!$P$10 -> 72.346176 | F41: =F$26*'01_Recursos'!$P$10 -> 53.51647 | G41: =G$26*'01_Recursos'!$P$10 -> 136.17445 | H41: =H$26*'01_Recursos'!$P$10 -> 39.333723 | I41: =I$26*'01_Recursos'!$P$10 -> 36.930717 | ... T41: =T$26*'01_Recursos'!$P$10 -> 0
A42: 10 - Atividades imobiliárias | B42: =B$27*'01_Recursos'!$P$11 -> 0.0092063674 | C42: =C$27*'01_Recursos'!$P$11 -> 0.017919099 | D42: =D$27*'01_Recursos'!$P$11 -> 0.85182442 | E42: =E$27*'01_Recursos'!$P$11 -> 0.91030617 | F42: =F$27*'01_Recursos'!$P$11 -> 0.53116388 | G42: =G$27*'01_Recursos'!$P$11 -> 14.490481 | H42: =H$27*'01_Recursos'!$P$11 -> 1.7692377 | I42: =I$27*'01_Recursos'!$P$11 -> 0.99091291 | ... T42: =T$27*'01_Recursos'!$P$11 -> 0
A43: 11 - Outras atividades de serviços | B43: =B$28*'01_Recursos'!$P$12 -> 11.554057 | C43: =C$28*'01_Recursos'!$P$12 -> 3.4365961 | D43: =D$28*'01_Recursos'!$P$12 -> 125.85287 | E43: =E$28*'01_Recursos'!$P$12 -> 78.518359 | F43: =F$28*'01_Recursos'!$P$12 -> 49.100087 | G43: =G$28*'01_Recursos'!$P$12 -> 274.01771 | H43: =H$28*'01_Recursos'!$P$12 -> 50.604709 | I43: =I$28*'01_Recursos'!$P$12 -> 92.850203 | ... T43: =T$28*'01_Recursos'!$P$12 -> 0
A44: 12 - Administração, defesa, saúde e educação públicas e seguridade social | B44: =B$29*'01_Recursos'!$P$13 -> 0 | C44: =C$29*'01_Recursos'!$P$13 -> 0 | D44: =D$29*'01_Recursos'!$P$13 -> 0 | E44: =E$29*'01_Recursos'!$P$13 -> 0 | F44: =F$29*'01_Recursos'!$P$13 -> 0 | G44: =G$29*'01_Recursos'!$P$13 -> 0 | H44: =H$29*'01_Recursos'!$P$13 -> 0 | I44: =I$29*'01_Recursos'!$P$13 -> 0 | ... T44: =T$29*'01_Recursos'!$P$13 -> 0
A46: ETAPA 12d - importacoes de outros paises distribuidas
A47: Produto \ Destino | B47: 01 - Agropecuária | C47: 02 - Indústrias extrativas | D47: 03 - Indústrias de transformação | E47: 04 - Eletricidade e gás, água, esgoto e gestão de resíduos | F47: 05 - Construção | G47: 06 - Comércio | H47: 07 - Transporte, armazenagem e correio | I47: 08 - Informação e comunicação | J47: 09 - Atividades financeiras, de seguros e serviços relacionados | K47: 10 - Atividades imobiliárias | L47: 11 - Outras atividades de serviços | M47: 12 - Administração, defesa, saúde e educação públicas e seguridade social | N47: Exportacoes outros paises | O47: Exportacoes outras UFs | P47: Consumo do governo | Q47: Consumo das familias | R47: Consumo das ISFLSF | S47: FBCF | T47: Variacao de estoques
A48: 01 - Agropecuária | B48: =B$18*'01_Recursos'!$O$2 -> 6.8703926 | C48: =C$18*'01_Recursos'!$O$2 -> 0.00023889038 | D48: =D$18*'01_Recursos'!$O$2 -> 32.495845 | E48: =E$18*'01_Recursos'!$O$2 -> 0.0054269723 | F48: =F$18*'01_Recursos'!$O$2 -> 0.20307431 | G48: =G$18*'01_Recursos'!$O$2 -> 1.3053607 | H48: =H$18*'01_Recursos'!$O$2 -> 0 | I48: =I$18*'01_Recursos'!$O$2 -> 0 | ... T48: =T$18*'01_Recursos'!$O$2 -> 16.814362
A49: 02 - Indústrias extrativas | B49: =B$19*'01_Recursos'!$O$3 -> 1.1382196 | C49: =C$19*'01_Recursos'!$O$3 -> 0.64212845 | D49: =D$19*'01_Recursos'!$O$3 -> 19.28415 | E49: =E$19*'01_Recursos'!$O$3 -> 0.51696973 | F49: =F$19*'01_Recursos'!$O$3 -> 13.083871 | G49: =G$19*'01_Recursos'!$O$3 -> 0.070229046 | H49: =H$19*'01_Recursos'!$O$3 -> 0.0005918072 | I49: =I$19*'01_Recursos'!$O$3 -> 0 | ... T49: =T$19*'01_Recursos'!$O$3 -> 7.761736
A50: 03 - Indústrias de transformação | B50: =B$20*'01_Recursos'!$O$4 -> 190.46741 | C50: =C$20*'01_Recursos'!$O$4 -> 4.8960853 | D50: =D$20*'01_Recursos'!$O$4 -> 295.1513 | E50: =E$20*'01_Recursos'!$O$4 -> 34.226994 | F50: =F$20*'01_Recursos'!$O$4 -> 165.58097 | G50: =G$20*'01_Recursos'!$O$4 -> 75.577078 | H50: =H$20*'01_Recursos'!$O$4 -> 63.174498 | I50: =I$20*'01_Recursos'!$O$4 -> 5.1957969 | ... T50: =T$20*'01_Recursos'!$O$4 -> 175.89786
A51: 04 - Eletricidade e gás, água, esgoto e gestão de resíduos | B51: =B$21*'01_Recursos'!$O$5 -> 1.6499781 | C51: =C$21*'01_Recursos'!$O$5 -> 0.08420889 | D51: =D$21*'01_Recursos'!$O$5 -> 1.4598003 | E51: =E$21*'01_Recursos'!$O$5 -> 15.777337 | F51: =F$21*'01_Recursos'!$O$5 -> 0.11734157 | G51: =G$21*'01_Recursos'!$O$5 -> 2.7240139 | H51: =H$21*'01_Recursos'!$O$5 -> 0.27829917 | I51: =I$21*'01_Recursos'!$O$5 -> 0.23171644 | ... T51: =T$21*'01_Recursos'!$O$5 -> 0.017816255
A52: 05 - Construção | B52: =B$22*'01_Recursos'!$O$6 -> 0.015332086 | C52: =C$22*'01_Recursos'!$O$6 -> 5.5300294e-05 | D52: =D$22*'01_Recursos'!$O$6 -> 0.0090819349 | E52: =E$22*'01_Recursos'!$O$6 -> 0.3169598 | F52: =F$22*'01_Recursos'!$O$6 -> 2.8283324 | G52: =G$22*'01_Recursos'!$O$6 -> 0.044832399 | H52: =H$22*'01_Recursos'!$O$6 -> 0.03349717 | I52: =I$22*'01_Recursos'!$O$6 -> 0.13619744 | ... T52: =T$22*'01_Recursos'!$O$6 -> 0
A53: 06 - Comércio | B53: =B$23*'01_Recursos'!$O$7 -> 0.030743651 | C53: =C$23*'01_Recursos'!$O$7 -> 0.0015067491 | D53: =D$23*'01_Recursos'!$O$7 -> 0.59151299 | E53: =E$23*'01_Recursos'!$O$7 -> 0.092420583 | F53: =F$23*'01_Recursos'!$O$7 -> 0.039843057 | G53: =G$23*'01_Recursos'!$O$7 -> 0.5328766 | H53: =H$23*'01_Recursos'!$O$7 -> 0.35275252 | I53: =I$23*'01_Recursos'!$O$7 -> 0.17830229 | ... T53: =T$23*'01_Recursos'!$O$7 -> 0
A54: 07 - Transporte, armazenagem e correio | B54: =B$24*'01_Recursos'!$O$8 -> 3.8943493 | C54: =C$24*'01_Recursos'!$O$8 -> 0.21646785 | D54: =D$24*'01_Recursos'!$O$8 -> 14.075607 | E54: =E$24*'01_Recursos'!$O$8 -> 0.78027181 | F54: =F$24*'01_Recursos'!$O$8 -> 1.2159141 | G54: =G$24*'01_Recursos'!$O$8 -> 16.516668 | H54: =H$24*'01_Recursos'!$O$8 -> 10.589529 | I54: =I$24*'01_Recursos'!$O$8 -> 0.38200317 | ... T54: =T$24*'01_Recursos'!$O$8 -> 0
A55: 08 - Informação e comunicação | B55: =B$25*'01_Recursos'!$O$9 -> 0.029772463 | C55: =C$25*'01_Recursos'!$O$9 -> 0.011031191 | D55: =D$25*'01_Recursos'!$O$9 -> 2.3532286 | E55: =E$25*'01_Recursos'!$O$9 -> 1.9846775 | F55: =F$25*'01_Recursos'!$O$9 -> 0.80783098 | G55: =G$25*'01_Recursos'!$O$9 -> 7.4412187 | H55: =H$25*'01_Recursos'!$O$9 -> 1.5335317 | I55: =I$25*'01_Recursos'!$O$9 -> 12.614516 | ... T55: =T$25*'01_Recursos'!$O$9 -> -0.021994308
A56: 09 - Atividades financeiras, de seguros e serviços relacionados | B56: =B$26*'01_Recursos'!$O$10 -> 3.8869775 | C56: =C$26*'01_Recursos'!$O$10 -> 0.21776758 | D56: =D$26*'01_Recursos'!$O$10 -> 5.4526862 | E56: =E$26*'01_Recursos'!$O$10 -> 3.8978533 | F56: =F$26*'01_Recursos'!$O$10 -> 2.8833501 | G56: =G$26*'01_Recursos'!$O$10 -> 7.336781 | H56: =H$26*'01_Recursos'!$O$10 -> 2.1192148 | I56: =I$26*'01_Recursos'!$O$10 -> 1.989746 | ... T56: =T$26*'01_Recursos'!$O$10 -> 0
A57: 10 - Atividades imobiliárias | B57: =B$27*'01_Recursos'!$O$11 -> 0.0015163211 | C57: =C$27*'01_Recursos'!$O$11 -> 0.0029513386 | D57: =D$27*'01_Recursos'!$O$11 -> 0.14029848 | E57: =E$27*'01_Recursos'!$O$11 -> 0.14993063 | F57: =F$27*'01_Recursos'!$O$11 -> 0.087484559 | G57: =G$27*'01_Recursos'!$O$11 -> 2.3866331 | H57: =H$27*'01_Recursos'!$O$11 -> 0.29139967 | I57: =I$27*'01_Recursos'!$O$11 -> 0.16320684 | ... T57: =T$27*'01_Recursos'!$O$11 -> 0
A58: 11 - Outras atividades de serviços | B58: =B$28*'01_Recursos'!$O$12 -> 2.3578173 | C58: =C$28*'01_Recursos'!$O$12 -> 0.70130048 | D58: =D$28*'01_Recursos'!$O$12 -> 25.682587 | E58: =E$28*'01_Recursos'!$O$12 -> 16.023112 | F58: =F$28*'01_Recursos'!$O$12 -> 10.019773 | G58: =G$28*'01_Recursos'!$O$12 -> 55.918341 | H58: =H$28*'01_Recursos'!$O$12 -> 10.326819 | I58: =I$28*'01_Recursos'!$O$12 -> 18.947787 | ... T58: =T$28*'01_Recursos'!$O$12 -> 0
A59: 12 - Administração, defesa, saúde e educação públicas e seguridade social | B59: =B$29*'01_Recursos'!$O$13 -> 0 | C59: =C$29*'01_Recursos'!$O$13 -> 0 | D59: =D$29*'01_Recursos'!$O$13 -> 0 | E59: =E$29*'01_Recursos'!$O$13 -> 0 | F59: =F$29*'01_Recursos'!$O$13 -> 0 | G59: =G$29*'01_Recursos'!$O$13 -> 0 | H59: =H$29*'01_Recursos'!$O$13 -> 0 | I59: =I$29*'01_Recursos'!$O$13 -> 0 | ... T59: =T$29*'01_Recursos'!$O$13 -> 0
A61: ETAPA 12e - importacoes totais (outras UFs + outros paises)
A62: Produto \ Destino | B62: 01 - Agropecuária | C62: 02 - Indústrias extrativas | D62: 03 - Indústrias de transformação | E62: 04 - Eletricidade e gás, água, esgoto e gestão de resíduos | F62: 05 - Construção | G62: 06 - Comércio | H62: 07 - Transporte, armazenagem e correio | I62: 08 - Informação e comunicação | J62: 09 - Atividades financeiras, de seguros e serviços relacionados | K62: 10 - Atividades imobiliárias | L62: 11 - Outras atividades de serviços | M62: 12 - Administração, defesa, saúde e educação públicas e seguridade social | N62: Exportacoes outros paises | O62: Exportacoes outras UFs | P62: Consumo do governo | Q62: Consumo das familias | R62: Consumo das ISFLSF | S62: FBCF | T62: Variacao de estoques | U62: Soma da linha | V62: Importacao total do produto (TRUR) | W62: Diferenca
A63: 01 - Agropecuária | B63: =B$33+B$48 -> 46.119567 | C63: =C$33+C$48 -> 0.0016036232 | D63: =D$33+D$48 -> 218.13809 | E63: =E$33+E$48 -> 0.036430177 | F63: =F$33+F$48 -> 1.3631971 | G63: =G$33+G$48 -> 8.7626247 | H63: =H$33+H$48 -> 0 | I63: =I$33+I$48 -> 0 | ... T63: =T$33+T$48 -> 112.87144 | U63: =SUM(B63:T63) -> 1007.4354 | V63: ='01_Recursos'!$Q$2 -> 1007.4354 | W63: =U63-V63 -> -2.7284841e-12
A64: 02 - Indústrias extrativas | B64: =B$34+B$49 -> 1.7221286 | C64: =C$34+C$49 -> 0.97154169 | D64: =D$34+D$49 -> 29.17696 | E64: =E$34+E$49 -> 0.78217629 | F64: =F$34+F$49 -> 19.795924 | G64: =G$34+G$49 -> 0.10625669 | H64: =H$34+H$49 -> 0.00089540554 | I64: =I$34+I$49 -> 0 | ... T64: =T$34+T$49 -> 11.743523 | U64: =SUM(B64:T64) -> 83.02914 | V64: ='01_Recursos'!$Q$3 -> 83.02914 | W64: =U64-V64 -> 0
A65: 03 - Indústrias de transformação | B65: =B$35+B$50 -> 1248.3186 | C65: =C$35+C$50 -> 32.088819 | D65: =D$35+D$50 -> 1934.4142 | E65: =E$35+E$50 -> 224.32285 | F65: =F$35+F$50 -> 1085.2135 | G65: =G$35+G$50 -> 495.33026 | H65: =H$35+H$50 -> 414.04407 | I65: =I$35+I$50 -> 34.053122 | ... T65: =T$35+T$50 -> 1152.8302 | U65: =SUM(B65:T65) -> 24270.282 | V65: ='01_Recursos'!$Q$4 -> 24270.282 | W65: =U65-V65 -> -4.0017767e-11
A66: 04 - Eletricidade e gás, água, esgoto e gestão de resíduos | B66: =B$36+B$51 -> 1.6499781 | C66: =C$36+C$51 -> 0.08420889 | D66: =D$36+D$51 -> 1.4598003 | E66: =E$36+E$51 -> 15.777337 | F66: =F$36+F$51 -> 0.11734157 | G66: =G$36+G$51 -> 2.7240139 | H66: =H$36+H$51 -> 0.27829917 | I66: =I$36+I$51 -> 0.23171644 | ... T66: =T$36+T$51 -> 0.017816255 | U66: =SUM(B66:T66) -> 48.494222 | V66: ='01_Recursos'!$Q$5 -> 48.494222 | W66: =U66-V66 -> 0
A67: 05 - Construção | B67: =B$37+B$52 -> 0.11666016 | C67: =C$37+C$52 -> 0.00042077385 | D67: =D$37+D$52 -> 0.069103443 | E67: =E$37+E$52 -> 2.4117123 | F67: =F$37+F$52 -> 21.52047 | G67: =G$37+G$52 -> 0.34112479 | H67: =H$37+H$52 -> 0.25487628 | I67: =I$37+I$52 -> 1.0363113 | ... T67: =T$37+T$52 -> 0 | U67: =SUM(B67:T67) -> 186.63303 | V67: ='01_Recursos'!$Q$6 -> 186.63303 | W67: =U67-V67 -> -5.1159077e-13
A68: 06 - Comércio | B68: =B$38+B$53 -> 9.907052 | C68: =C$38+C$53 -> 0.48554552 | D68: =D$38+D$53 -> 190.61334 | E68: =E$38+E$53 -> 29.782264 | F68: =F$38+F$53 -> 12.839309 | G68: =G$38+G$53 -> 171.71793 | H68: =H$38+H$53 -> 113.67347 | I68: =I$38+I$53 -> 57.457394 | ... T68: =T$38+T$53 -> 0 | U68: =SUM(B68:T68) -> 1926.0814 | V68: ='01_Recursos'!$Q$7 -> 1926.0814 | W68: =U68-V68 -> -3.4106051e-12
A69: 07 - Transporte, armazenagem e correio | B69: =B$39+B$54 -> 29.610017 | C69: =C$39+C$54 -> 1.6458761 | D69: =D$39+D$54 -> 107.02146 | E69: =E$39+E$54 -> 5.9326628 | F69: =F$39+F$54 -> 9.2449942 | G69: =G$39+G$54 -> 125.58165 | H69: =H$39+H$54 -> 80.51567 | I69: =I$39+I$54 -> 2.9044955 | ... T69: =T$39+T$54 -> 0 | U69: =SUM(B69:T69) -> 770.54071 | V69: ='01_Recursos'!$Q$8 -> 770.54071 | W69: =U69-V69 -> 0
A70: 08 - Informação e comunicação | B70: =B$40+B$55 -> 0.11321239 | C70: =C$40+C$55 -> 0.041947068 | D70: =D$40+D$55 -> 8.948357 | E70: =E$40+E$55 -> 7.5469095 | F70: =F$40+F$55 -> 3.0718478 | G70: =G$40+G$55 -> 28.295884 | H70: =H$40+H$55 -> 5.8313882 | I70: =I$40+I$55 -> 47.967797 | ... T70: =T$40+T$55 -> -0.083635277 | U70: =SUM(B70:T70) -> 409.43564 | V70: ='01_Recursos'!$Q$9 -> 409.43564 | W70: =U70-V70 -> 0
A71: 09 - Atividades financeiras, de seguros e serviços relacionados | B71: =B$41+B$56 -> 76.031293 | C71: =C$41+C$56 -> 4.2596466 | D71: =D$41+D$56 -> 106.65737 | E71: =E$41+E$56 -> 76.244029 | F71: =F$41+F$56 -> 56.39982 | G71: =G$41+G$56 -> 143.51124 | H71: =H$41+H$56 -> 41.452938 | I71: =I$41+I$56 -> 38.920463 | ... T71: =T$41+T$56 -> 0 | U71: =SUM(B71:T71) -> 3545.0421 | V71: ='01_Recursos'!$Q$10 -> 3545.0421 | W71: =U71-V71 -> 0
A72: 10 - Atividades imobiliárias | B72: =B$42+B$57 -> 0.010722688 | C72: =C$42+C$57 -> 0.020870438 | D72: =D$42+D$57 -> 0.9921229 | E72: =E$42+E$57 -> 1.0602368 | F72: =F$42+F$57 -> 0.61864844 | G72: =G$42+G$57 -> 16.877114 | H72: =H$42+H$57 -> 2.0606374 | I72: =I$42+I$57 -> 1.1541198 | ... T72: =T$42+T$57 -> 0 | U72: =SUM(B72:T72) -> 203.76778 | V72: ='01_Recursos'!$Q$11 -> 203.76778 | W72: =U72-V72 -> 5.4001248e-13
A73: 11 - Outras atividades de serviços | B73: =B$43+B$58 -> 13.911874 | C73: =C$43+C$58 -> 4.1378966 | D73: =D$43+D$58 -> 151.53545 | E73: =E$43+E$58 -> 94.54147 | F73: =F$43+F$58 -> 59.11986 | G73: =G$43+G$58 -> 329.93605 | H73: =H$43+H$58 -> 60.931528 | I73: =I$43+I$58 -> 111.79799 | ... T73: =T$43+T$58 -> 0 | U73: =SUM(B73:T73) -> 5124.9558 | V73: ='01_Recursos'!$Q$12 -> 5124.9558 | W73: =U73-V73 -> 0
A74: 12 - Administração, defesa, saúde e educação públicas e seguridade social | B74: =B$44+B$59 -> 0 | C74: =C$44+C$59 -> 0 | D74: =D$44+D$59 -> 0 | E74: =E$44+E$59 -> 0 | F74: =F$44+F$59 -> 0 | G74: =G$44+G$59 -> 0 | H74: =H$44+H$59 -> 0 | I74: =I$44+I$59 -> 0 | ... T74: =T$44+T$59 -> 0 | U74: =SUM(B74:T74) -> 422.67171 | V74: ='01_Recursos'!$Q$13 -> 422.67171 | W74: =U74-V74 -> 0

Sheet 10_Usos_basicos
A1: ETAPA 13a - usos a precos de consumidor (CI + demanda final completa)
A2: Produto \ Destino | B2: 01 - Agropecuária | C2: 02 - Indústrias extrativas | D2: 03 - Indústrias de transformação | E2: 04 - Eletricidade e gás, água, esgoto e gestão de resíduos | F2: 05 - Construção | G2: 06 - Comércio | H2: 07 - Transporte, armazenagem e correio | I2: 08 - Informação e comunicação | J2: 09 - Atividades financeiras, de seguros e serviços relacionados | K2: 10 - Atividades imobiliárias | L2: 11 - Outras atividades de serviços | M2: 12 - Administração, defesa, saúde e educação públicas e seguridade social | N2: Exportacoes outros paises | O2: Exportacoes outras UFs | P2: Consumo do governo | Q2: Consumo das familias | R2: Consumo das ISFLSF | S2: FBCF | T2: Variacao de estoques
A3: 01 - Agropecuária | B3: ='02_Usos'!$B$2 -> 336.52786 | C3: ='02_Usos'!$C$2 -> 0.011701408 | D3: ='02_Usos'!$D$2 -> 1591.7223 | E3: ='02_Usos'!$E$2 -> 0.26582577 | F3: ='02_Usos'!$F$2 -> 9.9470537 | G3: ='02_Usos'!$G$2 -> 63.939615 | H3: ='02_Usos'!$H$2 -> 0 | I3: ='02_Usos'!$I$2 -> 0 | J3: ='02_Usos'!$J$2 -> 0 | K3: ='02_Usos'!$K$2 -> 0 | L3: ='02_Usos'!$L$2 -> 67.900903 | M3: ='02_Usos'!$M$2 -> 45.176743 | N3: ='02_Usos'!$O$2 -> 2073.7754 | O3: ='02_Usos'!$P$2 -> 1269.6183 | P3: ='02_Usos'!$R$2 -> 1.2191883 | Q3: ='02_Usos'!$S$2 -> 2973.5572 | R3: ='02_Usos'!$T$2 -> 0 | S3: ='02_Usos'!$U$2 -> 167.61783 | T3: ='02_Usos'!$V$2 -> 823.60672
A4: 02 - Indústrias extrativas | B4: ='02_Usos'!$B$3 -> 8.2404914 | C4: ='02_Usos'!$C$3 -> 4.6488867 | D4: ='02_Usos'!$D$3 -> 139.61354 | E4: ='02_Usos'!$E$3 -> 3.7427616 | F4: ='02_Usos'!$F$3 -> 94.724711 | G4: ='02_Usos'!$G$3 -> 0.50844481 | H4: ='02_Usos'!$H$3 -> 0.0042845705 | I4: ='02_Usos'!$I$3 -> 0 | J4: ='02_Usos'!$J$3 -> 0 | K4: ='02_Usos'!$K$3 -> 5.5097789 | L4: ='02_Usos'!$L$3 -> 0.3817976 | M4: ='02_Usos'!$M$3 -> 1.8826824 | N4: ='02_Usos'!$O$3 -> 3.3882649 | O4: ='02_Usos'!$P$3 -> 81.848675 | P4: ='02_Usos'!$R$3 -> 0 | Q4: ='02_Usos'!$S$3 -> 0 | R4: ='02_Usos'!$T$3 -> 0 | S4: ='02_Usos'!$U$3 -> 0 | T4: ='02_Usos'!$V$3 -> 56.193479
A5: 03 - Indústrias de transformação | B5: ='02_Usos'!$B$4 -> 2378.5487 | C5: ='02_Usos'!$C$4 -> 61.142098 | D5: ='02_Usos'!$D$4 -> 3685.8365 | E5: ='02_Usos'!$E$4 -> 427.4252 | F5: ='02_Usos'!$F$4 -> 2067.7679 | G5: ='02_Usos'!$G$4 -> 943.80323 | H5: ='02_Usos'!$H$4 -> 788.92036 | I5: ='02_Usos'!$I$4 -> 64.884884 | J5: ='02_Usos'!$J$4 -> 32.678772 | K5: ='02_Usos'!$K$4 -> 54.565436 | L5: ='02_Usos'!$L$4 -> 1245.9919 | M5: ='02_Usos'!$M$4 -> 994.02563 | N5: ='02_Usos'!$O$4 -> 546.53567 | O5: ='02_Usos'!$P$4 -> 5170.1451 | P5: ='02_Usos'!$R$4 -> 114.71822 | Q5: ='02_Usos'!$S$4 -> 23647.917 | R5: ='02_Usos'!$T$4 -> 0 | S5: ='02_Usos'!$U$4 -> 2369.6669 | T5: ='02_Usos'!$V$4 -> 2196.6048
A6: 04 - Eletricidade e gás, água, esgoto e gestão de resíduos | B6: ='02_Usos'!$B$5 -> 154.80937 | C6: ='02_Usos'!$C$5 -> 7.900908 | D6: ='02_Usos'!$D$5 -> 136.96591 | E6: ='02_Usos'!$E$5 -> 1480.3103 | F6: ='02_Usos'!$F$5 -> 11.009585 | G6: ='02_Usos'!$G$5 -> 255.58089 | H6: ='02_Usos'!$H$5 -> 26.111449 | I6: ='02_Usos'!$I$5 -> 21.74082 | J6: ='02_Usos'!$J$5 -> 12.939323 | K6: ='02_Usos'!$K$5 -> 7.1191336 | L6: ='02_Usos'!$L$5 -> 216.79545 | M6: ='02_Usos'!$M$5 -> 382.08587 | N6: ='02_Usos'!$O$5 -> 0 | O6: ='02_Usos'!$P$5 -> 613.90952 | P6: ='02_Usos'!$R$5 -> 0 | Q6: ='02_Usos'!$S$5 -> 1221.0253 | R6: ='02_Usos'!$T$5 -> 0 | S6: ='02_Usos'!$U$5 -> 0 | T6: ='02_Usos'!$V$5 -> 1.671612
A7: 05 - Construção | B7: ='02_Usos'!$B$6 -> 3.8224895 | C7: ='02_Usos'!$C$6 -> 0.013787086 | D7: ='02_Usos'!$D$6 -> 2.264245 | E7: ='02_Usos'!$E$6 -> 79.02222 | F7: ='02_Usos'!$F$6 -> 705.14023 | G7: ='02_Usos'!$G$6 -> 11.177303 | H7: ='02_Usos'!$H$6 -> 8.3512823 | I7: ='02_Usos'!$I$6 -> 33.955801 | J7: ='02_Usos'!$J$6 -> 4.9087163 | K7: ='02_Usos'!$K$6 -> 10.536414 | L7: ='02_Usos'!$L$6 -> 24.851141 | M7: ='02_Usos'!$M$6 -> 362.99379 | N7: ='02_Usos'!$O$6 -> 0 | O7: ='02_Usos'!$P$6 -> 0 | P7: ='02_Usos'!$R$6 -> 0 | Q7: ='02_Usos'!$S$6 -> 0 | R7: ='02_Usos'!$T$6 -> 0 | S7: ='02_Usos'!$U$6 -> 4868.1849 | T7: ='02_Usos'!$V$6 -> 0
A8: 06 - Comércio | B8: ='02_Usos'!$B$7 -> 4.0645391 | C8: ='02_Usos'!$C$7 -> 0.19920343 | D8: ='02_Usos'!$D$7 -> 78.202412 | E8: ='02_Usos'!$E$7 -> 12.218688 | F8: ='02_Usos'!$F$7 -> 5.2675482 | G8: ='02_Usos'!$G$7 -> 70.450246 | H8: ='02_Usos'!$H$7 -> 46.636504 | I8: ='02_Usos'!$I$7 -> 23.572888 | J8: ='02_Usos'!$J$7 -> 0.47196288 | K8: ='02_Usos'!$K$7 -> 0.125092 | L8: ='02_Usos'!$L$7 -> 12.265165 | M8: ='02_Usos'!$M$7 -> 53.081127 | N8: ='02_Usos'!$O$7 -> 26.994692 | O8: ='02_Usos'!$P$7 -> 0 | P8: ='02_Usos'!$R$7 -> 0 | Q8: ='02_Usos'!$S$7 -> 483.65278 | R8: ='02_Usos'!$T$7 -> 0 | S8: ='02_Usos'!$U$7 -> 0 | T8: ='02_Usos'!$V$7 -> 0
A9: 07 - Transporte, armazenagem e correio | B9: ='02_Usos'!$B$8 -> 112.1417 | C9: ='02_Usos'!$C$8 -> 6.233409 | D9: ='02_Usos'!$D$8 -> 405.32122 | E9: ='02_Usos'!$E$8 -> 22.46871 | F9: ='02_Usos'!$F$8 -> 35.013467 | G9: ='02_Usos'!$G$8 -> 475.61402 | H9: ='02_Usos'!$H$8 -> 304.93613 | I9: ='02_Usos'!$I$8 -> 11.000165 | J9: ='02_Usos'!$J$8 -> 27.967707 | K9: ='02_Usos'!$K$8 -> 1.895719 | L9: ='02_Usos'!$L$8 -> 133.12582 | M9: ='02_Usos'!$M$8 -> 205.00275 | N9: ='02_Usos'!$O$8 -> 16 | O9: ='02_Usos'!$P$8 -> 0 | P9: ='02_Usos'!$R$8 -> 0 | Q9: ='02_Usos'!$S$8 -> 1177.5397 | R9: ='02_Usos'!$T$8 -> 0 | S9: ='02_Usos'!$U$8 -> 0 | T9: ='02_Usos'!$V$8 -> 0
A10: 08 - Informação e comunicação | B10: ='02_Usos'!$B$9 -> 0.61710297 | C10: ='02_Usos'!$C$9 -> 0.22864689 | D10: ='02_Usos'!$D$9 -> 48.77609 | E10: ='02_Usos'!$E$9 -> 41.137019 | F10: ='02_Usos'!$F$9 -> 16.744161 | G10: ='02_Usos'!$G$9 -> 154.23642 | H10: ='02_Usos'!$H$9 -> 31.785982 | I10: ='02_Usos'!$I$9 -> 261.46494 | J10: ='02_Usos'!$J$9 -> 105.33487 | K10: ='02_Usos'!$K$9 -> 5.9821949 | L10: ='02_Usos'!$L$9 -> 204.74525 | M10: ='02_Usos'!$M$9 -> 399.41456 | N10: ='02_Usos'!$O$9 -> 2.6752358 | O10: ='02_Usos'!$P$9 -> 26.678261 | P10: ='02_Usos'!$R$9 -> 0 | Q10: ='02_Usos'!$S$9 -> 824.8463 | R10: ='02_Usos'!$T$9 -> 0 | S10: ='02_Usos'!$U$9 -> 110.23355 | T10: ='02_Usos'!$V$9 -> -0.45588277
A11: 09 - Atividades financeiras, de seguros e serviços relacionados | B11: ='02_Usos'!$B$10 -> 130.45603 | C11: ='02_Usos'!$C$10 -> 7.3087877 | D11: ='02_Usos'!$D$10 -> 183.00486 | E11: ='02_Usos'!$E$10 -> 130.82105 | F11: ='02_Usos'!$F$10 -> 96.771951 | G11: ='02_Usos'!$G$10 -> 246.23948 | H11: ='02_Usos'!$H$10 -> 71.125789 | I11: ='02_Usos'!$I$10 -> 66.780516 | J11: ='02_Usos'!$J$10 -> 366.11925 | K11: ='02_Usos'!$K$10 -> 153.22607 | L11: ='02_Usos'!$L$10 -> 148.85236 | M11: ='02_Usos'!$M$10 -> 670.49076 | N11: ='02_Usos'!$O$10 -> 8.4055004 | O11: ='02_Usos'!$P$10 -> 0 | P11: ='02_Usos'!$R$10 -> 7.7394705 | Q11: ='02_Usos'!$S$10 -> 3803.7186 | R11: ='02_Usos'!$T$10 -> 0 | S11: ='02_Usos'!$U$10 -> 0 | T11: ='02_Usos'!$V$10 -> 0
A12: 10 - Atividades imobiliárias | B12: ='02_Usos'!$B$11 -> 0.23503353 | C12: ='02_Usos'!$C$11 -> 0.45746481 | D12: ='02_Usos'!$D$11 -> 21.746612 | E12: ='02_Usos'!$E$11 -> 23.239619 | F12: ='02_Usos'!$F$11 -> 13.560324 | G12: ='02_Usos'!$G$11 -> 369.93406 | H12: ='02_Usos'!$H$11 -> 45.167673 | I12: ='02_Usos'!$I$11 -> 25.297465 | J12: ='02_Usos'!$J$11 -> 22.641905 | K12: ='02_Usos'!$K$11 -> 12.590016 | L12: ='02_Usos'!$L$11 -> 189.57111 | M12: ='02_Usos'!$M$11 -> 52.578599 | N12: ='02_Usos'!$O$11 -> 0 | O12: ='02_Usos'!$P$11 -> 3.8794981 | P12: ='02_Usos'!$R$11 -> 0 | Q12: ='02_Usos'!$S$11 -> 3685.5422 | R12: ='02_Usos'!$T$11 -> 0 | S12: ='02_Usos'!$U$11 -> 0 | T12: ='02_Usos'!$V$11 -> 0
A13: 11 - Outras atividades de serviços | B13: ='02_Usos'!$B$12 -> 42.118355 | C13: ='02_Usos'!$C$12 -> 12.527528 | D13: ='02_Usos'!$D$12 -> 458.77529 | E13: ='02_Usos'!$E$12 -> 286.22536 | F13: ='02_Usos'!$F$12 -> 178.98604 | G13: ='02_Usos'!$G$12 -> 998.8851 | H13: ='02_Usos'!$H$12 -> 184.47089 | I13: ='02_Usos'!$I$12 -> 338.46968 | J13: ='02_Usos'!$J$12 -> 261.46515 | K13: ='02_Usos'!$K$12 -> 34.804537 | L13: ='02_Usos'!$L$12 -> 903.45327 | M13: ='02_Usos'!$M$12 -> 1594.054 | N13: ='02_Usos'!$O$12 -> 39.490348 | O13: ='02_Usos'!$P$12 -> 213.00548 | P13: ='02_Usos'!$R$12 -> 564.58529 | Q13: ='02_Usos'!$S$12 -> 8822.4347 | R13: ='02_Usos'!$T$12 -> 462.8832 | S13: ='02_Usos'!$U$12 -> 158.71751 | T13: ='02_Usos'!$V$12 -> 0
A14: 12 - Administração, defesa, saúde e educação públicas e seguridade social | B14: ='02_Usos'!$B$13 -> 0 | C14: ='02_Usos'!$C$13 -> 0 | D14: ='02_Usos'!$D$13 -> 0 | E14: ='02_Usos'!$E$13 -> 0 | F14: ='02_Usos'!$F$13 -> 0 | G14: ='02_Usos'!$G$13 -> 0 | H14: ='02_Usos'!$H$13 -> 0 | I14: ='02_Usos'!$I$13 -> 0 | J14: ='02_Usos'!$J$13 -> 0 | K14: ='02_Usos'!$K$13 -> 0 | L14: ='02_Usos'!$L$13 -> 0 | M14: ='02_Usos'!$M$13 -> 0 | N14: ='02_Usos'!$O$13 -> 0 | O14: ='02_Usos'!$P$13 -> 0 | P14: ='02_Usos'!$R$13 -> 19737.217 | Q14: ='02_Usos'!$S$13 -> 0 | R14: ='02_Usos'!$T$13 -> 0 | S14: ='02_Usos'!$U$13 -> 0 | T14: ='02_Usos'!$V$13 -> 0
A16: ETAPA 13b - usos a precos basicos = consumidor - margens - impostos - importacoes
A17: Produto \ Destino | B17: 01 - Agropecuária | C17: 02 - Indústrias extrativas | D17: 03 - Indústrias de transformação | E17: 04 - Eletricidade e gás, água, esgoto e gestão de resíduos | F17: 05 - Construção | G17: 06 - Comércio | H17: 07 - Transporte, armazenagem e correio | I17: 08 - Informação e comunicação | J17: 09 - Atividades financeiras, de seguros e serviços relacionados | K17: 10 - Atividades imobiliárias | L17: 11 - Outras atividades de serviços | M17: 12 - Administração, defesa, saúde e educação públicas e seguridade social | N17: Exportacoes outros paises | O17: Exportacoes outras UFs | P17: Consumo do governo | Q17: Consumo das familias | R17: Consumo das ISFLSF | S17: FBCF | T17: Variacao de estoques | U17: Soma da linha | V17: Producao do produto | W17: Diferenca
A18: 01 - Agropecuária | B18: =B$3-'06_M_comercio'!$B$20-'07_M_transporte'!$B$20-'08_M_impostos'!$B$33-'09_M_importacoes'!$B$63 -> 250.8631 | C18: =C$3-'06_M_comercio'!$C$20-'07_M_transporte'!$C$20-'08_M_impostos'!$C$33-'09_M_importacoes'!$C$63 -> 0.0087227592 | D18: =D$3-'06_M_comercio'!$D$20-'07_M_transporte'!$D$20-'08_M_impostos'!$D$33-'09_M_importacoes'!$D$63 -> 1186.5418 | E18: =E$3-'06_M_comercio'!$E$20-'07_M_transporte'!$E$20-'08_M_impostos'!$E$33-'09_M_importacoes'!$E$63 -> 0.19815856 | F18: =F$3-'06_M_comercio'!$F$20-'07_M_transporte'!$F$20-'08_M_impostos'!$F$33-'09_M_importacoes'!$F$63 -> 7.414984 | G18: =G$3-'06_M_comercio'!$G$20-'07_M_transporte'!$G$20-'08_M_impostos'!$G$33-'09_M_importacoes'!$G$63 -> 47.663482 | H18: =H$3-'06_M_comercio'!$H$20-'07_M_transporte'!$H$20-'08_M_impostos'!$H$33-'09_M_importacoes'!$H$63 -> 0 | I18: =I$3-'06_M_comercio'!$I$20-'07_M_transporte'!$I$20-'08_M_impostos'!$I$33-'09_M_importacoes'!$I$63 -> 0 | J18: =J$3-'06_M_comercio'!$J$20-'07_M_transporte'!$J$20-'08_M_impostos'!$J$33-'09_M_importacoes'!$J$63 -> 0 | K18: =K$3-'06_M_comercio'!$K$20-'07_M_transporte'!$K$20-'08_M_impostos'!$K$33-'09_M_importacoes'!$K$63 -> 0 | L18: =L$3-'06_M_comercio'!$L$20-'07_M_transporte'!$L$20-'08_M_impostos'!$L$33-'09_M_importacoes'!$L$63 -> 50.616406 | M18: =M$3-'06_M_comercio'!$M$20-'07_M_transporte'!$M$20-'08_M_impostos'!$M$33-'09_M_importacoes'!$M$63 -> 33.676789 | N18: =N$3-'06_M_comercio'!$N$20-'07_M_transporte'!$N$20-'08_M_impostos'!$N$33-'09_M_importacoes'!$N$63 -> 1867.6464 | O18: =O$3-'06_M_comercio'!$O$20-'07_M_transporte'!$O$20-'08_M_impostos'!$O$33-'09_M_importacoes'!$O$63 -> 946.43092 | P18: =P$3-'06_M_comercio'!$P$20-'07_M_transporte'!$P$20-'08_M_impostos'!$P$33-'09_M_importacoes'!$P$63 -> 0.90883816 | Q18: =Q$3-'06_M_comercio'!$Q$20-'07_M_transporte'!$Q$20-'08_M_impostos'!$Q$33-'09_M_importacoes'!$Q$63 -> 2216.6241 | R18: =R$3-'06_M_comercio'!$R$20-'07_M_transporte'!$R$20-'08_M_impostos'!$R$33-'09_M_importacoes'!$R$63 -> 0 | S18: =S$3-'06_M_comercio'!$S$20-'07_M_transporte'!$S$20-'08_M_impostos'!$S$33-'09_M_importacoes'!$S$63 -> 124.94991 | T18: =T$3-'06_M_comercio'!$T$20-'07_M_transporte'!$T$20-'08_M_impostos'!$T$33-'09_M_importacoes'!$T$63 -> 613.95372 | U18: =SUM(B18:T18) -> 7347.4974 | V18: ='01_Recursos'!$W$2 -> 7347.4974 | W18: =U18-V18 -> 0
A19: 02 - Indústrias extrativas | B19: =B$4-'06_M_comercio'!$B$21-'07_M_transporte'!$B$21-'08_M_impostos'!$B$34-'09_M_importacoes'!$B$64 -> 4.2881517 | C19: =C$4-'06_M_comercio'!$C$21-'07_M_transporte'!$C$21-'08_M_impostos'!$C$34-'09_M_importacoes'!$C$64 -> 2.4191678 | D19: =D$4-'06_M_comercio'!$D$21-'07_M_transporte'!$D$21-'08_M_impostos'!$D$34-'09_M_importacoes'!$D$64 -> 72.6515 | E19: =E$4-'06_M_comercio'!$E$21-'07_M_transporte'!$E$21-'08_M_impostos'!$E$34-'09_M_importacoes'!$E$64 -> 1.9476423 | F19: =F$4-'06_M_comercio'!$F$21-'07_M_transporte'!$F$21-'08_M_impostos'!$F$34-'09_M_importacoes'!$F$64 -> 49.292441 | G19: =G$4-'06_M_comercio'!$G$21-'07_M_transporte'!$G$21-'08_M_impostos'!$G$34-'09_M_importacoes'!$G$64 -> 0.26458234 | H19: =H$4-'06_M_comercio'!$H$21-'07_M_transporte'!$H$21-'08_M_impostos'!$H$34-'09_M_importacoes'!$H$64 -> 0.0022295865 | I19: =I$4-'06_M_comercio'!$I$21-'07_M_transporte'!$I$21-'08_M_impostos'!$I$34-'09_M_importacoes'!$I$64 -> 0 | J19: =J$4-'06_M_comercio'!$J$21-'07_M_transporte'!$J$21-'08_M_impostos'!$J$34-'09_M_importacoes'!$J$64 -> 0 | K19: =K$4-'06_M_comercio'!$K$21-'07_M_transporte'!$K$21-'08_M_impostos'!$K$34-'09_M_importacoes'!$K$64 -> 2.8671552 | L19: =L$4-'06_M_comercio'!$L$21-'07_M_transporte'!$L$21-'08_M_impostos'!$L$34-'09_M_importacoes'!$L$64 -> 0.1986782 | M19: =M$4-'06_M_comercio'!$M$21-'07_M_transporte'!$M$21-'08_M_impostos'!$M$34-'09_M_importacoes'!$M$64 -> 0.97970224 | N19: =N$4-'06_M_comercio'!$N$21-'07_M_transporte'!$N$21-'08_M_impostos'!$N$34-'09_M_importacoes'!$N$64 -> 2.5597959 | O19: =O$4-'06_M_comercio'!$O$21-'07_M_transporte'!$O$21-'08_M_impostos'!$O$34-'09_M_importacoes'!$O$64 -> 42.592064 | P19: =P$4-'06_M_comercio'!$P$21-'07_M_transporte'!$P$21-'08_M_impostos'!$P$34-'09_M_importacoes'!$P$64 -> 0 | Q19: =Q$4-'06_M_comercio'!$Q$21-'07_M_transporte'!$Q$21-'08_M_impostos'!$Q$34-'09_M_importacoes'!$Q$64 -> 0 | R19: =R$4-'06_M_comercio'!$R$21-'07_M_transporte'!$R$21-'08_M_impostos'!$R$34-'09_M_importacoes'!$R$64 -> 0 | S19: =S$4-'06_M_comercio'!$S$21-'07_M_transporte'!$S$21-'08_M_impostos'!$S$34-'09_M_importacoes'!$S$64 -> 0 | T19: =T$4-'06_M_comercio'!$T$21-'07_M_transporte'!$T$21-'08_M_impostos'!$T$34-'09_M_importacoes'!$T$64 -> 29.241722 | U19: =SUM(B19:T19) -> 209.30483 | V19: ='01_Recursos'!$W$3 -> 209.30483 | W19: =U19-V19 -> 3.6948222e-13
A20: 03 - Indústrias de transformação | B20: =B$5-'06_M_comercio'!$B$22-'07_M_transporte'!$B$22-'08_M_impostos'!$B$35-'09_M_importacoes'!$B$65 -> 415.28075 | C20: =C$5-'06_M_comercio'!$C$22-'07_M_transporte'!$C$22-'08_M_impostos'!$C$35-'09_M_importacoes'!$C$65 -> 10.675054 | D20: =D$5-'06_M_comercio'!$D$22-'07_M_transporte'!$D$22-'08_M_impostos'!$D$35-'09_M_importacoes'!$D$65 -> 643.52559 | E20: =E$5-'06_M_comercio'!$E$22-'07_M_transporte'!$E$22-'08_M_impostos'!$E$35-'09_M_importacoes'!$E$65 -> 74.625951 | F20: =F$5-'06_M_comercio'!$F$22-'07_M_transporte'!$F$22-'08_M_impostos'!$F$35-'09_M_importacoes'!$F$65 -> 361.02023 | G20: =G$5-'06_M_comercio'!$G$22-'07_M_transporte'!$G$22-'08_M_impostos'!$G$35-'09_M_importacoes'!$G$65 -> 164.78255 | H20: =H$5-'06_M_comercio'!$H$22-'07_M_transporte'!$H$22-'08_M_impostos'!$H$35-'09_M_importacoes'!$H$65 -> 137.7409 | I20: =I$5-'06_M_comercio'!$I$22-'07_M_transporte'!$I$22-'08_M_impostos'!$I$35-'09_M_importacoes'!$I$65 -> 11.328523 | J20: =J$5-'06_M_comercio'!$J$22-'07_M_transporte'!$J$22-'08_M_impostos'!$J$35-'09_M_importacoes'!$J$65 -> 5.7055234 | K20: =K$5-'06_M_comercio'!$K$22-'07_M_transporte'!$K$22-'08_M_impostos'!$K$35-'09_M_importacoes'!$K$65 -> 9.5268075 | L20: =L$5-'06_M_comercio'!$L$22-'07_M_transporte'!$L$22-'08_M_impostos'!$L$35-'09_M_importacoes'!$L$65 -> 217.54294 | M20: =M$5-'06_M_comercio'!$M$22-'07_M_transporte'!$M$22-'08_M_impostos'!$M$35-'09_M_importacoes'!$M$65 -> 173.55109 | N20: =N$5-'06_M_comercio'!$N$22-'07_M_transporte'!$N$22-'08_M_impostos'!$N$35-'09_M_importacoes'!$N$65 -> 427.01426 | O20: =O$5-'06_M_comercio'!$O$22-'07_M_transporte'!$O$22-'08_M_impostos'!$O$35-'09_M_importacoes'!$O$65 -> 902.67724 | P20: =P$5-'06_M_comercio'!$P$22-'07_M_transporte'!$P$22-'08_M_impostos'!$P$35-'09_M_importacoes'!$P$65 -> 20.029133 | Q20: =Q$5-'06_M_comercio'!$Q$22-'07_M_transporte'!$Q$22-'08_M_impostos'!$Q$35-'09_M_importacoes'!$Q$65 -> 4128.7887 | R20: =R$5-'06_M_comercio'!$R$22-'07_M_transporte'!$R$22-'08_M_impostos'!$R$35-'09_M_importacoes'!$R$65 -> 0 | S20: =S$5-'06_M_comercio'!$S$22-'07_M_transporte'!$S$22-'08_M_impostos'!$S$35-'09_M_importacoes'!$S$65 -> 413.73004 | T20: =T$5-'06_M_comercio'!$T$22-'07_M_transporte'!$T$22-'08_M_impostos'!$T$35-'09_M_importacoes'!$T$65 -> 383.51441 | U20: =SUM(B20:T20) -> 8501.0597 | V20: ='01_Recursos'!$W$4 -> 8501.0597 | W20: =U20-V20 -> -4.1836756e-11
A21: 04 - Eletricidade e gás, água, esgoto e gestão de resíduos | B21: =B$6-'06_M_comercio'!$B$23-'07_M_transporte'!$B$23-'08_M_impostos'!$B$36-'09_M_importacoes'!$B$66 -> 137.55237 | C21: =C$6-'06_M_comercio'!$C$23-'07_M_transporte'!$C$23-'08_M_impostos'!$C$36-'09_M_importacoes'!$C$66 -> 7.0201736 | D21: =D$6-'06_M_comercio'!$D$23-'07_M_transporte'!$D$23-'08_M_impostos'!$D$36-'09_M_importacoes'!$D$66 -> 121.69797 | E21: =E$6-'06_M_comercio'!$E$23-'07_M_transporte'!$E$23-'08_M_impostos'!$E$36-'09_M_importacoes'!$E$66 -> 1315.2963 | F21: =F$6-'06_M_comercio'!$F$23-'07_M_transporte'!$F$23-'08_M_impostos'!$F$36-'09_M_importacoes'!$F$66 -> 9.7823185 | G21: =G$6-'06_M_comercio'!$G$23-'07_M_transporte'!$G$23-'08_M_impostos'!$G$36-'09_M_importacoes'!$G$66 -> 227.09064 | H21: =H$6-'06_M_comercio'!$H$23-'07_M_transporte'!$H$23-'08_M_impostos'!$H$36-'09_M_importacoes'!$H$66 -> 23.200739 | I21: =I$6-'06_M_comercio'!$I$23-'07_M_transporte'!$I$23-'08_M_impostos'!$I$36-'09_M_importacoes'!$I$66 -> 19.317315 | J21: =J$6-'06_M_comercio'!$J$23-'07_M_transporte'!$J$23-'08_M_impostos'!$J$36-'09_M_importacoes'!$J$66 -> 11.496944 | K21: =K$6-'06_M_comercio'!$K$23-'07_M_transporte'!$K$23-'08_M_impostos'!$K$36-'09_M_importacoes'!$K$66 -> 6.3255456 | L21: =L$6-'06_M_comercio'!$L$23-'07_M_transporte'!$L$23-'08_M_impostos'!$L$36-'09_M_importacoes'!$L$66 -> 192.62871 | M21: =M$6-'06_M_comercio'!$M$23-'07_M_transporte'!$M$23-'08_M_impostos'!$M$36-'09_M_importacoes'!$M$66 -> 339.49378 | N21: =N$6-'06_M_comercio'!$N$23-'07_M_transporte'!$N$23-'08_M_impostos'!$N$36-'09_M_importacoes'!$N$66 -> 0 | O21: =O$6-'06_M_comercio'!$O$23-'07_M_transporte'!$O$23-'08_M_impostos'!$O$36-'09_M_importacoes'!$O$66 -> 545.47546 | P21: =P$6-'06_M_comercio'!$P$23-'07_M_transporte'!$P$23-'08_M_impostos'!$P$36-'09_M_importacoes'!$P$66 -> 0 | Q21: =Q$6-'06_M_comercio'!$Q$23-'07_M_transporte'!$Q$23-'08_M_impostos'!$Q$36-'09_M_importacoes'!$Q$66 -> 1084.9145 | R21: =R$6-'06_M_comercio'!$R$23-'07_M_transporte'!$R$23-'08_M_impostos'!$R$36-'09_M_importacoes'!$R$66 -> 0 | S21: =S$6-'06_M_comercio'!$S$23-'07_M_transporte'!$S$23-'08_M_impostos'!$S$36-'09_M_importacoes'!$S$66 -> 0 | T21: =T$6-'06_M_comercio'!$T$23-'07_M_transporte'!$T$23-'08_M_impostos'!$T$36-'09_M_importacoes'!$T$66 -> 1.4852732 | U21: =SUM(B21:T21) -> 4042.7781 | V21: ='01_Recursos'!$W$5 -> 4042.8136 | W21: =U21-V21 -> -0.035464606
A22: 05 - Construção | B22: =B$7-'06_M_comercio'!$B$24-'07_M_transporte'!$B$24-'08_M_impostos'!$B$37-'09_M_importacoes'!$B$67 -> 3.608063 | C22: =C$7-'06_M_comercio'!$C$24-'07_M_transporte'!$C$24-'08_M_impostos'!$C$37-'09_M_importacoes'!$C$67 -> 0.013013685 | D22: =D$7-'06_M_comercio'!$D$24-'07_M_transporte'!$D$24-'08_M_impostos'!$D$37-'09_M_importacoes'!$D$67 -> 2.1372299 | E22: =E$7-'06_M_comercio'!$E$24-'07_M_transporte'!$E$24-'08_M_impostos'!$E$37-'09_M_importacoes'!$E$67 -> 74.589387 | F22: =F$7-'06_M_comercio'!$F$24-'07_M_transporte'!$F$24-'08_M_impostos'!$F$37-'09_M_importacoes'!$F$67 -> 665.58465 | G22: =G$7-'06_M_comercio'!$G$24-'07_M_transporte'!$G$24-'08_M_impostos'!$G$37-'09_M_importacoes'!$G$67 -> 10.5503 | H22: =H$7-'06_M_comercio'!$H$24-'07_M_transporte'!$H$24-'08_M_impostos'!$H$37-'09_M_importacoes'!$H$67 -> 7.8828084 | I22: =I$7-'06_M_comercio'!$I$24-'07_M_transporte'!$I$24-'08_M_impostos'!$I$37-'09_M_importacoes'!$I$67 -> 32.051015 | J22: =J$7-'06_M_comercio'!$J$24-'07_M_transporte'!$J$24-'08_M_impostos'!$J$37-'09_M_importacoes'!$J$67 -> 4.6333568 | K22: =K$7-'06_M_comercio'!$K$24-'07_M_transporte'!$K$24-'08_M_impostos'!$K$37-'09_M_importacoes'!$K$67 -> 9.9453626 | L22: =L$7-'06_M_comercio'!$L$24-'07_M_transporte'!$L$24-'08_M_impostos'!$L$37-'09_M_importacoes'!$L$67 -> 23.457091 | M22: =M$7-'06_M_comercio'!$M$24-'07_M_transporte'!$M$24-'08_M_impostos'!$M$37-'09_M_importacoes'!$M$67 -> 342.63128 | N22: =N$7-'06_M_comercio'!$N$24-'07_M_transporte'!$N$24-'08_M_impostos'!$N$37-'09_M_importacoes'!$N$67 -> 0 | O22: =O$7-'06_M_comercio'!$O$24-'07_M_transporte'!$O$24-'08_M_impostos'!$O$37-'09_M_importacoes'!$O$67 -> 0 | P22: =P$7-'06_M_comercio'!$P$24-'07_M_transporte'!$P$24-'08_M_impostos'!$P$37-'09_M_importacoes'!$P$67 -> 0 | Q22: =Q$7-'06_M_comercio'!$Q$24-'07_M_transporte'!$Q$24-'08_M_impostos'!$Q$37-'09_M_importacoes'!$Q$67 -> 0 | R22: =R$7-'06_M_comercio'!$R$24-'07_M_transporte'!$R$24-'08_M_impostos'!$R$37-'09_M_importacoes'!$R$67 -> 0 | S22: =S$7-'06_M_comercio'!$S$24-'07_M_transporte'!$S$24-'08_M_impostos'!$S$37-'09_M_importacoes'!$S$67 -> 4595.099 | T22: =T$7-'06_M_comercio'!$T$24-'07_M_transporte'!$T$24-'08_M_impostos'!$T$37-'09_M_importacoes'!$T$67 -> 0 | U22: =SUM(B22:T22) -> 5772.1826 | V22: ='01_Recursos'!$W$6 -> 5772.1826 | W22: =U22-V22 -> 0
A23: 06 - Comércio | B23: =B$8-'06_M_comercio'!$B$25-'07_M_transporte'!$B$25-'08_M_impostos'!$B$38-'09_M_importacoes'!$B$68 -> 524.20625 | C23: =C$8-'06_M_comercio'!$C$25-'07_M_transporte'!$C$25-'08_M_impostos'!$C$38-'09_M_importacoes'!$C$68 -> 13.102172 | D23: =D$8-'06_M_comercio'!$D$25-'07_M_transporte'!$D$25-'08_M_impostos'!$D$38-'09_M_importacoes'!$D$68 -> 817.48395 | E23: =E$8-'06_M_comercio'!$E$25-'07_M_transporte'!$E$25-'08_M_impostos'!$E$38-'09_M_importacoes'!$E$68 -> 78.240183 | F23: =F$8-'06_M_comercio'!$F$25-'07_M_transporte'!$F$25-'08_M_impostos'!$F$38-'09_M_importacoes'!$F$68 -> 438.71917 | G23: =G$8-'06_M_comercio'!$G$25-'07_M_transporte'!$G$25-'08_M_impostos'!$G$38-'09_M_importacoes'!$G$68 -> 108.86565 | H23: =H$8-'06_M_comercio'!$H$25-'07_M_transporte'!$H$25-'08_M_impostos'!$H$38-'09_M_importacoes'!$H$68 -> 99.508203 | I23: =I$8-'06_M_comercio'!$I$25-'07_M_transporte'!$I$25-'08_M_impostos'!$I$38-'09_M_importacoes'!$I$68 -> -9.6543281 | J23: =J$8-'06_M_comercio'!$J$25-'07_M_transporte'!$J$25-'08_M_impostos'!$J$38-'09_M_importacoes'!$J$68 -> 10.55836 | K23: =K$8-'06_M_comercio'!$K$25-'07_M_transporte'!$K$25-'08_M_impostos'!$K$38-'09_M_importacoes'!$K$68 -> 12.159504 | L23: =L$8-'06_M_comercio'!$L$25-'07_M_transporte'!$L$25-'08_M_impostos'!$L$38-'09_M_importacoes'!$L$68 -> 258.84245 | M23: =M$8-'06_M_comercio'!$M$25-'07_M_transporte'!$M$25-'08_M_impostos'!$M$38-'09_M_importacoes'!$M$68 -> 153.53031 | N23: =N$8-'06_M_comercio'!$N$25-'07_M_transporte'!$N$25-'08_M_impostos'!$N$38-'09_M_importacoes'!$N$68 -> 323.05485 | O23: =O$8-'06_M_comercio'!$O$25-'07_M_transporte'!$O$25-'08_M_impostos'!$O$38-'09_M_importacoes'!$O$68 -> 1208.135 | P23: =P$8-'06_M_comercio'!$P$25-'07_M_transporte'!$P$25-'08_M_impostos'!$P$38-'09_M_importacoes'!$P$68 -> 24.191188 | Q23: =Q$8-'06_M_comercio'!$Q$25-'07_M_transporte'!$Q$25-'08_M_impostos'!$Q$38-'09_M_importacoes'!$Q$68 -> 4561.3891 | R23: =R$8-'06_M_comercio'!$R$25-'07_M_transporte'!$R$25-'08_M_impostos'!$R$38-'09_M_importacoes'!$R$68 -> 0 | S23: =S$8-'06_M_comercio'!$S$25-'07_M_transporte'!$S$25-'08_M_impostos'!$S$38-'09_M_importacoes'!$S$68 -> 516.67023 | T23: =T$8-'06_M_comercio'!$T$25-'07_M_transporte'!$T$25-'08_M_impostos'!$T$38-'09_M_importacoes'!$T$68 -> 539.28139 | U23: =SUM(B23:T23) -> 9678.2836 | V23: ='01_Recursos'!$W$7 -> 9678.2836 | W23: =U23-V23 -> 0
A24: 07 - Transporte, armazenagem e correio | B24: =B$9-'06_M_comercio'!$B$26-'07_M_transporte'!$B$26-'08_M_impostos'!$B$39-'09_M_importacoes'!$B$69 -> 102.53044 | C24: =C$9-'06_M_comercio'!$C$26-'07_M_transporte'!$C$26-'08_M_impostos'!$C$39-'09_M_importacoes'!$C$69 -> 5.4041784 | D24: =D$9-'06_M_comercio'!$D$26-'07_M_transporte'!$D$26-'08_M_impostos'!$D$39-'09_M_importacoes'!$D$69 -> 346.76257 | E24: =E$9-'06_M_comercio'!$E$26-'07_M_transporte'!$E$26-'08_M_impostos'!$E$39-'09_M_importacoes'!$E$69 -> 19.570656 | F24: =F$9-'06_M_comercio'!$F$26-'07_M_transporte'!$F$26-'08_M_impostos'!$F$39-'09_M_importacoes'!$F$69 -> 54.623922 | G24: =G$9-'06_M_comercio'!$G$26-'07_M_transporte'!$G$26-'08_M_impostos'!$G$39-'09_M_importacoes'!$G$69 -> 333.73221 | H24: =H$9-'06_M_comercio'!$H$26-'07_M_transporte'!$H$26-'08_M_impostos'!$H$39-'09_M_importacoes'!$H$69 -> 215.03365 | I24: =I$9-'06_M_comercio'!$I$26-'07_M_transporte'!$I$26-'08_M_impostos'!$I$39-'09_M_importacoes'!$I$69 -> 8.0754271 | J24: =J$9-'06_M_comercio'!$J$26-'07_M_transporte'!$J$26-'08_M_impostos'!$J$39-'09_M_importacoes'!$J$69 -> 19.375278 | K24: =K$9-'06_M_comercio'!$K$26-'07_M_transporte'!$K$26-'08_M_impostos'!$K$39-'09_M_importacoes'!$K$69 -> 2.4996887 | L24: =L$9-'06_M_comercio'!$L$26-'07_M_transporte'!$L$26-'08_M_impostos'!$L$39-'09_M_importacoes'!$L$69 -> 102.63652 | M24: =M$9-'06_M_comercio'!$M$26-'07_M_transporte'!$M$26-'08_M_impostos'!$M$39-'09_M_importacoes'!$M$69 -> 149.41565 | N24: =N$9-'06_M_comercio'!$N$26-'07_M_transporte'!$N$26-'08_M_impostos'!$N$39-'09_M_importacoes'!$N$69 -> 46.529087 | O24: =O$9-'06_M_comercio'!$O$26-'07_M_transporte'!$O$26-'08_M_impostos'!$O$39-'09_M_importacoes'!$O$69 -> 71.509935 | P24: =P$9-'06_M_comercio'!$P$26-'07_M_transporte'!$P$26-'08_M_impostos'!$P$39-'09_M_importacoes'!$P$69 -> 1.017624 | Q24: =Q$9-'06_M_comercio'!$Q$26-'07_M_transporte'!$Q$26-'08_M_impostos'!$Q$39-'09_M_importacoes'!$Q$69 -> 1046.7295 | R24: =R$9-'06_M_comercio'!$R$26-'07_M_transporte'!$R$26-'08_M_impostos'!$R$39-'09_M_importacoes'!$R$69 -> 0 | S24: =S$9-'06_M_comercio'!$S$26-'07_M_transporte'!$S$26-'08_M_impostos'!$S$39-'09_M_importacoes'!$S$69 -> 22.758401 | T24: =T$9-'06_M_comercio'!$T$26-'07_M_transporte'!$T$26-'08_M_impostos'!$T$39-'09_M_importacoes'!$T$69 -> 36.682732 | U24: =SUM(B24:T24) -> 2584.8875 | V24: ='01_Recursos'!$W$8 -> 2584.6516 | W24: =U24-V24 -> 0.23582886
A25: 08 - Informação e comunicação | B25: =B$10-'06_M_comercio'!$B$27-'07_M_transporte'!$B$27-'08_M_impostos'!$B$40-'09_M_importacoes'!$B$70 -> 0.41385026 | C25: =C$10-'06_M_comercio'!$C$27-'07_M_transporte'!$C$27-'08_M_impostos'!$C$40-'09_M_importacoes'!$C$70 -> 0.15333839 | D25: =D$10-'06_M_comercio'!$D$27-'07_M_transporte'!$D$27-'08_M_impostos'!$D$40-'09_M_importacoes'!$D$70 -> 32.710907 | E25: =E$10-'06_M_comercio'!$E$27-'07_M_transporte'!$E$27-'08_M_impostos'!$E$40-'09_M_importacoes'!$E$70 -> 27.587886 | F25: =F$10-'06_M_comercio'!$F$27-'07_M_transporte'!$F$27-'08_M_impostos'!$F$40-'09_M_importacoes'!$F$70 -> 11.229204 | G25: =G$10-'06_M_comercio'!$G$27-'07_M_transporte'!$G$27-'08_M_impostos'!$G$40-'09_M_importacoes'!$G$70 -> 103.4362 | H25: =H$10-'06_M_comercio'!$H$27-'07_M_transporte'!$H$27-'08_M_impostos'!$H$40-'09_M_importacoes'!$H$70 -> 21.316762 | I25: =I$10-'06_M_comercio'!$I$27-'07_M_transporte'!$I$27-'08_M_impostos'!$I$40-'09_M_importacoes'!$I$70 -> 175.34729 | J25: =J$10-'06_M_comercio'!$J$27-'07_M_transporte'!$J$27-'08_M_impostos'!$J$40-'09_M_importacoes'!$J$70 -> 70.64115 | K25: =K$10-'06_M_comercio'!$K$27-'07_M_transporte'!$K$27-'08_M_impostos'!$K$40-'09_M_importacoes'!$K$70 -> 4.0118636 | L25: =L$10-'06_M_comercio'!$L$27-'07_M_transporte'!$L$27-'08_M_impostos'!$L$40-'09_M_importacoes'!$L$70 -> 137.30914 | M25: =M$10-'06_M_comercio'!$M$27-'07_M_transporte'!$M$27-'08_M_impostos'!$M$40-'09_M_importacoes'!$M$70 -> 267.861 | N25: =N$10-'06_M_comercio'!$N$27-'07_M_transporte'!$N$27-'08_M_impostos'!$N$40-'09_M_importacoes'!$N$70 -> 2.5648765 | O25: =O$10-'06_M_comercio'!$O$27-'07_M_transporte'!$O$27-'08_M_impostos'!$O$40-'09_M_importacoes'!$O$70 -> 17.89135 | P25: =P$10-'06_M_comercio'!$P$27-'07_M_transporte'!$P$27-'08_M_impostos'!$P$40-'09_M_importacoes'!$P$70 -> 0 | Q25: =Q$10-'06_M_comercio'!$Q$27-'07_M_transporte'!$Q$27-'08_M_impostos'!$Q$40-'09_M_importacoes'!$Q$70 -> 553.17001 | R25: =R$10-'06_M_comercio'!$R$27-'07_M_transporte'!$R$27-'08_M_impostos'!$R$40-'09_M_importacoes'!$R$70 -> 0 | S25: =S$10-'06_M_comercio'!$S$27-'07_M_transporte'!$S$27-'08_M_impostos'!$S$40-'09_M_importacoes'!$S$70 -> 73.926374 | T25: =T$10-'06_M_comercio'!$T$27-'07_M_transporte'!$T$27-'08_M_impostos'!$T$40-'09_M_importacoes'!$T$70 -> -0.30573051 | U25: =SUM(B25:T25) -> 1499.2655 | V25: ='01_Recursos'!$W$9 -> 1499.2655 | W25: =U25-V25 -> -5.2295945e-12
A26: 09 - Atividades financeiras, de seguros e serviços relacionados | B26: =B$11-'06_M_comercio'!$B$28-'07_M_transporte'!$B$28-'08_M_impostos'!$B$41-'09_M_importacoes'!$B$71 -> 49.033294 | C26: =C$11-'06_M_comercio'!$C$28-'07_M_transporte'!$C$28-'08_M_impostos'!$C$41-'09_M_importacoes'!$C$71 -> 2.747086 | D26: =D$11-'06_M_comercio'!$D$28-'07_M_transporte'!$D$28-'08_M_impostos'!$D$41-'09_M_importacoes'!$D$71 -> 68.784334 | E26: =E$11-'06_M_comercio'!$E$28-'07_M_transporte'!$E$28-'08_M_impostos'!$E$41-'09_M_importacoes'!$E$71 -> 49.170489 | F26: =F$11-'06_M_comercio'!$F$28-'07_M_transporte'!$F$28-'08_M_impostos'!$F$41-'09_M_importacoes'!$F$71 -> 36.372773 | G26: =G$11-'06_M_comercio'!$G$28-'07_M_transporte'!$G$28-'08_M_impostos'!$G$41-'09_M_importacoes'!$G$71 -> 92.551741 | H26: =H$11-'06_M_comercio'!$H$28-'07_M_transporte'!$H$28-'08_M_impostos'!$H$41-'09_M_importacoes'!$H$71 -> 26.733388 | I26: =I$11-'06_M_comercio'!$I$28-'07_M_transporte'!$I$28-'08_M_impostos'!$I$41-'09_M_importacoes'!$I$71 -> 25.100171 | J26: =J$11-'06_M_comercio'!$J$28-'07_M_transporte'!$J$28-'08_M_impostos'!$J$41-'09_M_importacoes'!$J$71 -> 137.60983 | K26: =K$11-'06_M_comercio'!$K$28-'07_M_transporte'!$K$28-'08_M_impostos'!$K$41-'09_M_importacoes'!$K$71 -> 57.591658 | L26: =L$11-'06_M_comercio'!$L$28-'07_M_transporte'!$L$28-'08_M_impostos'!$L$41-'09_M_importacoes'!$L$71 -> 55.947753 | M26: =M$11-'06_M_comercio'!$M$28-'07_M_transporte'!$M$28-'08_M_impostos'!$M$41-'09_M_importacoes'!$M$71 -> 252.01112 | N26: =N$11-'06_M_comercio'!$N$28-'07_M_transporte'!$N$28-'08_M_impostos'!$N$41-'09_M_importacoes'!$N$71 -> 8.4055004 | O26: =O$11-'06_M_comercio'!$O$28-'07_M_transporte'!$O$28-'08_M_impostos'!$O$41-'09_M_importacoes'!$O$71 -> 0 | P26: =P$11-'06_M_comercio'!$P$28-'07_M_transporte'!$P$28-'08_M_impostos'!$P$41-'09_M_importacoes'!$P$71 -> 2.9089627 | Q26: =Q$11-'06_M_comercio'!$Q$28-'07_M_transporte'!$Q$28-'08_M_impostos'!$Q$41-'09_M_importacoes'!$Q$71 -> 1429.6683 | R26: =R$11-'06_M_comercio'!$R$28-'07_M_transporte'!$R$28-'08_M_impostos'!$R$41-'09_M_importacoes'!$R$71 -> 0 | S26: =S$11-'06_M_comercio'!$S$28-'07_M_transporte'!$S$28-'08_M_impostos'!$S$41-'09_M_importacoes'!$S$71 -> 0 | T26: =T$11-'06_M_comercio'!$T$28-'07_M_transporte'!$T$28-'08_M_impostos'!$T$41-'09_M_importacoes'!$T$71 -> 0 | U26: =SUM(B26:T26) -> 2294.6364 | V26: ='01_Recursos'!$W$10 -> 2294.6362 | W26: =U26-V26 -> 0.00017510846
A27: 10 - Atividades imobiliárias | B27: =B$12-'06_M_comercio'!$B$29-'07_M_transporte'!$B$29-'08_M_impostos'!$B$42-'09_M_importacoes'!$B$72 -> 0.22420049 | C27: =C$12-'06_M_comercio'!$C$29-'07_M_transporte'!$C$29-'08_M_impostos'!$C$42-'09_M_importacoes'!$C$72 -> 0.4363796 | D27: =D$12-'06_M_comercio'!$D$29-'07_M_transporte'!$D$29-'08_M_impostos'!$D$42-'09_M_importacoes'!$D$72 -> 20.744279 | E27: =E$12-'06_M_comercio'!$E$29-'07_M_transporte'!$E$29-'08_M_impostos'!$E$42-'09_M_importacoes'!$E$72 -> 22.168472 | F27: =F$12-'06_M_comercio'!$F$29-'07_M_transporte'!$F$29-'08_M_impostos'!$F$42-'09_M_importacoes'!$F$72 -> 12.935309 | G27: =G$12-'06_M_comercio'!$G$29-'07_M_transporte'!$G$29-'08_M_impostos'!$G$42-'09_M_importacoes'!$G$72 -> 352.88326 | H27: =H$12-'06_M_comercio'!$H$29-'07_M_transporte'!$H$29-'08_M_impostos'!$H$42-'09_M_importacoes'!$H$72 -> 43.085829 | I27: =I$12-'06_M_comercio'!$I$29-'07_M_transporte'!$I$29-'08_M_impostos'!$I$42-'09_M_importacoes'!$I$72 -> 24.131469 | J27: =J$12-'06_M_comercio'!$J$29-'07_M_transporte'!$J$29-'08_M_impostos'!$J$42-'09_M_importacoes'!$J$72 -> 21.598307 | K27: =K$12-'06_M_comercio'!$K$29-'07_M_transporte'!$K$29-'08_M_impostos'!$K$42-'09_M_importacoes'!$K$72 -> 12.009724 | L27: =L$12-'06_M_comercio'!$L$29-'07_M_transporte'!$L$29-'08_M_impostos'!$L$42-'09_M_importacoes'!$L$72 -> 180.83351 | M27: =M$12-'06_M_comercio'!$M$29-'07_M_transporte'!$M$29-'08_M_impostos'!$M$42-'09_M_importacoes'!$M$72 -> 50.155175 | N27: =N$12-'06_M_comercio'!$N$29-'07_M_transporte'!$N$29-'08_M_impostos'!$N$42-'09_M_importacoes'!$N$72 -> 0 | O27: =O$12-'06_M_comercio'!$O$29-'07_M_transporte'!$O$29-'08_M_impostos'!$O$42-'09_M_importacoes'!$O$72 -> 3.7006865 | P27: =P$12-'06_M_comercio'!$P$29-'07_M_transporte'!$P$29-'08_M_impostos'!$P$42-'09_M_importacoes'!$P$72 -> 0 | Q27: =Q$12-'06_M_comercio'!$Q$29-'07_M_transporte'!$Q$29-'08_M_impostos'!$Q$42-'09_M_importacoes'!$Q$72 -> 3515.6702 | R27: =R$12-'06_M_comercio'!$R$29-'07_M_transporte'!$R$29-'08_M_impostos'!$R$42-'09_M_importacoes'!$R$72 -> 0 | S27: =S$12-'06_M_comercio'!$S$29-'07_M_transporte'!$S$29-'08_M_impostos'!$S$42-'09_M_importacoes'!$S$72 -> 0 | T27: =T$12-'06_M_comercio'!$T$29-'07_M_transporte'!$T$29-'08_M_impostos'!$T$42-'09_M_importacoes'!$T$72 -> 0 | U27: =SUM(B27:T27) -> 4260.5768 | V27: ='01_Recursos'!$W$11 -> 4260.5768 | W27: =U27-V27 -> 0
A28: 11 - Outras atividades de serviços | B28: =B$13-'06_M_comercio'!$B$30-'07_M_transporte'!$B$30-'08_M_impostos'!$B$43-'09_M_importacoes'!$B$73 -> 26.849569 | C28: =C$13-'06_M_comercio'!$C$30-'07_M_transporte'!$C$30-'08_M_impostos'!$C$43-'09_M_importacoes'!$C$73 -> 7.986037 | D28: =D$13-'06_M_comercio'!$D$30-'07_M_transporte'!$D$30-'08_M_impostos'!$D$43-'09_M_importacoes'!$D$73 -> 292.45964 | E28: =E$13-'06_M_comercio'!$E$30-'07_M_transporte'!$E$30-'08_M_impostos'!$E$43-'09_M_importacoes'!$E$73 -> 182.46268 | F28: =F$13-'06_M_comercio'!$F$30-'07_M_transporte'!$F$30-'08_M_impostos'!$F$43-'09_M_importacoes'!$F$73 -> 114.09985 | G28: =G$13-'06_M_comercio'!$G$30-'07_M_transporte'!$G$30-'08_M_impostos'!$G$43-'09_M_importacoes'!$G$73 -> 636.76834 | H28: =H$13-'06_M_comercio'!$H$30-'07_M_transporte'!$H$30-'08_M_impostos'!$H$43-'09_M_importacoes'!$H$73 -> 117.59633 | I28: =I$13-'06_M_comercio'!$I$30-'07_M_transporte'!$I$30-'08_M_impostos'!$I$43-'09_M_importacoes'!$I$73 -> 215.76733 | J28: =J$13-'06_M_comercio'!$J$30-'07_M_transporte'!$J$30-'08_M_impostos'!$J$43-'09_M_importacoes'!$J$73 -> 166.67856 | K28: =K$13-'06_M_comercio'!$K$30-'07_M_transporte'!$K$30-'08_M_impostos'!$K$43-'09_M_importacoes'!$K$73 -> 22.187163 | L28: =L$13-'06_M_comercio'!$L$30-'07_M_transporte'!$L$30-'08_M_impostos'!$L$43-'09_M_importacoes'!$L$73 -> 575.93254 | M28: =M$13-'06_M_comercio'!$M$30-'07_M_transporte'!$M$30-'08_M_impostos'!$M$43-'09_M_importacoes'!$M$73 -> 1016.176 | N28: =N$13-'06_M_comercio'!$N$30-'07_M_transporte'!$N$30-'08_M_impostos'!$N$43-'09_M_importacoes'!$N$73 -> 39.490348 | O28: =O$13-'06_M_comercio'!$O$30-'07_M_transporte'!$O$30-'08_M_impostos'!$O$43-'09_M_importacoes'!$O$73 -> 135.78653 | P28: =P$13-'06_M_comercio'!$P$30-'07_M_transporte'!$P$30-'08_M_impostos'!$P$43-'09_M_importacoes'!$P$73 -> 359.9113 | Q28: =Q$13-'06_M_comercio'!$Q$30-'07_M_transporte'!$Q$30-'08_M_impostos'!$Q$43-'09_M_importacoes'!$Q$73 -> 5624.1174 | R28: =R$13-'06_M_comercio'!$R$30-'07_M_transporte'!$R$30-'08_M_impostos'!$R$43-'09_M_importacoes'!$R$73 -> 295.07835 | S28: =S$13-'06_M_comercio'!$S$30-'07_M_transporte'!$S$30-'08_M_impostos'!$S$43-'09_M_importacoes'!$S$73 -> 101.17909 | T28: =T$13-'06_M_comercio'!$T$30-'07_M_transporte'!$T$30-'08_M_impostos'!$T$43-'09_M_importacoes'!$T$73 -> 0 | U28: =SUM(B28:T28) -> 9930.527 | V28: ='01_Recursos'!$W$12 -> 9930.527 | W28: =U28-V28 -> 0
A29: 12 - Administração, defesa, saúde e educação públicas e seguridade social | B29: =B$14-'06_M_comercio'!$B$31-'07_M_transporte'!$B$31-'08_M_impostos'!$B$44-'09_M_importacoes'!$B$74 -> 0 | C29: =C$14-'06_M_comercio'!$C$31-'07_M_transporte'!$C$31-'08_M_impostos'!$C$44-'09_M_importacoes'!$C$74 -> 0 | D29: =D$14-'06_M_comercio'!$D$31-'07_M_transporte'!$D$31-'08_M_impostos'!$D$44-'09_M_importacoes'!$D$74 -> 0 | E29: =E$14-'06_M_comercio'!$E$31-'07_M_transporte'!$E$31-'08_M_impostos'!$E$44-'09_M_importacoes'!$E$74 -> 0 | F29: =F$14-'06_M_comercio'!$F$31-'07_M_transporte'!$F$31-'08_M_impostos'!$F$44-'09_M_importacoes'!$F$74 -> 0 | G29: =G$14-'06_M_comercio'!$G$31-'07_M_transporte'!$G$31-'08_M_impostos'!$G$44-'09_M_importacoes'!$G$74 -> 0 | H29: =H$14-'06_M_comercio'!$H$31-'07_M_transporte'!$H$31-'08_M_impostos'!$H$44-'09_M_importacoes'!$H$74 -> 0 | I29: =I$14-'06_M_comercio'!$I$31-'07_M_transporte'!$I$31-'08_M_impostos'!$I$44-'09_M_importacoes'!$I$74 -> 0 | J29: =J$14-'06_M_comercio'!$J$31-'07_M_transporte'!$J$31-'08_M_impostos'!$J$44-'09_M_importacoes'!$J$74 -> 0 | K29: =K$14-'06_M_comercio'!$K$31-'07_M_transporte'!$K$31-'08_M_impostos'!$K$44-'09_M_importacoes'!$K$74 -> 0 | L29: =L$14-'06_M_comercio'!$L$31-'07_M_transporte'!$L$31-'08_M_impostos'!$L$44-'09_M_importacoes'!$L$74 -> 0 | M29: =M$14-'06_M_comercio'!$M$31-'07_M_transporte'!$M$31-'08_M_impostos'!$M$44-'09_M_importacoes'!$M$74 -> 0 | N29: =N$14-'06_M_comercio'!$N$31-'07_M_transporte'!$N$31-'08_M_impostos'!$N$44-'09_M_importacoes'!$N$74 -> 0 | O29: =O$14-'06_M_comercio'!$O$31-'07_M_transporte'!$O$31-'08_M_impostos'!$O$44-'09_M_importacoes'!$O$74 -> 0 | P29: =P$14-'06_M_comercio'!$P$31-'07_M_transporte'!$P$31-'08_M_impostos'!$P$44-'09_M_importacoes'!$P$74 -> 19314.545 | Q29: =Q$14-'06_M_comercio'!$Q$31-'07_M_transporte'!$Q$31-'08_M_impostos'!$Q$44-'09_M_importacoes'!$Q$74 -> 0 | R29: =R$14-'06_M_comercio'!$R$31-'07_M_transporte'!$R$31-'08_M_impostos'!$R$44-'09_M_importacoes'!$R$74 -> 0 | S29: =S$14-'06_M_comercio'!$S$31-'07_M_transporte'!$S$31-'08_M_impostos'!$S$44-'09_M_importacoes'!$S$74 -> 0 | T29: =T$14-'06_M_comercio'!$T$31-'07_M_transporte'!$T$31-'08_M_impostos'!$T$44-'09_M_importacoes'!$T$74 -> 0 | U29: =SUM(B29:T29) -> 19314.545 | V29: ='01_Recursos'!$W$13 -> 19314.545 | W29: =U29-V29 -> 8.0035534e-10
A32: Celulas que ficaram negativas apos a passagem a precos basicos | B32: =SUMPRODUCT(($B$18:$T$29<(-0.00000001))*($B$3:$T$14>=0)) -> 1

Sheet 11_D
A1: ETAPA 14 - matriz D: participacao de cada atividade na producao de cada produto
A2: Atividade \ Produto | B2: 01 - Agropecuária | C2: 02 - Indústrias extrativas | D2: 03 - Indústrias de transformação | E2: 04 - Eletricidade e gás, água, esgoto e gestão de resíduos | F2: 05 - Construção | G2: 06 - Comércio | H2: 07 - Transporte, armazenagem e correio | I2: 08 - Informação e comunicação | J2: 09 - Atividades financeiras, de seguros e serviços relacionados | K2: 10 - Atividades imobiliárias | L2: 11 - Outras atividades de serviços | M2: 12 - Administração, defesa, saúde e educação públicas e seguridade social
A3: 01 - Agropecuária | B3: ='01_Recursos'!$B$2/'01_Recursos'!$W$2 -> 0.99765501 | C3: ='01_Recursos'!$B$3/'01_Recursos'!$W$3 -> 0.0076874932 | D3: ='01_Recursos'!$B$4/'01_Recursos'!$W$4 -> 0.023930892 | E3: ='01_Recursos'!$B$5/'01_Recursos'!$W$5 -> 0 | F3: ='01_Recursos'!$B$6/'01_Recursos'!$W$6 -> 0.012549095 | G3: ='01_Recursos'!$B$7/'01_Recursos'!$W$7 -> 0 | H3: ='01_Recursos'!$B$8/'01_Recursos'!$W$8 -> 0 | I3: ='01_Recursos'!$B$9/'01_Recursos'!$W$9 -> 0 | J3: ='01_Recursos'!$B$10/'01_Recursos'!$W$10 -> 0 | K3: ='01_Recursos'!$B$11/'01_Recursos'!$W$11 -> 0.0001756674 | L3: ='01_Recursos'!$B$12/'01_Recursos'!$W$12 -> 2.8580131e-05 | M3: ='01_Recursos'!$B$13/'01_Recursos'!$W$13 -> 0
A4: 02 - Indústrias extrativas | B4: ='01_Recursos'!$C$2/'01_Recursos'!$W$2 -> 0 | C4: ='01_Recursos'!$C$3/'01_Recursos'!$W$3 -> 0.97658957 | D4: ='01_Recursos'!$C$4/'01_Recursos'!$W$4 -> 0.000632418 | E4: ='01_Recursos'!$C$5/'01_Recursos'!$W$5 -> 0 | F4: ='01_Recursos'!$C$6/'01_Recursos'!$W$6 -> 0 | G4: ='01_Recursos'!$C$7/'01_Recursos'!$W$7 -> 1.5978923e-05 | H4: ='01_Recursos'!$C$8/'01_Recursos'!$W$8 -> 0 | I4: ='01_Recursos'!$C$9/'01_Recursos'!$W$9 -> 0 | J4: ='01_Recursos'!$C$10/'01_Recursos'!$W$10 -> 0 | K4: ='01_Recursos'!$C$11/'01_Recursos'!$W$11 -> 8.8294716e-05 | L4: ='01_Recursos'!$C$12/'01_Recursos'!$W$12 -> 0 | M4: ='01_Recursos'!$C$13/'01_Recursos'!$W$13 -> 0
A5: 03 - Indústrias de transformação | B5: ='01_Recursos'!$D$2/'01_Recursos'!$W$2 -> 0 | C5: ='01_Recursos'!$D$3/'01_Recursos'!$W$3 -> 0.015596448 | D5: ='01_Recursos'!$D$4/'01_Recursos'!$W$4 -> 0.93610785 | E5: ='01_Recursos'!$D$5/'01_Recursos'!$W$5 -> 0 | F5: ='01_Recursos'!$D$6/'01_Recursos'!$W$6 -> 0 | G5: ='01_Recursos'!$D$7/'01_Recursos'!$W$7 -> 0.014934224 | H5: ='01_Recursos'!$D$8/'01_Recursos'!$W$8 -> 0 | I5: ='01_Recursos'!$D$9/'01_Recursos'!$W$9 -> 0 | J5: ='01_Recursos'!$D$10/'01_Recursos'!$W$10 -> 0 | K5: ='01_Recursos'!$D$11/'01_Recursos'!$W$11 -> 0.0093327846 | L5: ='01_Recursos'!$D$12/'01_Recursos'!$W$12 -> 1.3265697e-05 | M5: ='01_Recursos'!$D$13/'01_Recursos'!$W$13 -> 0
A6: 04 - Eletricidade e gás, água, esgoto e gestão de resíduos | B6: ='01_Recursos'!$E$2/'01_Recursos'!$W$2 -> 0 | C6: ='01_Recursos'!$E$3/'01_Recursos'!$W$3 -> 0 | D6: ='01_Recursos'!$E$4/'01_Recursos'!$W$4 -> 0 | E6: ='01_Recursos'!$E$5/'01_Recursos'!$W$5 -> 0.99812855 | F6: ='01_Recursos'!$E$6/'01_Recursos'!$W$6 -> 0 | G6: ='01_Recursos'!$E$7/'01_Recursos'!$W$7 -> 0 | H6: ='01_Recursos'!$E$8/'01_Recursos'!$W$8 -> 0 | I6: ='01_Recursos'!$E$9/'01_Recursos'!$W$9 -> 0 | J6: ='01_Recursos'!$E$10/'01_Recursos'!$W$10 -> 0 | K6: ='01_Recursos'!$E$11/'01_Recursos'!$W$11 -> 0.013315129 | L6: ='01_Recursos'!$E$12/'01_Recursos'!$W$12 -> 4.2828395e-08 | M6: ='01_Recursos'!$E$13/'01_Recursos'!$W$13 -> 0
A7: 05 - Construção | B7: ='01_Recursos'!$F$2/'01_Recursos'!$W$2 -> 0 | C7: ='01_Recursos'!$F$3/'01_Recursos'!$W$3 -> 0 | D7: ='01_Recursos'!$F$4/'01_Recursos'!$W$4 -> 4.964508e-06 | E7: ='01_Recursos'!$F$5/'01_Recursos'!$W$5 -> 0 | F7: ='01_Recursos'!$F$6/'01_Recursos'!$W$6 -> 0.9874509 | G7: ='01_Recursos'!$F$7/'01_Recursos'!$W$7 -> 0 | H7: ='01_Recursos'!$F$8/'01_Recursos'!$W$8 -> 0 | I7: ='01_Recursos'!$F$9/'01_Recursos'!$W$9 -> 0 | J7: ='01_Recursos'!$F$10/'01_Recursos'!$W$10 -> 0 | K7: ='01_Recursos'!$F$11/'01_Recursos'!$W$11 -> 0.00090872315 | L7: ='01_Recursos'!$F$12/'01_Recursos'!$W$12 -> 0.00034548178 | M7: ='01_Recursos'!$F$13/'01_Recursos'!$W$13 -> 0
A8: 06 - Comércio | B8: ='01_Recursos'!$G$2/'01_Recursos'!$W$2 -> 0.0010166001 | C8: ='01_Recursos'!$G$3/'01_Recursos'!$W$3 -> 0.00012648606 | D8: ='01_Recursos'!$G$4/'01_Recursos'!$W$4 -> 0.038740848 | E8: ='01_Recursos'!$G$5/'01_Recursos'!$W$5 -> 0 | F8: ='01_Recursos'!$G$6/'01_Recursos'!$W$6 -> 0 | G8: ='01_Recursos'!$G$7/'01_Recursos'!$W$7 -> 0.98178896 | H8: ='01_Recursos'!$G$8/'01_Recursos'!$W$8 -> 0.0039151724 | I8: ='01_Recursos'!$G$9/'01_Recursos'!$W$9 -> 0.0019804288 | J8: ='01_Recursos'!$G$10/'01_Recursos'!$W$10 -> 0 | K8: ='01_Recursos'!$G$11/'01_Recursos'!$W$11 -> 0.0084172791 | L8: ='01_Recursos'!$G$12/'01_Recursos'!$W$12 -> 0.0064656752 | M8: ='01_Recursos'!$G$13/'01_Recursos'!$W$13 -> 0
A9: 07 - Transporte, armazenagem e correio | B9: ='01_Recursos'!$H$2/'01_Recursos'!$W$2 -> 2.6822911e-12 | C9: ='01_Recursos'!$H$3/'01_Recursos'!$W$3 -> 0 | D9: ='01_Recursos'!$H$4/'01_Recursos'!$W$4 -> 3.1968332e-12 | E9: ='01_Recursos'!$H$5/'01_Recursos'!$W$5 -> 0 | F9: ='01_Recursos'!$H$6/'01_Recursos'!$W$6 -> 0 | G9: ='01_Recursos'!$H$7/'01_Recursos'!$W$7 -> 0.00091583843 | H9: ='01_Recursos'!$H$8/'01_Recursos'!$W$8 -> 0.98829724 | I9: ='01_Recursos'!$H$9/'01_Recursos'!$W$9 -> 0.00048259832 | J9: ='01_Recursos'!$H$10/'01_Recursos'!$W$10 -> 0 | K9: ='01_Recursos'!$H$11/'01_Recursos'!$W$11 -> 0.001944623 | L9: ='01_Recursos'!$H$12/'01_Recursos'!$W$12 -> 0.0081846888 | M9: ='01_Recursos'!$H$13/'01_Recursos'!$W$13 -> 0
A10: 08 - Informação e comunicação | B10: ='01_Recursos'!$I$2/'01_Recursos'!$W$2 -> 0 | C10: ='01_Recursos'!$I$3/'01_Recursos'!$W$3 -> 0 | D10: ='01_Recursos'!$I$4/'01_Recursos'!$W$4 -> 0 | E10: ='01_Recursos'!$I$5/'01_Recursos'!$W$5 -> 0 | F10: ='01_Recursos'!$I$6/'01_Recursos'!$W$6 -> 0 | G10: ='01_Recursos'!$I$7/'01_Recursos'!$W$7 -> 0 | H10: ='01_Recursos'!$I$8/'01_Recursos'!$W$8 -> 0 | I10: ='01_Recursos'!$I$9/'01_Recursos'!$W$9 -> 0.99215177 | J10: ='01_Recursos'!$I$10/'01_Recursos'!$W$10 -> 0 | K10: ='01_Recursos'!$I$11/'01_Recursos'!$W$11 -> 3.3096391e-05 | L10: ='01_Recursos'!$I$12/'01_Recursos'!$W$12 -> 1.119758e-05 | M10: ='01_Recursos'!$I$13/'01_Recursos'!$W$13 -> 0
A11: 09 - Atividades financeiras, de seguros e serviços relacionados | B11: ='01_Recursos'!$J$2/'01_Recursos'!$W$2 -> 0 | C11: ='01_Recursos'!$J$3/'01_Recursos'!$W$3 -> 0 | D11: ='01_Recursos'!$J$4/'01_Recursos'!$W$4 -> 0 | E11: ='01_Recursos'!$J$5/'01_Recursos'!$W$5 -> 0 | F11: ='01_Recursos'!$J$6/'01_Recursos'!$W$6 -> 0 | G11: ='01_Recursos'!$J$7/'01_Recursos'!$W$7 -> 0 | H11: ='01_Recursos'!$J$8/'01_Recursos'!$W$8 -> 0 | I11: ='01_Recursos'!$J$9/'01_Recursos'!$W$9 -> 0.0030426923 | J11: ='01_Recursos'!$J$10/'01_Recursos'!$W$10 -> 1 | K11: ='01_Recursos'!$J$11/'01_Recursos'!$W$11 -> 0.0098938425 | L11: ='01_Recursos'!$J$12/'01_Recursos'!$W$12 -> 0.00068964129 | M11: ='01_Recursos'!$J$13/'01_Recursos'!$W$13 -> 0
A12: 10 - Atividades imobiliárias | B12: ='01_Recursos'!$K$2/'01_Recursos'!$W$2 -> 0 | C12: ='01_Recursos'!$K$3/'01_Recursos'!$W$3 -> 0 | D12: ='01_Recursos'!$K$4/'01_Recursos'!$W$4 -> 0 | E12: ='01_Recursos'!$K$5/'01_Recursos'!$W$5 -> 0 | F12: ='01_Recursos'!$K$6/'01_Recursos'!$W$6 -> 0 | G12: ='01_Recursos'!$K$7/'01_Recursos'!$W$7 -> 0 | H12: ='01_Recursos'!$K$8/'01_Recursos'!$W$8 -> 0 | I12: ='01_Recursos'!$K$9/'01_Recursos'!$W$9 -> 0 | J12: ='01_Recursos'!$K$10/'01_Recursos'!$W$10 -> 0 | K12: ='01_Recursos'!$K$11/'01_Recursos'!$W$11 -> 0.94558413 | L12: ='01_Recursos'!$K$12/'01_Recursos'!$W$12 -> 0 | M12: ='01_Recursos'!$K$13/'01_Recursos'!$W$13 -> 0
A13: 11 - Outras atividades de serviços | B13: ='01_Recursos'!$L$2/'01_Recursos'!$W$2 -> 0 | C13: ='01_Recursos'!$L$3/'01_Recursos'!$W$3 -> 0 | D13: ='01_Recursos'!$L$4/'01_Recursos'!$W$4 -> 0.00058302852 | E13: ='01_Recursos'!$L$5/'01_Recursos'!$W$5 -> 0 | F13: ='01_Recursos'!$L$6/'01_Recursos'!$W$6 -> 0 | G13: ='01_Recursos'!$L$7/'01_Recursos'!$W$7 -> 0.0018660685 | H13: ='01_Recursos'!$L$8/'01_Recursos'!$W$8 -> 0 | I13: ='01_Recursos'!$L$9/'01_Recursos'!$W$9 -> 0.00049531996 | J13: ='01_Recursos'!$L$10/'01_Recursos'!$W$10 -> 0 | K13: ='01_Recursos'!$L$11/'01_Recursos'!$W$11 -> 0.008610095 | L13: ='01_Recursos'!$L$12/'01_Recursos'!$W$12 -> 0.95548815 | M13: ='01_Recursos'!$L$13/'01_Recursos'!$W$13 -> 0
A14: 12 - Administração, defesa, saúde e educação públicas e seguridade social | B14: ='01_Recursos'!$M$2/'01_Recursos'!$W$2 -> 0.0013283942 | C14: ='01_Recursos'!$M$3/'01_Recursos'!$W$3 -> 0 | D14: ='01_Recursos'!$M$4/'01_Recursos'!$W$4 -> 0 | E14: ='01_Recursos'!$M$5/'01_Recursos'!$W$5 -> 0.0018714501 | F14: ='01_Recursos'!$M$6/'01_Recursos'!$W$6 -> 0 | G14: ='01_Recursos'!$M$7/'01_Recursos'!$W$7 -> 0.00047892986 | H14: ='01_Recursos'!$M$8/'01_Recursos'!$W$8 -> 0.0077875877 | I14: ='01_Recursos'!$M$9/'01_Recursos'!$W$9 -> 0.0018471898 | J14: ='01_Recursos'!$M$10/'01_Recursos'!$W$10 -> 0 | K14: ='01_Recursos'!$M$11/'01_Recursos'!$W$11 -> 0.0016963347 | L14: ='01_Recursos'!$M$12/'01_Recursos'!$W$12 -> 0.028773282 | M14: ='01_Recursos'!$M$13/'01_Recursos'!$W$13 -> 1
A16: Conferencia: soma da coluna (deve ser 1) | B16: =SUM(B3:B14) -> 1 | C16: =SUM(C3:C14) -> 1 | D16: =SUM(D3:D14) -> 1 | E16: =SUM(E3:E14) -> 1 | F16: =SUM(F3:F14) -> 1 | G16: =SUM(G3:G14) -> 1 | H16: =SUM(H3:H14) -> 1 | I16: =SUM(I3:I14) -> 1 | ... M16: =SUM(M3:M14) -> 1

Sheet 12_X
A1: Setor | B1: Producao da atividade X (soma da coluna de 01_Recursos) | C1: Producao do produto q (soma da linha de 01_Recursos) | D1: Valor adicionado da TRUR
A2: 01 - Agropecuária | B2: ='01_Recursos'!$B$15 -> 7608.7824 | C2: ='01_Recursos'!$W$2 -> 7347.4974 | D2: ='03_VA'!$B$2 -> 4437.2008
A3: 02 - Indústrias extrativas | B3: ='01_Recursos'!$C$15 -> 210.31198 | C3: ='01_Recursos'!$W$3 -> 209.30483 | D3: ='03_VA'!$C$2 -> 109.63955
A4: 03 - Indústrias de transformação | B4: ='01_Recursos'!$D$15 -> 8145.6056 | C4: ='01_Recursos'!$W$4 -> 8501.0597 | D4: ='03_VA'!$D$2 -> 1393.3766
A5: 04 - Eletricidade e gás, água, esgoto e gestão de resíduos | B5: ='01_Recursos'!$E$15 -> 4091.9782 | C5: ='01_Recursos'!$W$5 -> 4042.8136 | D5: ='03_VA'!$E$2 -> 1585.1014
A6: 05 - Construção | B6: ='01_Recursos'!$F$15 -> 5707.0916 | C6: ='01_Recursos'!$W$6 -> 5772.1826 | D6: ='03_VA'!$F$2 -> 2472.1587
A7: 06 - Comércio | B7: ='01_Recursos'!$G$15 -> 9952.0248 | C7: ='01_Recursos'!$W$7 -> 9678.2836 | D7: ='03_VA'!$G$2 -> 6361.656
A8: 07 - Transporte, armazenagem e correio | B8: ='01_Recursos'!$H$15 -> 2653.5548 | C8: ='01_Recursos'!$W$8 -> 2584.6516 | D8: ='03_VA'!$H$2 -> 1146.0445
A9: 08 - Informação e comunicação | B9: ='01_Recursos'!$I$15 -> 1487.7511 | C9: ='01_Recursos'!$W$9 -> 1499.2655 | D9: ='03_VA'!$I$2 -> 640.58395
A10: 09 - Atividades financeiras, de seguros e serviços relacionados | B10: ='01_Recursos'!$J$15 -> 2348.2 | C10: ='01_Recursos'!$W$10 -> 2294.6362 | D10: ='03_VA'!$J$2 -> 1513.6724
A11: 10 - Atividades imobiliárias | B11: ='01_Recursos'!$K$15 -> 4028.7338 | C11: ='01_Recursos'!$W$11 -> 4260.5768 | D11: ='03_VA'!$K$2 -> 3742.3795
A12: 11 - Outras atividades de serviços | B12: ='01_Recursos'!$L$15 -> 9548.9441 | C12: ='01_Recursos'!$W$12 -> 9930.527 | D12: ='03_VA'!$L$2 -> 6401.0099
A13: 12 - Administração, defesa, saúde e educação públicas e seguridade social | B13: ='01_Recursos'!$M$15 -> 19652.365 | C13: ='01_Recursos'!$W$13 -> 19314.545 | D13: ='03_VA'!$M$2 -> 14891.579

Sheet 13_Bn
A1: ETAPA 16a - Bn: CI regional a precos basicos dividido pela producao da atividade
A2: Produto \ Atividade | B2: 01 - Agropecuária | C2: 02 - Indústrias extrativas | D2: 03 - Indústrias de transformação | E2: 04 - Eletricidade e gás, água, esgoto e gestão de resíduos | F2: 05 - Construção | G2: 06 - Comércio | H2: 07 - Transporte, armazenagem e correio | I2: 08 - Informação e comunicação | J2: 09 - Atividades financeiras, de seguros e serviços relacionados | K2: 10 - Atividades imobiliárias | L2: 11 - Outras atividades de serviços | M2: 12 - Administração, defesa, saúde e educação públicas e seguridade social
A3: 01 - Agropecuária | B3: ='10_Usos_basicos'!$B$18/'12_X'!$B$2 -> 0.032970202 | C3: ='10_Usos_basicos'!$C$18/'12_X'!$B$3 -> 4.1475333e-05 | D3: ='10_Usos_basicos'!$D$18/'12_X'!$B$4 -> 0.1456665 | E3: ='10_Usos_basicos'!$E$18/'12_X'!$B$5 -> 4.8426103e-05 | F3: ='10_Usos_basicos'!$F$18/'12_X'!$B$6 -> 0.0012992579 | G3: ='10_Usos_basicos'!$G$18/'12_X'!$B$7 -> 0.0047893251 | H3: ='10_Usos_basicos'!$H$18/'12_X'!$B$8 -> 0 | I3: ='10_Usos_basicos'!$I$18/'12_X'!$B$9 -> 0 | J3: ='10_Usos_basicos'!$J$18/'12_X'!$B$10 -> 0 | K3: ='10_Usos_basicos'!$K$18/'12_X'!$B$11 -> 0 | L3: ='10_Usos_basicos'!$L$18/'12_X'!$B$12 -> 0.0053007333 | M3: ='10_Usos_basicos'!$M$18/'12_X'!$B$13 -> 0.0017136252
A4: 02 - Indústrias extrativas | B4: ='10_Usos_basicos'!$B$19/'12_X'!$B$2 -> 0.00056357923 | C4: ='10_Usos_basicos'!$C$19/'12_X'!$B$3 -> 0.011502758 | D4: ='10_Usos_basicos'!$D$19/'12_X'!$B$4 -> 0.0089191036 | E4: ='10_Usos_basicos'!$E$19/'12_X'!$B$5 -> 0.00047596595 | F4: ='10_Usos_basicos'!$F$19/'12_X'!$B$6 -> 0.0086370509 | G4: ='10_Usos_basicos'!$G$19/'12_X'!$B$7 -> 2.658578e-05 | H4: ='10_Usos_basicos'!$H$19/'12_X'!$B$8 -> 8.4022628e-07 | I4: ='10_Usos_basicos'!$I$19/'12_X'!$B$9 -> 0 | J4: ='10_Usos_basicos'!$J$19/'12_X'!$B$10 -> 0 | K4: ='10_Usos_basicos'!$K$19/'12_X'!$B$11 -> 0.0007116765 | L4: ='10_Usos_basicos'!$L$19/'12_X'!$B$12 -> 2.0806301e-05 | M4: ='10_Usos_basicos'!$M$19/'12_X'!$B$13 -> 4.985162e-05
A5: 03 - Indústrias de transformação | B5: ='10_Usos_basicos'!$B$20/'12_X'!$B$2 -> 0.054579134 | C5: ='10_Usos_basicos'!$C$20/'12_X'!$B$3 -> 0.050758186 | D5: ='10_Usos_basicos'!$D$20/'12_X'!$B$4 -> 0.079002793 | E5: ='10_Usos_basicos'!$E$20/'12_X'!$B$5 -> 0.018237133 | F5: ='10_Usos_basicos'!$F$20/'12_X'!$B$6 -> 0.06325818 | G5: ='10_Usos_basicos'!$G$20/'12_X'!$B$7 -> 0.016557691 | H5: ='10_Usos_basicos'!$H$20/'12_X'!$B$8 -> 0.051908067 | I5: ='10_Usos_basicos'!$I$20/'12_X'!$B$9 -> 0.0076145284 | J5: ='10_Usos_basicos'!$J$20/'12_X'!$B$10 -> 0.0024297434 | K5: ='10_Usos_basicos'!$K$20/'12_X'!$B$11 -> 0.002364715 | L5: ='10_Usos_basicos'!$L$20/'12_X'!$B$12 -> 0.022781884 | M5: ='10_Usos_basicos'!$M$20/'12_X'!$B$13 -> 0.0088310535
A6: 04 - Eletricidade e gás, água, esgoto e gestão de resíduos | B6: ='10_Usos_basicos'!$B$21/'12_X'!$B$2 -> 0.018078105 | C6: ='10_Usos_basicos'!$C$21/'12_X'!$B$3 -> 0.033379809 | D6: ='10_Usos_basicos'!$D$21/'12_X'!$B$4 -> 0.014940322 | E6: ='10_Usos_basicos'!$E$21/'12_X'!$B$5 -> 0.32143288 | F6: ='10_Usos_basicos'!$F$21/'12_X'!$B$6 -> 0.0017140637 | G6: ='10_Usos_basicos'!$G$21/'12_X'!$B$7 -> 0.022818536 | H6: ='10_Usos_basicos'!$H$21/'12_X'!$B$8 -> 0.0087432671 | I6: ='10_Usos_basicos'!$I$21/'12_X'!$B$9 -> 0.012984238 | J6: ='10_Usos_basicos'!$J$21/'12_X'!$B$10 -> 0.0048960666 | K6: ='10_Usos_basicos'!$K$21/'12_X'!$B$11 -> 0.0015701076 | L6: ='10_Usos_basicos'!$L$21/'12_X'!$B$12 -> 0.020172776 | M6: ='10_Usos_basicos'!$M$21/'12_X'!$B$13 -> 0.017274958
A7: 05 - Construção | B7: ='10_Usos_basicos'!$B$22/'12_X'!$B$2 -> 0.00047419715 | C7: ='10_Usos_basicos'!$C$22/'12_X'!$B$3 -> 6.1878003e-05 | D7: ='10_Usos_basicos'!$D$22/'12_X'!$B$4 -> 0.00026237827 | E7: ='10_Usos_basicos'!$E$22/'12_X'!$B$5 -> 0.018228197 | F7: ='10_Usos_basicos'!$F$22/'12_X'!$B$6 -> 0.11662414 | G7: ='10_Usos_basicos'!$G$22/'12_X'!$B$7 -> 0.001060116 | H7: ='10_Usos_basicos'!$H$22/'12_X'!$B$8 -> 0.0029706597 | I7: ='10_Usos_basicos'!$I$22/'12_X'!$B$9 -> 0.021543264 | J7: ='10_Usos_basicos'!$J$22/'12_X'!$B$10 -> 0.0019731525 | K7: ='10_Usos_basicos'!$K$22/'12_X'!$B$11 -> 0.0024686075 | L7: ='10_Usos_basicos'!$L$22/'12_X'!$B$12 -> 0.0024565115 | M7: ='10_Usos_basicos'!$M$22/'12_X'!$B$13 -> 0.017434608
A8: 06 - Comércio | B8: ='10_Usos_basicos'!$B$23/'12_X'!$B$2 -> 0.068894893 | C8: ='10_Usos_basicos'!$C$23/'12_X'!$B$3 -> 0.062298744 | D8: ='10_Usos_basicos'!$D$23/'12_X'!$B$4 -> 0.10035889 | E8: ='10_Usos_basicos'!$E$23/'12_X'!$B$5 -> 0.019120381 | F8: ='10_Usos_basicos'!$F$23/'12_X'!$B$6 -> 0.076872634 | G8: ='10_Usos_basicos'!$G$23/'12_X'!$B$7 -> 0.010939045 | H8: ='10_Usos_basicos'!$H$23/'12_X'!$B$8 -> 0.037499961 | I8: ='10_Usos_basicos'!$I$23/'12_X'!$B$9 -> -0.0064892092 | J8: ='10_Usos_basicos'!$J$23/'12_X'!$B$10 -> 0.0044963633 | K8: ='10_Usos_basicos'!$K$23/'12_X'!$B$11 -> 0.003018195 | L8: ='10_Usos_basicos'!$L$23/'12_X'!$B$12 -> 0.027106919 | M8: ='10_Usos_basicos'!$M$23/'12_X'!$B$13 -> 0.007812307
A9: 07 - Transporte, armazenagem e correio | B9: ='10_Usos_basicos'!$B$24/'12_X'!$B$2 -> 0.013475276 | C9: ='10_Usos_basicos'!$C$24/'12_X'!$B$3 -> 0.025696009 | D9: ='10_Usos_basicos'!$D$24/'12_X'!$B$4 -> 0.042570509 | E9: ='10_Usos_basicos'!$E$24/'12_X'!$B$5 -> 0.0047826882 | F9: ='10_Usos_basicos'!$F$24/'12_X'!$B$6 -> 0.0095712362 | G9: ='10_Usos_basicos'!$G$24/'12_X'!$B$7 -> 0.033534102 | H9: ='10_Usos_basicos'!$H$24/'12_X'!$B$8 -> 0.081036067 | I9: ='10_Usos_basicos'!$I$24/'12_X'!$B$9 -> 0.0054279423 | J9: ='10_Usos_basicos'!$J$24/'12_X'!$B$10 -> 0.0082511191 | K9: ='10_Usos_basicos'!$K$24/'12_X'!$B$11 -> 0.00062046508 | L9: ='10_Usos_basicos'!$L$24/'12_X'!$B$12 -> 0.010748468 | M9: ='10_Usos_basicos'!$M$24/'12_X'!$B$13 -> 0.0076029345
A10: 08 - Informação e comunicação | B10: ='10_Usos_basicos'!$B$25/'12_X'!$B$2 -> 5.4391128e-05 | C10: ='10_Usos_basicos'!$C$25/'12_X'!$B$3 -> 0.00072909965 | D10: ='10_Usos_basicos'!$D$25/'12_X'!$B$4 -> 0.0040157735 | E10: ='10_Usos_basicos'!$E$25/'12_X'!$B$5 -> 0.0067419435 | F10: ='10_Usos_basicos'!$F$25/'12_X'!$B$6 -> 0.0019675879 | G10: ='10_Usos_basicos'!$G$25/'12_X'!$B$7 -> 0.010393483 | H10: ='10_Usos_basicos'!$H$25/'12_X'!$B$8 -> 0.0080332849 | I10: ='10_Usos_basicos'!$I$25/'12_X'!$B$9 -> 0.11786063 | J10: ='10_Usos_basicos'!$J$25/'12_X'!$B$10 -> 0.030083106 | K10: ='10_Usos_basicos'!$K$25/'12_X'!$B$11 -> 0.00099581251 | L10: ='10_Usos_basicos'!$L$25/'12_X'!$B$12 -> 0.01437951 | M10: ='10_Usos_basicos'!$M$25/'12_X'!$B$13 -> 0.013629963
A11: 09 - Atividades financeiras, de seguros e serviços relacionados | B11: ='10_Usos_basicos'!$B$26/'12_X'!$B$2 -> 0.0064443022 | C11: ='10_Usos_basicos'!$C$26/'12_X'!$B$3 -> 0.013061957 | D11: ='10_Usos_basicos'!$D$26/'12_X'!$B$4 -> 0.0084443488 | E11: ='10_Usos_basicos'!$E$26/'12_X'!$B$5 -> 0.012016313 | F11: ='10_Usos_basicos'!$F$26/'12_X'!$B$6 -> 0.0063732589 | G11: ='10_Usos_basicos'!$G$26/'12_X'!$B$7 -> 0.00929979 | H11: ='10_Usos_basicos'!$H$26/'12_X'!$B$8 -> 0.010074557 | I11: ='10_Usos_basicos'!$I$26/'12_X'!$B$9 -> 0.016871217 | J11: ='10_Usos_basicos'!$J$26/'12_X'!$B$10 -> 0.058602263 | K11: ='10_Usos_basicos'!$K$26/'12_X'!$B$11 -> 0.014295225 | L11: ='10_Usos_basicos'!$L$26/'12_X'!$B$12 -> 0.0058590512 | M11: ='10_Usos_basicos'!$M$26/'12_X'!$B$13 -> 0.01282345
A12: 10 - Atividades imobiliárias | B12: ='10_Usos_basicos'!$B$27/'12_X'!$B$2 -> 2.9466015e-05 | C12: ='10_Usos_basicos'!$C$27/'12_X'!$B$3 -> 0.0020749156 | D12: ='10_Usos_basicos'!$D$27/'12_X'!$B$4 -> 0.0025466835 | E12: ='10_Usos_basicos'!$E$27/'12_X'!$B$5 -> 0.0054175439 | F12: ='10_Usos_basicos'!$F$27/'12_X'!$B$6 -> 0.0022665325 | G12: ='10_Usos_basicos'!$G$27/'12_X'!$B$7 -> 0.035458439 | H12: ='10_Usos_basicos'!$H$27/'12_X'!$B$8 -> 0.016237022 | I12: ='10_Usos_basicos'!$I$27/'12_X'!$B$9 -> 0.016220098 | J12: ='10_Usos_basicos'!$J$27/'12_X'!$B$10 -> 0.0091978139 | K12: ='10_Usos_basicos'!$K$27/'12_X'!$B$11 -> 0.0029810169 | L12: ='10_Usos_basicos'!$L$27/'12_X'!$B$12 -> 0.01893754 | M12: ='10_Usos_basicos'!$M$27/'12_X'!$B$13 -> 0.002552119
A13: 11 - Outras atividades de serviços | B13: ='10_Usos_basicos'!$B$28/'12_X'!$B$2 -> 0.0035287603 | C13: ='10_Usos_basicos'!$C$28/'12_X'!$B$3 -> 0.037972336 | D13: ='10_Usos_basicos'!$D$28/'12_X'!$B$4 -> 0.035903978 | E13: ='10_Usos_basicos'!$E$28/'12_X'!$B$5 -> 0.044590334 | F13: ='10_Usos_basicos'!$F$28/'12_X'!$B$6 -> 0.019992644 | G13: ='10_Usos_basicos'!$G$28/'12_X'!$B$7 -> 0.063983797 | H13: ='10_Usos_basicos'!$H$28/'12_X'!$B$8 -> 0.044316524 | I13: ='10_Usos_basicos'!$I$28/'12_X'!$B$9 -> 0.14502919 | J13: ='10_Usos_basicos'!$J$28/'12_X'!$B$10 -> 0.070981413 | K13: ='10_Usos_basicos'!$K$28/'12_X'!$B$11 -> 0.0055072298 | L13: ='10_Usos_basicos'!$L$28/'12_X'!$B$12 -> 0.060313741 | M13: ='10_Usos_basicos'!$M$28/'12_X'!$B$13 -> 0.051707569
A14: 12 - Administração, defesa, saúde e educação públicas e seguridade social | B14: ='10_Usos_basicos'!$B$29/'12_X'!$B$2 -> 0 | C14: ='10_Usos_basicos'!$C$29/'12_X'!$B$3 -> 0 | D14: ='10_Usos_basicos'!$D$29/'12_X'!$B$4 -> 0 | E14: ='10_Usos_basicos'!$E$29/'12_X'!$B$5 -> 0 | F14: ='10_Usos_basicos'!$F$29/'12_X'!$B$6 -> 0 | G14: ='10_Usos_basicos'!$G$29/'12_X'!$B$7 -> 0 | H14: ='10_Usos_basicos'!$H$29/'12_X'!$B$8 -> 0 | I14: ='10_Usos_basicos'!$I$29/'12_X'!$B$9 -> 0 | J14: ='10_Usos_basicos'!$J$29/'12_X'!$B$10 -> 0 | K14: ='10_Usos_basicos'!$K$29/'12_X'!$B$11 -> 0 | L14: ='10_Usos_basicos'!$L$29/'12_X'!$B$12 -> 0 | M14: ='10_Usos_basicos'!$M$29/'12_X'!$B$13 -> 0

Sheet 14_A
A1: ETAPA 16b - matriz tecnica A = D x Bn (atividade x atividade)
A2: Atividade \ Atividade | B2: 01 - Agropecuária | C2: 02 - Indústrias extrativas | D2: 03 - Indústrias de transformação | E2: 04 - Eletricidade e gás, água, esgoto e gestão de resíduos | F2: 05 - Construção | G2: 06 - Comércio | H2: 07 - Transporte, armazenagem e correio | I2: 08 - Informação e comunicação | J2: 09 - Atividades financeiras, de seguros e serviços relacionados | K2: 10 - Atividades imobiliárias | L2: 11 - Outras atividades de serviços | M2: 12 - Administração, defesa, saúde e educação públicas e seguridade social
A3: 01 - Agropecuária | B3: {=MMULT('11_D'!$B$3:$M$3,'13_Bn'!$B$3:$B$14)} -> 0.034209404 | C3: {=MMULT('11_D'!$B$3:$M$3,'13_Bn'!$C$3:$C$14)} -> 0.0013467204 | D3: {=MMULT('11_D'!$B$3:$M$3,'13_Bn'!$D$3:$D$14)} -> 0.14728885 | E3: {=MMULT('11_D'!$B$3:$M$3,'13_Bn'!$E$3:$E$14)} -> 0.00071937587 | F3: {=MMULT('11_D'!$B$3:$M$3,'13_Bn'!$F$3:$F$14)} -> 0.0043409301 | G3: {=MMULT('11_D'!$B$3:$M$3,'13_Bn'!$G$3:$G$14)} -> 0.0051958999 | H3: {=MMULT('11_D'!$B$3:$M$3,'13_Bn'!$H$3:$H$14)} -> 0.0012836108 | I3: {=MMULT('11_D'!$B$3:$M$3,'13_Bn'!$I$3:$I$14)} -> 0.00045956523 | J3: {=MMULT('11_D'!$B$3:$M$3,'13_Bn'!$J$3:$J$14)} -> 8.6551621e-05 | K3: {=MMULT('11_D'!$B$3:$M$3,'13_Bn'!$K$3:$K$14)} -> 9.3720605e-05 | L3: {=MMULT('11_D'!$B$3:$M$3,'13_Bn'!$L$3:$L$14)} -> 0.0058695313 | M3: {=MMULT('11_D'!$B$3:$M$3,'13_Bn'!$M$3:$M$14)} -> 0.0021420397
A4: 02 - Indústrias extrativas | B4: {=MMULT('11_D'!$B$4:$M$4,'13_Bn'!$B$3:$B$14)} -> 0.00058600589 | C4: {=MMULT('11_D'!$B$4:$M$4,'13_Bn'!$C$3:$C$14)} -> 0.011266753 | D4: {=MMULT('11_D'!$B$4:$M$4,'13_Bn'!$D$3:$D$14)} -> 0.0087620949 | E4: {=MMULT('11_D'!$B$4:$M$4,'13_Bn'!$E$3:$E$14)} -> 0.00047714074 | F4: {=MMULT('11_D'!$B$4:$M$4,'13_Bn'!$F$3:$F$14)} -> 0.0084762879 | G4: {=MMULT('11_D'!$B$4:$M$4,'13_Bn'!$G$3:$G$14)} -> 3.9740364e-05 | H4: {=MMULT('11_D'!$B$4:$M$4,'13_Bn'!$H$3:$H$14)} -> 3.5681004e-05 | I4: {=MMULT('11_D'!$B$4:$M$4,'13_Bn'!$I$3:$I$14)} -> 6.1440232e-06 | J4: {=MMULT('11_D'!$B$4:$M$4,'13_Bn'!$J$3:$J$14)} -> 2.4205788e-06 | K4: {=MMULT('11_D'!$B$4:$M$4,'13_Bn'!$K$3:$K$14)} -> 0.00069682277 | L4: {=MMULT('11_D'!$B$4:$M$4,'13_Bn'!$L$3:$L$14)} -> 3.6832114e-05 | M4: {=MMULT('11_D'!$B$4:$M$4,'13_Bn'!$M$3:$M$14)} -> 5.461966e-05
A5: 03 - Indústrias de transformação | B5: {=MMULT('11_D'!$B$5:$M$5,'13_Bn'!$B$3:$B$14)} -> 0.052129959 | C5: {=MMULT('11_D'!$B$5:$M$5,'13_Bn'!$C$3:$C$14)} -> 0.04864479 | D5: {=MMULT('11_D'!$B$5:$M$5,'13_Bn'!$D$3:$D$14)} -> 0.075617267 | E5: {=MMULT('11_D'!$B$5:$M$5,'13_Bn'!$E$3:$E$14)} -> 0.017416047 | F5: {=MMULT('11_D'!$B$5:$M$5,'13_Bn'!$F$3:$F$14)} -> 0.060520638 | G5: {=MMULT('11_D'!$B$5:$M$5,'13_Bn'!$G$3:$G$14)} -> 0.01599534 | H5: {=MMULT('11_D'!$B$5:$M$5,'13_Bn'!$H$3:$H$14)} -> 0.049303719 | I5: {=MMULT('11_D'!$B$5:$M$5,'13_Bn'!$I$3:$I$14)} -> 0.007184411 | J5: {=MMULT('11_D'!$B$5:$M$5,'13_Bn'!$J$3:$J$14)} -> 0.0024284344 | K5: {=MMULT('11_D'!$B$5:$M$5,'13_Bn'!$K$3:$K$14)} -> 0.0022976966 | L5: {=MMULT('11_D'!$B$5:$M$5,'13_Bn'!$L$3:$L$14)} -> 0.021908986 | M5: {=MMULT('11_D'!$B$5:$M$5,'13_Bn'!$M$3:$M$14)} -> 0.008408771
A6: 04 - Eletricidade e gás, água, esgoto e gestão de resíduos | B6: {=MMULT('11_D'!$B$6:$M$6,'13_Bn'!$B$3:$B$14)} -> 0.018044666 | C6: {=MMULT('11_D'!$B$6:$M$6,'13_Bn'!$C$3:$C$14)} -> 0.03334497 | D6: {=MMULT('11_D'!$B$6:$M$6,'13_Bn'!$D$3:$D$14)} -> 0.014946273 | E6: {=MMULT('11_D'!$B$6:$M$6,'13_Bn'!$E$3:$E$14)} -> 0.32090347 | F6: {=MMULT('11_D'!$B$6:$M$6,'13_Bn'!$F$3:$F$14)} -> 0.0017410359 | G6: {=MMULT('11_D'!$B$6:$M$6,'13_Bn'!$G$3:$G$14)} -> 0.023247969 | H6: {=MMULT('11_D'!$B$6:$M$6,'13_Bn'!$H$3:$H$14)} -> 0.0089431044 | I6: {=MMULT('11_D'!$B$6:$M$6,'13_Bn'!$I$3:$I$14)} -> 0.013175918 | J6: {=MMULT('11_D'!$B$6:$M$6,'13_Bn'!$J$3:$J$14)} -> 0.0050093769 | K6: {=MMULT('11_D'!$B$6:$M$6,'13_Bn'!$K$3:$K$14)} -> 0.0016068621 | L6: {=MMULT('11_D'!$B$6:$M$6,'13_Bn'!$L$3:$L$14)} -> 0.020387182 | M6: {=MMULT('11_D'!$B$6:$M$6,'13_Bn'!$M$3:$M$14)} -> 0.017276613
A7: 05 - Construção | B7: {=MMULT('11_D'!$B$7:$M$7,'13_Bn'!$B$3:$B$14)} -> 0.00046976326 | C7: {=MMULT('11_D'!$B$7:$M$7,'13_Bn'!$C$3:$C$14)} -> 7.6357753e-05 | D7: {=MMULT('11_D'!$B$7:$M$7,'13_Bn'!$D$3:$D$14)} -> 0.00027419627 | E7: {=MMULT('11_D'!$B$7:$M$7,'13_Bn'!$E$3:$E$14)} -> 0.018019869 | F7: {=MMULT('11_D'!$B$7:$M$7,'13_Bn'!$F$3:$F$14)} -> 0.11516989 | G7: {=MMULT('11_D'!$B$7:$M$7,'13_Bn'!$G$3:$G$14)} -> 0.0011012218 | H7: {=MMULT('11_D'!$B$7:$M$7,'13_Bn'!$H$3:$H$14)} -> 0.0029637038 | I7: {=MMULT('11_D'!$B$7:$M$7,'13_Bn'!$I$3:$I$14)} -> 0.021337798 | J7: {=MMULT('11_D'!$B$7:$M$7,'13_Bn'!$J$3:$J$14)} -> 0.0019812844 | K7: {=MMULT('11_D'!$B$7:$M$7,'13_Bn'!$K$3:$K$14)} -> 0.002442252 | L7: {=MMULT('11_D'!$B$7:$M$7,'13_Bn'!$L$3:$L$14)} -> 0.0024638438 | M7: {=MMULT('11_D'!$B$7:$M$7,'13_Bn'!$M$3:$M$14)} -> 0.017236046
A8: 06 - Comércio | B8: {=MMULT('11_D'!$B$8:$M$8,'13_Bn'!$B$3:$B$14)} -> 0.069864206 | C8: {=MMULT('11_D'!$B$8:$M$8,'13_Bn'!$C$3:$C$14)} -> 0.063497162 | D8: {=MMULT('11_D'!$B$8:$M$8,'13_Bn'!$D$3:$D$14)} -> 0.1021693 | E8: {=MMULT('11_D'!$B$8:$M$8,'13_Bn'!$E$3:$E$14)} -> 0.019844795 | F8: {=MMULT('11_D'!$B$8:$M$8,'13_Bn'!$F$3:$F$14)} -> 0.078115506 | G8: {=MMULT('11_D'!$B$8:$M$8,'13_Bn'!$G$3:$G$14)} -> 0.012250202 | H8: {=MMULT('11_D'!$B$8:$M$8,'13_Bn'!$H$3:$H$14)} -> 0.039584398 | I8: {=MMULT('11_D'!$B$8:$M$8,'13_Bn'!$I$3:$I$14)} -> -0.004747134 | J8: {=MMULT('11_D'!$B$8:$M$8,'13_Bn'!$J$3:$J$14)} -> 0.0051368555 | K8: {=MMULT('11_D'!$B$8:$M$8,'13_Bn'!$K$3:$K$14)} -> 0.003120033 | L8: {=MMULT('11_D'!$B$8:$M$8,'13_Bn'!$L$3:$L$14)} -> 0.028121186 | M8: {=MMULT('11_D'!$B$8:$M$8,'13_Bn'!$M$3:$M$14)} -> 0.0084264739
A9: 07 - Transporte, armazenagem e correio | B9: {=MMULT('11_D'!$B$9:$M$9,'13_Bn'!$B$3:$B$14)} -> 0.01340964 | C9: {=MMULT('11_D'!$B$9:$M$9,'13_Bn'!$C$3:$C$14)} -> 0.025767529 | D9: {=MMULT('11_D'!$B$9:$M$9,'13_Bn'!$D$3:$D$14)} -> 0.042464982 | E9: {=MMULT('11_D'!$B$9:$M$9,'13_Bn'!$E$3:$E$14)} -> 0.0051229754 | F9: {=MMULT('11_D'!$B$9:$M$9,'13_Bn'!$F$3:$F$14)} -> 0.0096986199 | G9: {=MMULT('11_D'!$B$9:$M$9,'13_Bn'!$G$3:$G$14)} -> 0.033749335 | H9: {=MMULT('11_D'!$B$9:$M$9,'13_Bn'!$H$3:$H$14)} -> 0.080520234 | I9: {=MMULT('11_D'!$B$9:$M$9,'13_Bn'!$I$3:$I$14)} -> 0.0066339174 | J9: {=MMULT('11_D'!$B$9:$M$9,'13_Bn'!$J$3:$J$14)} -> 0.0087720413 | K9: {=MMULT('11_D'!$B$9:$M$9,'13_Bn'!$K$3:$K$14)} -> 0.0006673206 | L9: {=MMULT('11_D'!$B$9:$M$9,'13_Bn'!$L$3:$L$14)} -> 0.011184922 | M9: {=MMULT('11_D'!$B$9:$M$9,'13_Bn'!$M$3:$M$14)} -> 0.0079558651
A10: 08 - Informação e comunicação | B10: {=MMULT('11_D'!$B$10:$M$10,'13_Bn'!$B$3:$B$14)} -> 5.4004743e-05 | C10: {=MMULT('11_D'!$B$10:$M$10,'13_Bn'!$C$3:$C$14)} -> 0.00072387138 | D10: {=MMULT('11_D'!$B$10:$M$10,'13_Bn'!$D$3:$D$14)} -> 0.0039847431 | E10: {=MMULT('11_D'!$B$10:$M$10,'13_Bn'!$E$3:$E$14)} -> 0.0066897098 | F10: {=MMULT('11_D'!$B$10:$M$10,'13_Bn'!$F$3:$F$14)} -> 0.0019524447 | G10: {=MMULT('11_D'!$B$10:$M$10,'13_Bn'!$G$3:$G$14)} -> 0.010313802 | H10: {=MMULT('11_D'!$B$10:$M$10,'13_Bn'!$H$3:$H$14)} -> 0.0079712715 | I10: {=MMULT('11_D'!$B$10:$M$10,'13_Bn'!$I$3:$I$14)} -> 0.1169378 | J10: {=MMULT('11_D'!$B$10:$M$10,'13_Bn'!$J$3:$J$14)} -> 0.029848106 | K10: {=MMULT('11_D'!$B$10:$M$10,'13_Bn'!$K$3:$K$14)} -> 0.00098815747 | L10: {=MMULT('11_D'!$B$10:$M$10,'13_Bn'!$L$3:$L$14)} -> 0.014267958 | M10: {=MMULT('11_D'!$B$10:$M$10,'13_Bn'!$M$3:$M$14)} -> 0.013523655
A11: 09 - Atividades financeiras, de seguros e serviços relacionados | B11: {=MMULT('11_D'!$B$11:$M$11,'13_Bn'!$B$3:$B$14)} -> 0.0064471928 | C11: {=MMULT('11_D'!$B$11:$M$11,'13_Bn'!$C$3:$C$14)} -> 0.013110892 | D11: {=MMULT('11_D'!$B$11:$M$11,'13_Bn'!$D$3:$D$14)} -> 0.0085065249 | E11: {=MMULT('11_D'!$B$11:$M$11,'13_Bn'!$E$3:$E$14)} -> 0.012121178 | F11: {=MMULT('11_D'!$B$11:$M$11,'13_Bn'!$F$3:$F$14)} -> 0.0064154581 | G11: {=MMULT('11_D'!$B$11:$M$11,'13_Bn'!$G$3:$G$14)} -> 0.0097263602 | H11: {=MMULT('11_D'!$B$11:$M$11,'13_Bn'!$H$3:$H$14)} -> 0.010290208 | I11: {=MMULT('11_D'!$B$11:$M$11,'13_Bn'!$I$3:$I$14)} -> 0.017490327 | J11: {=MMULT('11_D'!$B$11:$M$11,'13_Bn'!$J$3:$J$14)} -> 0.05883375 | K11: {=MMULT('11_D'!$B$11:$M$11,'13_Bn'!$K$3:$K$14)} -> 0.014331547 | L11: {=MMULT('11_D'!$B$11:$M$11,'13_Bn'!$L$3:$L$14)} -> 0.0061317635 | M11: {=MMULT('11_D'!$B$11:$M$11,'13_Bn'!$M$3:$M$14)} -> 0.012925832
A12: 10 - Atividades imobiliárias | B12: {=MMULT('11_D'!$B$12:$M$12,'13_Bn'!$B$3:$B$14)} -> 2.7862596e-05 | C12: {=MMULT('11_D'!$B$12:$M$12,'13_Bn'!$C$3:$C$14)} -> 0.0019620073 | D12: {=MMULT('11_D'!$B$12:$M$12,'13_Bn'!$D$3:$D$14)} -> 0.0024081035 | E12: {=MMULT('11_D'!$B$12:$M$12,'13_Bn'!$E$3:$E$14)} -> 0.0051227436 | F12: {=MMULT('11_D'!$B$12:$M$12,'13_Bn'!$F$3:$F$14)} -> 0.0021431972 | G12: {=MMULT('11_D'!$B$12:$M$12,'13_Bn'!$G$3:$G$14)} -> 0.033528937 | H12: {=MMULT('11_D'!$B$12:$M$12,'13_Bn'!$H$3:$H$14)} -> 0.015353471 | I12: {=MMULT('11_D'!$B$12:$M$12,'13_Bn'!$I$3:$I$14)} -> 0.015337467 | J12: {=MMULT('11_D'!$B$12:$M$12,'13_Bn'!$J$3:$J$14)} -> 0.0086973069 | K12: {=MMULT('11_D'!$B$12:$M$12,'13_Bn'!$K$3:$K$14)} -> 0.0028188023 | L12: {=MMULT('11_D'!$B$12:$M$12,'13_Bn'!$L$3:$L$14)} -> 0.017907037 | M12: {=MMULT('11_D'!$B$12:$M$12,'13_Bn'!$M$3:$M$14)} -> 0.0024132433
A13: 11 - Outras atividades de serviços | B13: {=MMULT('11_D'!$B$13:$M$13,'13_Bn'!$B$3:$B$14)} -> 0.0035323531 | C13: {=MMULT('11_D'!$B$13:$M$13,'13_Bn'!$C$3:$C$14)} -> 0.03644619 | D13: {=MMULT('11_D'!$B$13:$M$13,'13_Bn'!$D$3:$D$14)} -> 0.034563079 | E13: {=MMULT('11_D'!$B$13:$M$13,'13_Bn'!$E$3:$E$14)} -> 0.042701834 | F13: {=MMULT('11_D'!$B$13:$M$13,'13_Bn'!$F$3:$F$14)} -> 0.019303555 | G13: {=MMULT('11_D'!$B$13:$M$13,'13_Bn'!$G$3:$G$14)} -> 0.061476275 | H13: {=MMULT('11_D'!$B$13:$M$13,'13_Bn'!$H$3:$H$14)} -> 0.042587936 | I13: {=MMULT('11_D'!$B$13:$M$13,'13_Bn'!$I$3:$I$14)} -> 0.13876403 | J13: {=MMULT('11_D'!$B$13:$M$13,'13_Bn'!$J$3:$J$14)} -> 0.067925801 | K13: {=MMULT('11_D'!$B$13:$M$13,'13_Bn'!$K$3:$K$14)} -> 0.0052952638 | L13: {=MMULT('11_D'!$B$13:$M$13,'13_Bn'!$L$3:$L$14)} -> 0.057863107 | M13: {=MMULT('11_D'!$B$13:$M$13,'13_Bn'!$M$3:$M$14)} -> 0.049454421
A14: 12 - Administração, defesa, saúde e educação públicas e seguridade social | B14: {=MMULT('11_D'!$B$14:$M$14,'13_Bn'!$B$3:$B$14)} -> 0.00031724988 | C14: {=MMULT('11_D'!$B$14:$M$14,'13_Bn'!$C$3:$C$14)} -> 0.0013899256 | D14: {=MMULT('11_D'!$B$14:$M$14,'13_Bn'!$D$3:$D$14)} -> 0.0016458622 | E14: {=MMULT('11_D'!$B$14:$M$14,'13_Bn'!$E$3:$E$14)} -> 0.0019526667 | F14: {=MMULT('11_D'!$B$14:$M$14,'13_Bn'!$F$3:$F$14)} -> 0.00069902044 | G14: {=MMULT('11_D'!$B$14:$M$14,'13_Bn'!$G$3:$G$14)} -> 0.0022358266 | H14: {=MMULT('11_D'!$B$14:$M$14,'13_Bn'!$H$3:$H$14)} -> 0.0019829122 | I14: {=MMULT('11_D'!$B$14:$M$14,'13_Bn'!$I$3:$I$14)} -> 0.0044816533 | J14: {=MMULT('11_D'!$B$14:$M$14,'13_Bn'!$J$3:$J$14)} -> 0.0021891125 | K14: {=MMULT('11_D'!$B$14:$M$14,'13_Bn'!$K$3:$K$14)} -> 0.00017457314 | L14: {=MMULT('11_D'!$B$14:$M$14,'13_Bn'!$L$3:$L$14)} -> 0.0019355911 | M14: {=MMULT('11_D'!$B$14:$M$14,'13_Bn'!$M$3:$M$14)} -> 0.0016148585

Sheet 15_Z
A1: ETAPA 16c - fluxos intermediarios Z = A x diag(X)
A2: Atividade \ Atividade | B2: 01 - Agropecuária | C2: 02 - Indústrias extrativas | D2: 03 - Indústrias de transformação | E2: 04 - Eletricidade e gás, água, esgoto e gestão de resíduos | F2: 05 - Construção | G2: 06 - Comércio | H2: 07 - Transporte, armazenagem e correio | I2: 08 - Informação e comunicação | J2: 09 - Atividades financeiras, de seguros e serviços relacionados | K2: 10 - Atividades imobiliárias | L2: 11 - Outras atividades de serviços | M2: 12 - Administração, defesa, saúde e educação públicas e seguridade social | N2: Soma da linha
A3: 01 - Agropecuária | B3: ='14_A'!$B$3*'12_X'!$B$2 -> 260.29191 | C3: ='14_A'!$C$3*'12_X'!$B$3 -> 0.28323143 | D3: ='14_A'!$D$3*'12_X'!$B$4 -> 1199.7569 | E3: ='14_A'!$E$3*'12_X'!$B$5 -> 2.9436704 | F3: ='14_A'!$F$3*'12_X'!$B$6 -> 24.774086 | G3: ='14_A'!$G$3*'12_X'!$B$7 -> 51.709725 | H3: ='14_A'!$H$3*'12_X'!$B$8 -> 3.4061317 | I3: ='14_A'!$I$3*'12_X'!$B$9 -> 0.68371868 | J3: ='14_A'!$J$3*'12_X'!$B$10 -> 0.20324052 | K3: ='14_A'!$K$3*'12_X'!$B$11 -> 0.37757537 | L3: ='14_A'!$L$3*'12_X'!$B$12 -> 56.047827 | M3: ='14_A'!$M$3*'12_X'!$B$13 -> 42.096146 | N3: =SUM(B3:M3) -> 1642.5741
A4: 02 - Indústrias extrativas | B4: ='14_A'!$B$4*'12_X'!$B$2 -> 4.4587913 | C4: ='14_A'!$C$4*'12_X'!$B$3 -> 2.369533 | D4: ='14_A'!$D$4*'12_X'!$B$4 -> 71.372569 | E4: ='14_A'!$E$4*'12_X'!$B$5 -> 1.9524495 | F4: ='14_A'!$F$4*'12_X'!$B$6 -> 48.374952 | G4: ='14_A'!$G$4*'12_X'!$B$7 -> 0.39549709 | H4: ='14_A'!$H$4*'12_X'!$B$8 -> 0.094681502 | I4: ='14_A'!$I$4*'12_X'!$B$9 -> 0.0091407772 | J4: ='14_A'!$J$4*'12_X'!$B$10 -> 0.0056840033 | K4: ='14_A'!$K$4*'12_X'!$B$11 -> 2.8073135 | L4: ='14_A'!$L$4*'12_X'!$B$12 -> 0.3517078 | M4: ='14_A'!$M$4*'12_X'!$B$13 -> 1.0734055 | N4: =SUM(B4:M4) -> 133.26572
A5: 03 - Indústrias de transformação | B5: ='14_A'!$B$5*'12_X'!$B$2 -> 396.64552 | C5: ='14_A'!$C$5*'12_X'!$B$3 -> 10.230582 | D5: ='14_A'!$D$5*'12_X'!$B$4 -> 615.94843 | E5: ='14_A'!$E$5*'12_X'!$B$5 -> 71.266086 | F5: ='14_A'!$F$5*'12_X'!$B$6 -> 345.39683 | G5: ='14_A'!$G$5*'12_X'!$B$7 -> 159.18602 | H5: ='14_A'!$H$5*'12_X'!$B$8 -> 130.83012 | I5: ='14_A'!$I$5*'12_X'!$B$9 -> 10.688615 | J5: ='14_A'!$J$5*'12_X'!$B$10 -> 5.7024496 | K5: ='14_A'!$K$5*'12_X'!$B$11 -> 9.256808 | L5: ='14_A'!$L$5*'12_X'!$B$12 -> 209.20768 | M5: ='14_A'!$M$5*'12_X'!$B$13 -> 165.25224 | N5: =SUM(B5:M5) -> 2129.6114
A6: 04 - Eletricidade e gás, água, esgoto e gestão de resíduos | B6: ='14_A'!$B$6*'12_X'!$B$2 -> 137.29793 | C6: ='14_A'!$C$6*'12_X'!$B$3 -> 7.0128465 | D6: ='14_A'!$D$6*'12_X'!$B$4 -> 121.74645 | E6: ='14_A'!$E$6*'12_X'!$B$5 -> 1313.13 | F6: ='14_A'!$F$6*'12_X'!$B$6 -> 9.9362515 | G6: ='14_A'!$G$6*'12_X'!$B$7 -> 231.36436 | H6: ='14_A'!$H$6*'12_X'!$B$8 -> 23.731018 | I6: ='14_A'!$I$6*'12_X'!$B$9 -> 19.602487 | J6: ='14_A'!$J$6*'12_X'!$B$10 -> 11.763019 | K6: ='14_A'!$K$6*'12_X'!$B$11 -> 6.4736196 | L6: ='14_A'!$L$6*'12_X'!$B$12 -> 194.67606 | M6: ='14_A'!$M$6*'12_X'!$B$13 -> 339.5263 | N6: =SUM(B6:M6) -> 2416.2604
A7: 05 - Construção | B7: ='14_A'!$B$7*'12_X'!$B$2 -> 3.5743265 | C7: ='14_A'!$C$7*'12_X'!$B$3 -> 0.01605895 | D7: ='14_A'!$D$7*'12_X'!$B$4 -> 2.2334946 | E7: ='14_A'!$E$7*'12_X'!$B$5 -> 73.73691 | F7: ='14_A'!$F$7*'12_X'!$B$6 -> 657.28514 | G7: ='14_A'!$G$7*'12_X'!$B$7 -> 10.959387 | H7: ='14_A'!$H$7*'12_X'!$B$8 -> 7.8643506 | I7: ='14_A'!$I$7*'12_X'!$B$9 -> 31.745332 | J7: ='14_A'!$J$7*'12_X'!$B$10 -> 4.652452 | K7: ='14_A'!$K$7*'12_X'!$B$11 -> 9.8391833 | L7: ='14_A'!$L$7*'12_X'!$B$12 -> 23.527107 | M7: ='14_A'!$M$7*'12_X'!$B$13 -> 338.72907 | N7: =SUM(B7:M7) -> 1164.1628
A8: 06 - Comércio | B8: ='14_A'!$B$8*'12_X'!$B$2 -> 531.58154 | C8: ='14_A'!$C$8*'12_X'!$B$3 -> 13.354214 | D8: ='14_A'!$D$8*'12_X'!$B$4 -> 832.23085 | E8: ='14_A'!$E$8*'12_X'!$B$5 -> 81.204469 | F8: ='14_A'!$F$8*'12_X'!$B$6 -> 445.81235 | G8: ='14_A'!$G$8*'12_X'!$B$7 -> 121.91432 | H8: ='14_A'!$H$8*'12_X'!$B$8 -> 105.03937 | I8: ='14_A'!$I$8*'12_X'!$B$9 -> -7.0625538 | J8: ='14_A'!$J$8*'12_X'!$B$10 -> 12.062364 | K8: ='14_A'!$K$8*'12_X'!$B$11 -> 12.569783 | L8: ='14_A'!$L$8*'12_X'!$B$12 -> 268.52763 | M8: ='14_A'!$M$8*'12_X'!$B$13 -> 165.60014 | N8: =SUM(B8:M8) -> 2582.8345
A9: 07 - Transporte, armazenagem e correio | B9: ='14_A'!$B$9*'12_X'!$B$2 -> 102.03103 | C9: ='14_A'!$C$9*'12_X'!$B$3 -> 5.4192199 | D9: ='14_A'!$D$9*'12_X'!$B$4 -> 345.903 | E9: ='14_A'!$E$9*'12_X'!$B$5 -> 20.963104 | F9: ='14_A'!$F$9*'12_X'!$B$6 -> 55.350912 | G9: ='14_A'!$G$9*'12_X'!$B$7 -> 335.87422 | H9: ='14_A'!$H$9*'12_X'!$B$8 -> 213.66486 | I9: ='14_A'!$I$9*'12_X'!$B$9 -> 9.8696179 | J9: ='14_A'!$J$9*'12_X'!$B$10 -> 20.598507 | K9: ='14_A'!$K$9*'12_X'!$B$11 -> 2.6884571 | L9: ='14_A'!$L$9*'12_X'!$B$12 -> 106.80419 | M9: ='14_A'!$M$9*'12_X'!$B$13 -> 156.35157 | N9: =SUM(B9:M9) -> 1375.5187
